Workbook
Name Add_on_Promotion: '[1]Dropdown list'!$H$2:$H$4
Name Campaign_Tiering: 'Dropdown list'!$C$2:$C$7
Name Combobuy: 'Dropdown list'!$Q$2:$Q$6
Name CPD: 'Dropdown list'!$M$26:$M$28
Name CPD_Brands: 'Dropdown list'!$M$26:$M$28
Name DealCriteria: 'Dropdown list'!$S$2:$S$4
Name FixedPrice: 'Dropdown list'!$R$2:$R$3
Name FlexiComboMechanics: 'Dropdown list'!$L$2:$L$6
Name Freegiftorsample: 'Dropdown list'!$P$2:$P$5
Name LDB: 'Dropdown list'!$Q$26:$Q$29
Name LDB_Brands: 'Dropdown list'!$Q$26:$Q$29
Name LLD: 'Dropdown list'!$P$26:$P$30
Name LLD_Brands: 'Dropdown list'!$P$26:$P$30
Name Member_Group: 'Dropdown list'!$H$2:$H$6
Name MoneyorDiscount: 'Dropdown list'!$N$2:$N$4
Name NA: 'Dropdown list'!$K$2:$K$3
Name Platform: 'Dropdown list'!$B$2:$B$4
Name PPD: 'Dropdown list'!$N$26:$N$27
Name PPD_Brands: 'Dropdown list'!$N$26:$N$27
Name Reward_Setting: '[1]Dropdown list'!$Q$2:$Q$4
Name SIS_Time_slot: 'Dropdown list'!$T$2:$T$8
Name StorewidevsSpecific: 'Dropdown list'!$M$2:$M$4
Name Type_of_Add_on_Promotion: 'Dropdown list'!$J$2:$J$4
Name Type_of_Mechanics: 'Dropdown list'!$I$2:$I$2
Name Type_of_Members: 'Dropdown list'!$G$2:$G$4
Name Voucher_Discount_Type: '[1]Dropdown list'!$R$2:$R$4
Name Voucher_Type: 'Dropdown list'!$D$2:$D$7
Name DealCriteria: '[2]Dropdown list'!$O$2:$O$4
Name NA: '[2]Dropdown list'!$H$2:$H$3
Name SIS_Time_slot: '[2]Dropdown list'!$P$2:$P$8
Name StorewidevsSpecific: '[2]Dropdown list'!$J$2:$J$4
Name DealCriteria: '[2]Dropdown list'!$O$2:$O$4
Name NA: '[2]Dropdown list'!$H$2:$H$3
Name SIS_Time_slot: '[2]Dropdown list'!$P$2:$P$8
Name StorewidevsSpecific: '[2]Dropdown list'!$J$2:$J$4
Name DealCriteria: '[2]Dropdown list'!$O$2:$O$4
Name NA: '[2]Dropdown list'!$H$2:$H$3
Name SIS_Time_slot: '[2]Dropdown list'!$P$2:$P$8
Name StorewidevsSpecific: '[2]Dropdown list'!$J$2:$J$4

Sheet Open Points
A1: S. No. | B1: Query Date | C1: Division | D1: Brand | E1: Archetype | F1: Platform | G1: Query raised by | H1: Role | I1: Query Details | J1: Query Status | K1: Query to | L1: Query Resolution Details | M1: Resolution Date | N1: Learning Shared with the Team Yes/No | O1: Comments if any
B2: (Date) | C2: (CPD/PPD/ LLD/ACD) | E2: (MP) | F2: (Shopee, Lazada) | G2: Name | H2: (E-shop, E-merch, etc.) | I2: (Add details/context to the query) | J2: (Open/Closed) | K2: (Name of the person to whom the query is addressed | L2: (Response recorded from Loreal)
A3: 1 | B3: 45166 | C3: LDB | D3: All | E3: MP | F3: Lazada | G3: Nikhil S | I3: Brand membership --> Type of mechanic Is New Member Voucher same as Welcome - voucher? | J3: Closed | K3: LDB
A4: 2 | B4: 45166 | C4: LDB | D4: All | E4: MP | F4: Lazada | G4: Nikhil S | I4: Brand membership --> Type of mechanic What is the Name of the points reedemable voucher on seller central? | J4: Open | K4: LDB
A5: 3 | B5: 45166 | C5: LDB | D5: All | E5: MP | F5: Lazada | G5: Nikhil S | I5: Brand membership --> Type of mechanic Is member exclusive voucher same as linked member voucher If different How does this work? | J5: Closed | K5: LDB
A6: 4 | B6: 45166 | C6: LDB | D6: All | E6: MP | F6: Lazada | G6: Nikhil S | I6: Brand membership --> Type of mechanic Is new member product offer same as linked member product offer if different How does this work? | J6: Closed | K6: LDB
A7: 5 | B7: 45167 | C7: LDB | D7: All | E7: MP | F7: Lazada | G7: Nikhil S | I7: Do we have to replicate the CEM structure that client has shared? | J7: Closed
A8: 6 | B8: 45167 | C8: LDB | D8: All | E8: MP | F8: Lazada | G8: Nikhil S | I8: Should we replicate the structure of visual template shared by the LDB team as is? Need clarity on how to read the LDB Artwork briefing template shared? | J8: Closed
A9: 7 | B9: 45167 | C9: LDB | D9: All | E9: MP | F9: Lazada | G9: Nikhil S | I9: Flash sale should be separate tab or should be part of the Price change (TB)? | J9: Closed
A10: 8 | B10: 45167 | C10: LDB | D10: All | E10: MP | F10: Lazada | G10: Nikhil S | I10: Add LZD in the tab names | J10: Closed | K10: Nikhil
A11: 9 | B11: 45167 | C11: LDB | D11: All | E11: MP | F11: Lazada | G11: Nikhil S | I11: Do we need a separate tab for VB? | J11: Closed | K11: Nicha
A12: 10 | B12: 45167 | C12: LDB | D12: All | E12: MP | F12: Lazada | G12: Nikhil S | I12: Need to check brand list and make it nested list | J12: Closed | K12: Nikhil
A13: 11 | B13: 45167 | C13: LDB | D13: All | E13: MP | F13: Lazada | G13: Nikhil S | I13: What are the date columns that we need for Launch Requirement GWP sheet | J13: Closed | K13: Hafizah
A14: 12 | B14: 45167 | C14: LDB | D14: All | E14: MP | F14: Lazada | G14: Nikhil S | I14: Is current price an optional field for Price change (TB) - LZD? | J14: Closed | K14: Hafizah
A15: 13 | B15: 45167 | C15: LDB | D15: All | E15: MP | F15: Lazada | G15: Nikhil S | I15: Is order limit same as total number of offers | J15: Closed | K15: Hafizah
A16: 14 | B16: 45167 | C16: LDB | D16: All | E16: MP | F16: Lazada | G16: Nikhil S | I16: Confirm Skin C brand division | J16: Closed | K16: Hafizah
A17: 15 | B17: 45167 | C17: LDB | D17: All | E17: MP | F17: Lazada | G17: Nikhil S | I17: Start time and end time are mandatory for all promotion? | J17: Closed | K17: Hafizah

Sheet Touchless
A1: Fields | B1: Values | C1: Tool Tips | D1: Comments
A2: Archetype | B2: Marketplace | C2: Select Archetype | D2: Archetype selected should be same as the one selected in CXL request flow
A3: Market | B3: Lazada | C3: Select Market
A4: Country | B4: Malaysia | C4: Select Country Based on the Market Selected
A5: Country | C5: Select Country Based on the Market Selected
A6: Division | B6: L’Oréal Luxe Division (LLD) | C6: Select Business Division
A7: Brands | B7: Shu Uemura | C7: Select Brands | D7: Provide atleast one value for the Brands to be included in the Request and provide multiple brands only if applicable or else leave the other brand fields as blank
A8: Brands | C8: Select Brands
A9: Brands | C9: Select Brands
A10: Brands | C10: Select Brands
A11: Brands | C11: Select Brands
A12: Brands | C12: Select Brands
A13: Brands | C13: Select Brands
A14: Brands | C14: Select Brands
A15: Brands | C15: Select Brands
A16: Brands | C16: Select Brands
A17: Request Type | B17: Campaign Management | C17: Select Request Type | D17: Please select relevant Request type if applicable oe else select "Not Applicable"
A18: Request Sub type | B18: Others | C18: Select Reqquest Sub Type | D18: Please select relevant Request Sub type if applicable oe else select "Not Applicable"
A19: Platform | C19: Select Platforms | D19: Provide atleast one value for the Platforms to be included in the Request and provide multiple brands only if applicable or else leave the other Platform fields as blank
A20: Platform | C20: Select Platforms
A21: Platform | C21: Select Platforms
A22: Delivery Date | C22: Enter the Delivery Date and Time | D22: Enter the Delivery date and press enter and then select the relevant time. If Time value is not provided then Default value of "0:00" will be selected
A23: Live Date | C23: Enter the Live Launch Date and Time | D23: Enter the Live date and press enter and then select the relevant time. If Time value is not provided then Default value of "0:00" will be selected

Sheet RGM
A1: BRAND | B1: SKU ID Shopee | C1: PID | D1: SID | E1: Barcode | F1: Product Name | G1: Status | H1: Variant | I1: RGM Code Mapping | J1: PRICE 2024 | K1: BAU | L1: BMO BAU | M1: FS BAU | N1: BRAND | O1: BMO BRAND | P1: FS BRAND | Q1: PLATFORM | R1: BMO PLATFORM | S1: FS PLATFORM | T1: >>> | V1: BAU | W1: BMO BAU | X1: FS BAU | Y1: BRAND | Z1: BMO BRAND | AA1: FS BRAND | AB1: PLATFORM | AC1: BMO PLATFORM | AD1: FS PLATFORM
A2: MYB | B2: 7150202805_ID-13461816795 | C2: =_xlfn.NUMBERVALUE(LEFT(B2,10)) | D2: =_xlfn.NUMBERVALUE(RIGHT(B2,11)) | E2: 8991380011170 | F2: Maybelline Define And Blend Mechanic Eyebrow Pencil Make up - 17gr (Pensil Alis Untuk Alis Tampak Tebal & Natural) | J2: 83900 | K2: 0.2 | L2: 0.25 | M2: 0.26 | N2: 0.21 | O2: 0.26 | P2: 0.27 | Q2: 0.22 | R2: 0.27 | S2: 0.28 | V2: 67200 | W2: 63000 | X2: 62100 | Y2: 66300 | Z2: 62100 | AA2: 61300 | AB2: 65500 | AC2: 61300 | AD2: 60500
A3: MYB | B3: 7150202805_ID-13461594514 | C3: =_xlfn.NUMBERVALUE(LEFT(B3,10)) | D3: =_xlfn.NUMBERVALUE(RIGHT(B3,11)) | E3: 8991380011163 | F3: Maybelline Define And Blend Mechanic Eyebrow Pencil Make up - 17gr (Pensil Alis Untuk Alis Tampak Tebal & Natural) | J3: 83900 | K3: 0.2 | L3: 0.25 | M3: 0.26 | N3: 0.21 | O3: 0.26 | P3: 0.27 | Q3: 0.22 | R3: 0.27 | S3: 0.28 | V3: 67200 | W3: 63000 | X3: 62100 | Y3: 66300 | Z3: 62100 | AA3: 61300 | AB3: 65500 | AC3: 61300 | AD3: 60500
A4: MYB | B4: 7116504754_ID-13418988876 | C4: =_xlfn.NUMBERVALUE(LEFT(B4,10)) | D4: =_xlfn.NUMBERVALUE(RIGHT(B4,11)) | E4: 6902395740353 | F4: Maybelline Line Tattoo High Impact Liner Make Up - 7gr (Eyeliner Hitam Waterproof Tahan Lama Hingga 36 Jam) | J4: 93900 | K4: 0.25 | L4: 0.26 | M4: 0.27 | N4: 0.26 | O4: 0.27 | P4: 0.28 | Q4: 0.27 | R4: 0.28 | S4: 0.29 | V4: 70500 | W4: 69500 | X4: 68600 | Y4: 69500 | Z4: 68600 | AA4: 67700 | AB4: 68600 | AC4: 67700 | AD4: 66700
A5: MYB | B5: 7113822983_ID-13415978652 | C5: =_xlfn.NUMBERVALUE(LEFT(B5,10)) | D5: =_xlfn.NUMBERVALUE(RIGHT(B5,11)) | E5: 6902395830566 | F5: Maybelline Fit Me Fresh Tint - Foundation Tint With Vitamin C And SPF 50 For Fresh & Bright Look Face Make Up | J5: 114900 | K5: 0.15 | L5: 0.16 | M5: 0.19 | N5: 0.2 | O5: 0.205 | P5: 0.22 | Q5: 0.22 | R5: 0.225 | S5: 0.23 | V5: 97700 | W5: 96600 | X5: 93100 | Y5: 92000 | Z5: 91400 | AA5: 89700 | AB5: 89700 | AC5: 89100 | AD5: 88500
A6: MYB | B6: 7113822983_ID-13415978653 | C6: =_xlfn.NUMBERVALUE(LEFT(B6,10)) | D6: =_xlfn.NUMBERVALUE(RIGHT(B6,11)) | E6: 6902395830580 | F6: Maybelline Fit Me Fresh Tint - Foundation Tint With Vitamin C And SPF 50 For Fresh & Bright Look Face Make Up | J6: 114900 | K6: 0.15 | L6: 0.16 | M6: 0.19 | N6: 0.2 | O6: 0.205 | P6: 0.22 | Q6: 0.22 | R6: 0.225 | S6: 0.23 | V6: 97700 | W6: 96600 | X6: 93100 | Y6: 92000 | Z6: 91400 | AA6: 89700 | AB6: 89700 | AC6: 89100 | AD6: 88500
A7: MYB | B7: 7113822983_ID-13415978649 | C7: =_xlfn.NUMBERVALUE(LEFT(B7,10)) | D7: =_xlfn.NUMBERVALUE(RIGHT(B7,11)) | E7: 6902395830528 | F7: Maybelline Fit Me Fresh Tint - Foundation Tint With Vitamin C And SPF 50 For Fresh & Bright Look Face Make Up | J7: 114900 | K7: 0.15 | L7: 0.16 | M7: 0.19 | N7: 0.2 | O7: 0.205 | P7: 0.22 | Q7: 0.22 | R7: 0.225 | S7: 0.23 | V7: 97700 | W7: 96600 | X7: 93100 | Y7: 92000 | Z7: 91400 | AA7: 89700 | AB7: 89700 | AC7: 89100 | AD7: 88500
A8: MYB | B8: 7113822983_ID-13415978650 | C8: =_xlfn.NUMBERVALUE(LEFT(B8,10)) | D8: =_xlfn.NUMBERVALUE(RIGHT(B8,11)) | E8: 6902395830542 | F8: Maybelline Fit Me Fresh Tint - Foundation Tint With Vitamin C And SPF 50 For Fresh & Bright Look Face Make Up | J8: 114900 | K8: 0.15 | L8: 0.16 | M8: 0.19 | N8: 0.2 | O8: 0.205 | P8: 0.22 | Q8: 0.22 | R8: 0.225 | S8: 0.23 | V8: 97700 | W8: 96600 | X8: 93100 | Y8: 92000 | Z8: 91400 | AA8: 89700 | AB8: 89700 | AC8: 89100 | AD8: 88500
A9: MYB | B9: 7113822983_ID-13415978651 | C9: =_xlfn.NUMBERVALUE(LEFT(B9,10)) | D9: =_xlfn.NUMBERVALUE(RIGHT(B9,11)) | E9: 6902395830559 | F9: Maybelline Fit Me Fresh Tint - Foundation Tint With Vitamin C And SPF 50 For Fresh & Bright Look Face Make Up | J9: 114900 | K9: 0.15 | L9: 0.16 | M9: 0.19 | N9: 0.2 | O9: 0.205 | P9: 0.22 | Q9: 0.22 | R9: 0.225 | S9: 0.23 | V9: 97700 | W9: 96600 | X9: 93100 | Y9: 92000 | Z9: 91400 | AA9: 89700 | AB9: 89700 | AC9: 89100 | AD9: 88500
A10: MYB | B10: 7110338143_ID-13411274157 | C10: =_xlfn.NUMBERVALUE(LEFT(B10,10)) | D10: =_xlfn.NUMBERVALUE(RIGHT(B10,11)) | E10: 41554453621 | F10: Maybelline Color Sensational Creamy Mattes Lipstick Make up - 4.2gr (Lipstick Matte Dengan Hasil 2x Lebih Intens) | J10: 88900 | K10: 0.02 | L10: 0.04 | M10: 0.05 | N10: 0.05 | O10: 0.06 | P10: 0.07 | Q10: 0.07 | R10: 0.08 | S10: 0.1 | V10: 87200 | W10: 85400 | X10: 84500 | Y10: 84500 | Z10: 83600 | AA10: 82700 | AB10: 82700 | AC10: 81800 | AD10: 80100
A11: MYB | B11: 7110338143_ID-13411274158 | C11: =_xlfn.NUMBERVALUE(LEFT(B11,10)) | D11: =_xlfn.NUMBERVALUE(RIGHT(B11,11)) | E11: 6902395703891 | F11: Maybelline Color Sensational Creamy Mattes Lipstick Make up - 4.2gr (Lipstick Matte Dengan Hasil 2x Lebih Intens) | J11: 88900 | K11: 0.02 | L11: 0.04 | M11: 0.05 | N11: 0.05 | O11: 0.06 | P11: 0.07 | Q11: 0.07 | R11: 0.08 | S11: 0.1 | V11: 87200 | W11: 85400 | X11: 84500 | Y11: 84500 | Z11: 83600 | AA11: 82700 | AB11: 82700 | AC11: 81800 | AD11: 80100
A12: MYB | B12: 7110338143_ID-13411274159 | C12: =_xlfn.NUMBERVALUE(LEFT(B12,10)) | D12: =_xlfn.NUMBERVALUE(RIGHT(B12,11)) | E12: 6902395780694 | F12: Maybelline Color Sensational Creamy Mattes Lipstick Make up - 4.2gr (Lipstick Matte Dengan Hasil 2x Lebih Intens) | J12: 88900 | K12: 0.02 | L12: 0.04 | M12: 0.05 | N12: 0.05 | O12: 0.06 | P12: 0.07 | Q12: 0.07 | R12: 0.08 | S12: 0.1 | V12: 87200 | W12: 85400 | X12: 84500 | Y12: 84500 | Z12: 83600 | AA12: 82700 | AB12: 82700 | AC12: 81800 | AD12: 80100
A13: MYB | B13: 7110338143_ID-13411274160 | C13: =_xlfn.NUMBERVALUE(LEFT(B13,10)) | D13: =_xlfn.NUMBERVALUE(RIGHT(B13,11)) | E13: 6902395780731 | F13: Maybelline Color Sensational Creamy Mattes Lipstick Make up - 4.2gr (Lipstick Matte Dengan Hasil 2x Lebih Intens) | J13: 88900 | K13: 0.02 | L13: 0.04 | M13: 0.05 | N13: 0.05 | O13: 0.06 | P13: 0.07 | Q13: 0.07 | R13: 0.08 | S13: 0.1 | V13: 87200 | W13: 85400 | X13: 84500 | Y13: 84500 | Z13: 83600 | AA13: 82700 | AB13: 82700 | AC13: 81800 | AD13: 80100
... A15: MYB | B15: 7110338143_ID-13411274162 | C15: =_xlfn.NUMBERVALUE(LEFT(B15,10)) | D15: =_xlfn.NUMBERVALUE(RIGHT(B15,11)) | E15: 6902395780809 | F15: Maybelline Color Sensational Creamy Mattes Lipstick Make up - 4.2gr (Lipstick Matte Dengan Hasil 2x Lebih Intens) | J15: 88900 | K15: 0.02 | L15: 0.04 | M15: 0.05 | N15: 0.05 | O15: 0.06 | P15: 0.07 | Q15: 0.07 | R15: 0.08 | S15: 0.1 | V15: 87200 | W15: 85400 | X15: 84500 | Y15: 84500 | Z15: 83600 | AA15: 82700 | AB15: 82700 | AC15: 81800 | AD15: 80100
A16: MYB | B16: 7109298970_ID-13409868601 | C16: =_xlfn.NUMBERVALUE(LEFT(B16,10)) | D16: =_xlfn.NUMBERVALUE(RIGHT(B16,11)) | E16: 6902395685746 | J16: 0 | K16: 0.15 | L16: 0.17 | M16: 0.2 | N16: 0.2 | O16: 0.21 | P16: 0.22 | Q16: 0.22 | R16: 0.23 | S16: 0.24 | V16: 0 | W16: 0 | X16: 0 | Y16: 0 | Z16: 0 | AA16: 0 | AB16: 0 | AC16: 0 | AD16: 0
A17: MYB | B17: 7109298970_ID-13409868600 | C17: =_xlfn.NUMBERVALUE(LEFT(B17,10)) | D17: =_xlfn.NUMBERVALUE(RIGHT(B17,11)) | E17: 6902395685715 | F17: Maybelline Superstay 24Hr Full Coverage Liquid Foundarion Make Up - 30ml (Foundation Matte Cair Tahan Lama Hingga 24 Jam) | J17: 0 | K17: 0.15 | L17: 0.17 | M17: 0.2 | N17: 0.2 | O17: 0.21 | P17: 0.22 | Q17: 0.22 | R17: 0.23 | S17: 0.24 | V17: 0 | W17: 0 | X17: 0 | Y17: 0 | Z17: 0 | AA17: 0 | AB17: 0 | AC17: 0 | AD17: 0
A18: MYB | B18: 7109298970_ID-13409868599 | C18: =_xlfn.NUMBERVALUE(LEFT(B18,10)) | D18: =_xlfn.NUMBERVALUE(RIGHT(B18,11)) | E18: 6902395685708 | F18: Maybelline Superstay 24Hr Full Coverage Liquid Foundarion Make Up - 30ml (Foundation Matte Cair Tahan Lama Hingga 24 Jam) | J18: 0 | K18: 0.15 | L18: 0.17 | M18: 0.2 | N18: 0.2 | O18: 0.21 | P18: 0.22 | Q18: 0.22 | R18: 0.23 | S18: 0.24 | V18: 0 | W18: 0 | X18: 0 | Y18: 0 | Z18: 0 | AA18: 0 | AB18: 0 | AC18: 0 | AD18: 0
A19: MYB | B19: 7109298817_ID-13409848345 | C19: =_xlfn.NUMBERVALUE(LEFT(B19,10)) | D19: =_xlfn.NUMBERVALUE(RIGHT(B19,11)) | E19: 6902395820222 | F19: Maybelline Fit Me Matte + Poreless Cushion Make Up - 14gr (Coverage instant & tahan lama hingga 20 jam) | J19: 265900 | K19: 0.27 | L19: 0.28 | M19: 0.3 | N19: 0.3 | O19: 0.31 | P19: 0.32 | Q19: 0.32 | R19: 0.33 | S19: 0.34 | V19: 194200 | W19: 191500 | X19: 186200 | Y19: 186200 | Z19: 183500 | AA19: 180900 | AB19: 180900 | AC19: 178200 | AD19: 175500
A20: MYB | B20: 7109298817_ID-13409848347 | C20: =_xlfn.NUMBERVALUE(LEFT(B20,10)) | D20: =_xlfn.NUMBERVALUE(RIGHT(B20,11)) | E20: 6902395820277 | F20: Maybelline Fit Me Matte + Poreless Cushion Make Up - 14gr (Coverage instant & tahan lama hingga 20 jam) | J20: 265900 | K20: 0.27 | L20: 0.28 | M20: 0.3 | N20: 0.3 | O20: 0.31 | P20: 0.32 | Q20: 0.32 | R20: 0.33 | S20: 0.34 | V20: 194200 | W20: 191500 | X20: 186200 | Y20: 186200 | Z20: 183500 | AA20: 180900 | AB20: 180900 | AC20: 178200 | AD20: 175500
A21: MYB | B21: 7109298817_ID-13409848346 | C21: =_xlfn.NUMBERVALUE(LEFT(B21,10)) | D21: =_xlfn.NUMBERVALUE(RIGHT(B21,11)) | E21: 6902395820253 | F21: Maybelline Fit Me Matte + Poreless Cushion Make Up - 14gr (Coverage instant & tahan lama hingga 20 jam) | J21: 265900 | K21: 0.27 | L21: 0.28 | M21: 0.3 | N21: 0.3 | O21: 0.31 | P21: 0.32 | Q21: 0.32 | R21: 0.33 | S21: 0.34 | V21: 194200 | W21: 191500 | X21: 186200 | Y21: 186200 | Z21: 183500 | AA21: 180900 | AB21: 180900 | AC21: 178200 | AD21: 175500
A22: MYB | B22: 7109300808_ID-13409832642 | C22: =_xlfn.NUMBERVALUE(LEFT(B22,10)) | D22: =_xlfn.NUMBERVALUE(RIGHT(B22,11)) | E22: 6902395487418 | F22: Maybelline Instant Age Rewind Treatment Concealer Make Up - 60ml (Concealer Cair Untuk Menghapus Lingkaran Hitam Mata) | J22: 155900 | K22: 0.05 | L22: 0.07 | M22: 0.1 | N22: 0.1 | O22: 0.11 | P22: 0.12 | Q22: 0.12 | R22: 0.13 | S22: 0.14 | V22: 148200 | W22: 145000 | X22: 140400 | Y22: 140400 | Z22: 138800 | AA22: 137200 | AB22: 137200 | AC22: 135700 | AD22: 134100
A23: MYB | B23: 7109300808_ID-13409832643 | C23: =_xlfn.NUMBERVALUE(LEFT(B23,10)) | D23: =_xlfn.NUMBERVALUE(RIGHT(B23,11)) | E23: 6902395487425 | F23: Maybelline Instant Age Rewind Treatment Concealer Make Up - 60ml (Concealer Cair Untuk Menghapus Lingkaran Hitam Mata) | J23: 155900 | K23: 0.05 | L23: 0.07 | M23: 0.1 | N23: 0.1 | O23: 0.11 | P23: 0.12 | Q23: 0.12 | R23: 0.13 | S23: 0.14 | V23: 148200 | W23: 145000 | X23: 140400 | Y23: 140400 | Z23: 138800 | AA23: 137200 | AB23: 137200 | AC23: 135700 | AD23: 134100
A24: MYB | B24: 7109300808_ID-13409832640 | C24: =_xlfn.NUMBERVALUE(LEFT(B24,10)) | D24: =_xlfn.NUMBERVALUE(RIGHT(B24,11)) | E24: 6902395748724 | F24: Maybelline Instant Age Rewind Treatment Concealer Make Up - 60ml (Concealer Cair Untuk Menghapus Lingkaran Hitam Mata) | J24: 155900 | K24: 0.05 | L24: 0.07 | M24: 0.1 | N24: 0.1 | O24: 0.11 | P24: 0.12 | Q24: 0.12 | R24: 0.13 | S24: 0.14 | V24: 148200 | W24: 145000 | X24: 140400 | Y24: 140400 | Z24: 138800 | AA24: 137200 | AB24: 137200 | AC24: 135700 | AD24: 134100
A25: MYB | B25: 7109300808_ID-13409832641 | C25: =_xlfn.NUMBERVALUE(LEFT(B25,10)) | D25: =_xlfn.NUMBERVALUE(RIGHT(B25,11)) | E25: 6902395487401 | F25: Maybelline Instant Age Rewind Treatment Concealer Make Up - 60ml (Concealer Cair Untuk Menghapus Lingkaran Hitam Mata) | J25: 155900 | K25: 0.05 | L25: 0.07 | M25: 0.1 | N25: 0.1 | O25: 0.11 | P25: 0.12 | Q25: 0.12 | R25: 0.13 | S25: 0.14 | V25: 148200 | W25: 145000 | X25: 140400 | Y25: 140400 | Z25: 138800 | AA25: 137200 | AB25: 137200 | AC25: 135700 | AD25: 134100
A26: MYB | B26: 7109300808_ID-13409832646 | C26: =_xlfn.NUMBERVALUE(LEFT(B26,10)) | D26: =_xlfn.NUMBERVALUE(RIGHT(B26,11)) | E26: 6902395677376 | F26: Maybelline Instant Age Rewind Treatment Concealer Make Up - 60ml (Concealer Cair Untuk Menghapus Lingkaran Hitam Mata) | J26: 155900 | K26: 0.05 | L26: 0.07 | M26: 0.1 | N26: 0.1 | O26: 0.11 | P26: 0.12 | Q26: 0.12 | R26: 0.13 | S26: 0.14 | V26: 148200 | W26: 145000 | X26: 140400 | Y26: 140400 | Z26: 138800 | AA26: 137200 | AB26: 137200 | AC26: 135700 | AD26: 134100
A27: MYB | B27: 7109300808_ID-13409832644 | C27: =_xlfn.NUMBERVALUE(LEFT(B27,10)) | D27: =_xlfn.NUMBERVALUE(RIGHT(B27,11)) | E27: 6902395487432 | F27: Maybelline Instant Age Rewind Treatment Concealer Make Up - 60ml (Concealer Cair Untuk Menghapus Lingkaran Hitam Mata) | J27: 155900 | K27: 0.05 | L27: 0.07 | M27: 0.1 | N27: 0.1 | O27: 0.11 | P27: 0.12 | Q27: 0.12 | R27: 0.13 | S27: 0.14 | V27: 148200 | W27: 145000 | X27: 140400 | Y27: 140400 | Z27: 138800 | AA27: 137200 | AB27: 137200 | AC27: 135700 | AD27: 134100
A28: MYB | B28: 7109300808_ID-13409832645 | C28: =_xlfn.NUMBERVALUE(LEFT(B28,10)) | D28: =_xlfn.NUMBERVALUE(RIGHT(B28,11)) | E28: 6902395487449 | F28: Maybelline Instant Age Rewind Treatment Concealer Make Up - 60ml (Concealer Cair Untuk Menghapus Lingkaran Hitam Mata) | J28: 155900 | K28: 0.05 | L28: 0.07 | M28: 0.1 | N28: 0.1 | O28: 0.11 | P28: 0.12 | Q28: 0.12 | R28: 0.13 | S28: 0.14 | V28: 148200 | W28: 145000 | X28: 140400 | Y28: 140400 | Z28: 138800 | AA28: 137200 | AB28: 137200 | AC28: 135700 | AD28: 134100
... A693: MYB | B693: 7545130789_ID-13957844057 | C693: =_xlfn.NUMBERVALUE(LEFT(B693,10)) | D693: =_xlfn.NUMBERVALUE(RIGHT(B693,11)) | E693: 8991380035633 | F693: EXCLUSIVE BUNDLE - Maybelline Sky High + Tattoo Liner | J693: 0 | K693: 0.25 | L693: 0.26 | M693: 0.27 | N693: 0.27 | O693: 0.275 | P693: 0.28 | Q693: 0.28 | R693: 0.285 | S693: 0.29 | V693: 0 | W693: 0 | X693: 0 | Y693: 0 | Z693: 0 | AA693: 0 | AB693: 0 | AC693: 0 | AD693: 0
A694: MYB | B694: 7545256453_ID-13957866058 | C694: =_xlfn.NUMBERVALUE(LEFT(B694,10)) | D694: =_xlfn.NUMBERVALUE(RIGHT(B694,11)) | E694: 8991380035640 | J694: 0 | K694: 0.24 | L694: 0.25 | M694: 0.26 | N694: 0.25 | O694: 0.26 | P694: 0.27 | Q694: 0.26 | R694: 0.27 | S694: 0.28 | V694: 0 | W694: 0 | X694: 0 | Y694: 0 | Z694: 0 | AA694: 0 | AB694: 0 | AC694: 0 | AD694: 0
A695: MYB | B695: 7098310224_ID-13971300930 | C695: =_xlfn.NUMBERVALUE(LEFT(B695,10)) | D695: =_xlfn.NUMBERVALUE(RIGHT(B695,11)) | E695: 6902395774211 | F695: Maybelline Fit Me Matte + Poreless Liquid Foundation Make Up 30ml - Makeup Ringan Full Coverage 16HR Oil Control | J695: 171900 | K695: 0.32 | L695: 0.33 | M695: 0.37 | N695: 0.365 | O695: 0.37 | P695: 0.39 | Q695: 0.39 | R695: 0.4 | S695: 0.405 | V695: 116900 | W695: 115200 | X695: 108300 | Y695: 109200 | Z695: 108300 | AA695: 104900 | AB695: 104900 | AC695: 103200 | AD695: 102300
A696: MYB | B696: 7098310224_ID-13971314489 | C696: =_xlfn.NUMBERVALUE(LEFT(B696,10)) | D696: =_xlfn.NUMBERVALUE(RIGHT(B696,11)) | E696: 6902395834403 | F696: Maybelline Fit Me Matte + Poreless Liquid Foundation Make Up 30ml - Makeup Ringan Full Coverage 16HR Oil Control | J696: 171900 | K696: 0.32 | L696: 0.33 | M696: 0.37 | N696: 0.365 | O696: 0.37 | P696: 0.39 | Q696: 0.39 | R696: 0.4 | S696: 0.405 | V696: 116900 | W696: 115200 | X696: 108300 | Y696: 109200 | Z696: 108300 | AA696: 104900 | AB696: 104900 | AC696: 103200 | AD696: 102300
A697: MYB | B697: 7098310224_ID-13971316527 | C697: =_xlfn.NUMBERVALUE(LEFT(B697,10)) | D697: =_xlfn.NUMBERVALUE(RIGHT(B697,11)) | E697: 6902395774297 | F697: Maybelline Fit Me Matte + Poreless Liquid Foundation Make Up 30ml - Makeup Ringan Full Coverage 16HR Oil Control | J697: 171900 | K697: 0.32 | L697: 0.33 | M697: 0.37 | N697: 0.365 | O697: 0.37 | P697: 0.39 | Q697: 0.39 | R697: 0.4 | S697: 0.405 | V697: 116900 | W697: 115200 | X697: 108300 | Y697: 109200 | Z697: 108300 | AA697: 104900 | AB697: 104900 | AC697: 103200 | AD697: 102300
A698: MYB | B698: 7098310224_ID-13971330236 | C698: =_xlfn.NUMBERVALUE(LEFT(B698,10)) | D698: =_xlfn.NUMBERVALUE(RIGHT(B698,11)) | E698: 6902395834410 | F698: Maybelline Fit Me Matte + Poreless Liquid Foundation Make Up 30ml - Makeup Ringan Full Coverage 16HR Oil Control | J698: 171900 | K698: 0.32 | L698: 0.33 | M698: 0.37 | N698: 0.365 | O698: 0.37 | P698: 0.39 | Q698: 0.39 | R698: 0.4 | S698: 0.405 | V698: 116900 | W698: 115200 | X698: 108300 | Y698: 109200 | Z698: 108300 | AA698: 104900 | AB698: 104900 | AC698: 103200 | AD698: 102300
A699: MYB | B699: 7098310224_ID-13971334240 | C699: =_xlfn.NUMBERVALUE(LEFT(B699,10)) | D699: =_xlfn.NUMBERVALUE(RIGHT(B699,11)) | E699: 6902395774433 | F699: Maybelline Fit Me Matte + Poreless Liquid Foundation Make Up 30ml - Makeup Ringan Full Coverage 16HR Oil Control | J699: 171900 | K699: 0.32 | L699: 0.33 | M699: 0.37 | N699: 0.365 | O699: 0.37 | P699: 0.39 | Q699: 0.39 | R699: 0.4 | S699: 0.405 | V699: 116900 | W699: 115200 | X699: 108300 | Y699: 109200 | Z699: 108300 | AA699: 104900 | AB699: 104900 | AC699: 103200 | AD699: 102300
A700: MYB | B700: 7098310224_ID-13971334241 | C700: =_xlfn.NUMBERVALUE(LEFT(B700,10)) | D700: =_xlfn.NUMBERVALUE(RIGHT(B700,11)) | E700: 6902395826934 | F700: Maybelline Fit Me Matte + Poreless Liquid Foundation Make Up 30ml - Makeup Ringan Full Coverage 16HR Oil Control | J700: 171900 | K700: 0.32 | L700: 0.33 | M700: 0.37 | N700: 0.365 | O700: 0.37 | P700: 0.39 | Q700: 0.39 | R700: 0.4 | S700: 0.405 | V700: 116900 | W700: 115200 | X700: 108300 | Y700: 109200 | Z700: 108300 | AA700: 104900 | AB700: 104900 | AC700: 103200 | AD700: 102300
A701: MYB | B701: 7098310224_ID-13971334249 | C701: =_xlfn.NUMBERVALUE(LEFT(B701,10)) | D701: =_xlfn.NUMBERVALUE(RIGHT(B701,11)) | E701: 6902395826941 | F701: Maybelline Fit Me Matte + Poreless Liquid Foundation Make Up 30ml - Makeup Ringan Full Coverage 16HR Oil Control | J701: 171900 | K701: 0.32 | L701: 0.33 | M701: 0.37 | N701: 0.365 | O701: 0.37 | P701: 0.39 | Q701: 0.39 | R701: 0.4 | S701: 0.405 | V701: 116900 | W701: 115200 | X701: 108300 | Y701: 109200 | Z701: 108300 | AA701: 104900 | AB701: 104900 | AC701: 103200 | AD701: 102300
A702: MYB | B702: 7098310224_ID-13971358053 | C702: =_xlfn.NUMBERVALUE(LEFT(B702,10)) | D702: =_xlfn.NUMBERVALUE(RIGHT(B702,11)) | E702: 6902395774426 | F702: Maybelline Fit Me Matte + Poreless Liquid Foundation Make Up 30ml - Makeup Ringan Full Coverage 16HR Oil Control | J702: 171900 | K702: 0.32 | L702: 0.33 | M702: 0.37 | N702: 0.365 | O702: 0.37 | P702: 0.39 | Q702: 0.39 | R702: 0.4 | S702: 0.405 | V702: 116900 | W702: 115200 | X702: 108300 | Y702: 109200 | Z702: 108300 | AA702: 104900 | AB702: 104900 | AC702: 103200 | AD702: 102300
A703: MYB | B703: 7488896493_ID-13903000882 | C703: =_xlfn.NUMBERVALUE(LEFT(B703,10)) | D703: =_xlfn.NUMBERVALUE(RIGHT(B703,11)) | E703: 6902395843467 | F703: Maybelline Lip & Eye Makeup Remover - 150 ml Mudah Hapus Make Up Waterproof | J703: 145900 | K703: 0.2 | L703: 0.21 | M703: 0.22 | N703: 0.22 | O703: 0.25 | P703: 0.27 | Q703: 0.27 | R703: 0.28 | S703: 0.29 | V703: 116800 | W703: 115300 | X703: 113900 | Y703: 113900 | Z703: 109500 | AA703: 106600 | AB703: 106600 | AC703: 105100 | AD703: 103600
A704: MYB | B704: 7488888545_ID-13902992712 | C704: =_xlfn.NUMBERVALUE(LEFT(B704,10)) | D704: =_xlfn.NUMBERVALUE(RIGHT(B704,11)) | E704: 6902395847335 | F704: Maybelline Lip & Eye Makeup Remover - 70 ml Pembersih Wajah Mudah Hapus Make Up Waterproof | J704: 95900 | K704: 0.2 | L704: 0.21 | M704: 0.22 | N704: 0.22 | O704: 0.25 | P704: 0.27 | Q704: 0.27 | R704: 0.28 | S704: 0.29 | V704: 76800 | W704: 75800 | X704: 74900 | Y704: 74900 | Z704: 72000 | AA704: 70100 | AB704: 70100 | AC704: 69100 | AD704: 68100
A705: MYB | B705: 7474598120_ID-13887174045 | C705: =_xlfn.NUMBERVALUE(LEFT(B705,10)) | D705: =_xlfn.NUMBERVALUE(RIGHT(B705,11)) | E705: 6902395844914 | F705: Maybelline Tattoo Liner 48H Liquid Pen Eyeliner Waterproof Makeup (Tahan Lama Hingga 48 Jam, Smudgeproof, Hitam Intens, Liquid Eyeliner) | J705: 93900 | K705: 0.28 | L705: 0.285 | M705: 0.295 | N705: 0.29 | O705: 0.3 | P705: 0.31 | Q705: 0.3 | R705: 0.31 | S705: 0.32 | V705: 67700 | W705: 67200 | X705: 66200 | Y705: 66700 | Z705: 65800 | AA705: 64800 | AB705: 65800 | AC705: 64800 | AD705: 63900
A706: GAR | B706: 7520530694_ID-13935134920 | C706: =_xlfn.NUMBERVALUE(LEFT(B706,10)) | D706: =_xlfn.NUMBERVALUE(RIGHT(B706,11)) | E706: 8991380035473 | F706: Garnier Gentle Brightening Set Bright Complete Vitamin C Serum 15ml + Vitamin C Gel Wash 120ml - Skincare Kulit Cerah | J706: 180000 | K706: 0.02 | L706: 0.03 | M706: 0.22 | N706: 0.19 | O706: 0.2 | P706: 0.23 | Q706: 0.2 | R706: 0.21 | S706: 0.24 | V706: 176400 | W706: 174600 | X706: 140400 | Y706: 145800 | Z706: 144000 | AA706: 138600 | AB706: 144000 | AC706: 142200 | AD706: 136800
... A810: MNY | B810: 8117118321_ID-14509960907 | C810: =_xlfn.NUMBERVALUE(LEFT(B810,10)) | D810: =_xlfn.NUMBERVALUE(RIGHT(B810,11)) | E810: 8991380042617 | F810: Maybelline Paket Hemat Hypercurl Waterproof Mascara + Tattoo Liner 48hr + Color Rivals Eyeshadow | Waterproof Maskara | J810: 282800 | K810: 0.02 | L810: 0.03 | M810: 0.04 | N810: 0.03 | O810: 0.04 | P810: 0.05 | Q810: 0.05 | R810: 0.06 | S810: 0.07 | V810: 277200 | W810: 274400 | X810: 271500 | Y810: 274400 | Z810: 271500 | AA810: 268700 | AB810: 268700 | AC810: 265900 | AD810: 263100
A811: MNY | B811: 8117070550_ID-14509904581 | C811: =_xlfn.NUMBERVALUE(LEFT(B811,10)) | D811: =_xlfn.NUMBERVALUE(RIGHT(B811,11)) | E811: 8991380042587 | F811: Maybelline PAKET MAKEUP LIMITED Feel The Power of Makeup - Paket Lengkap Hemat Seserahan Paket kosmetik | J811: TBC | K811: 0.02 | L811: 0.03 | M811: 0.04 | N811: 0.03 | O811: 0.04 | P811: 0.05 | Q811: 0.05 | R811: 0.06 | S811: 0.07 | V811: #VALUE! | W811: #VALUE! | X811: #VALUE! | Y811: #VALUE! | Z811: #VALUE! | AA811: #VALUE! | AB811: #VALUE! | AC811: #VALUE! | AD811: #VALUE!
A812: MNY | B812: 8117102007_ID-14509938230 | C812: =_xlfn.NUMBERVALUE(LEFT(B812,10)) | D812: =_xlfn.NUMBERVALUE(RIGHT(B812,11)) | E812: 8991380042600 | F812: Maybelline Paket Makeup Mata Hypercurl Waterproof Mascara + Define and Blend Eyebrow Pencil | Eye Make up | J812: TBC | K812: 0.02 | L812: 0.03 | M812: 0.04 | N812: 0.03 | O812: 0.04 | P812: 0.05 | Q812: 0.05 | R812: 0.06 | S812: 0.07 | V812: #VALUE! | W812: #VALUE! | X812: #VALUE! | Y812: #VALUE! | Z812: #VALUE! | AA812: #VALUE! | AB812: #VALUE! | AC812: #VALUE! | AD812: #VALUE!
A813: MNY | B813: 8117094061_ID-14509946040 | C813: =_xlfn.NUMBERVALUE(LEFT(B813,10)) | D813: =_xlfn.NUMBERVALUE(RIGHT(B813,11)) | E813: 8991380042570 | F813: Maybelline Paket Makeup Hemat Sky High Waterproof Mascara + Lash Boosting Serum | Maskara Eye Make up Bulu Mata Panjang | J813: TBC | K813: 0.02 | L813: 0.03 | M813: 0.04 | N813: 0.03 | O813: 0.04 | P813: 0.05 | Q813: 0.05 | R813: 0.06 | S813: 0.07 | V813: #VALUE! | W813: #VALUE! | X813: #VALUE! | Y813: #VALUE! | Z813: #VALUE! | AA813: #VALUE! | AB813: #VALUE! | AC813: #VALUE! | AD813: #VALUE!
A814: MNY | B814: 8117036959_ID-14509902361 | C814: =_xlfn.NUMBERVALUE(LEFT(B814,10)) | D814: =_xlfn.NUMBERVALUE(RIGHT(B814,11)) | E814: 8991380042747 | F814: Maybelline Paket Hemat Superstay Matte Ink 2 pcs Ombre Set Lipstick - Long Lasting | J814: 169900 | K814: 0.02 | L814: 0.03 | M814: 0.04 | N814: 0.03 | O814: 0.04 | P814: 0.05 | Q814: 0.05 | R814: 0.06 | S814: 0.07 | V814: 166600 | W814: 164900 | X814: 163200 | Y814: 164900 | Z814: 163200 | AA814: 161500 | AB814: 161500 | AC814: 159800 | AD814: 158100
A815: MNY | B815: 8117036959_ID-14509902362 | C815: =_xlfn.NUMBERVALUE(LEFT(B815,10)) | D815: =_xlfn.NUMBERVALUE(RIGHT(B815,11)) | E815: 8991380042754 | F815: Maybelline Paket Hemat Superstay Matte Ink 2 pcs Ombre Set Lipstick - Long Lasting | J815: 169900 | K815: 0.02 | L815: 0.03 | M815: 0.04 | N815: 0.03 | O815: 0.04 | P815: 0.05 | Q815: 0.05 | R815: 0.06 | S815: 0.07 | V815: 166600 | W815: 164900 | X815: 163200 | Y815: 164900 | Z815: 163200 | AA815: 161500 | AB815: 161500 | AC815: 159800 | AD815: 158100
A816: MNY | B816: 8117036959_ID-14509902363 | C816: =_xlfn.NUMBERVALUE(LEFT(B816,10)) | D816: =_xlfn.NUMBERVALUE(RIGHT(B816,11)) | E816: 8991380042761 | F816: Maybelline Paket Hemat Superstay Matte Ink 2 pcs Ombre Set Lipstick - Long Lasting | J816: 169900 | K816: 0.02 | L816: 0.03 | M816: 0.04 | N816: 0.03 | O816: 0.04 | P816: 0.05 | Q816: 0.05 | R816: 0.06 | S816: 0.07 | V816: 166600 | W816: 164900 | X816: 163200 | Y816: 164900 | Z816: 163200 | AA816: 161500 | AB816: 161500 | AC816: 159800 | AD816: 158100
A817: MNY | B817: 8117036959_ID-14509902364 | C817: =_xlfn.NUMBERVALUE(LEFT(B817,10)) | D817: =_xlfn.NUMBERVALUE(RIGHT(B817,11)) | E817: 8991380042778 | F817: Maybelline Paket Hemat Superstay Matte Ink 2 pcs Ombre Set Lipstick - Long Lasting | J817: 169900 | K817: 0.02 | L817: 0.03 | M817: 0.04 | N817: 0.03 | O817: 0.04 | P817: 0.05 | Q817: 0.05 | R817: 0.06 | S817: 0.07 | V817: 166600 | W817: 164900 | X817: 163200 | Y817: 164900 | Z817: 163200 | AA817: 161500 | AB817: 161500 | AC817: 159800 | AD817: 158100

Sheet Data_Validations
A1: Archetype | B1: E-Boutique | D1: Market 1 | E1: Australia / New Zealand | G1: Country 1 | H1: Malaysia | K1: Division | L1: Consumer Products Division (CPD) | N1: Brands | O1: Not Applicable | Q1: Request type | R1: Not Applicable | T1: Request SubType | U1: Not Applicable | W1: Platform | X1: Not Applicable | Z1: Date | AA1: =TODAY()
B2: E-Retailers | E2: India | H2: Singapore | L2: L’Oréal Dermatological Beauty (LDB) | O2: Biotherm | R2: Campaign Management | U2: New Product Listing | X2: Lazada
B3: Marketplace | E3: Indonesia | L3: L’Oréal Luxe Division (LLD) | O3: CeraVe | R3: Copywriting | U3: Product Details Update | X3: Shopee
B4: Pureplayers | E4: Malaysia / Singapore | L4: Professional Products Division (PPD) | O4: Garnier | R4: Product Management | U4: Price Update (Bulk,TB,BMO, CBMO) | X4: Tokopedia
E5: Thailand | G5: Country 2 | H5: Australia | O5: Kérastase | U5: Promo Mechanic Creation
H6: New Zealand | O6: Kiehl's | U6: Asset Creation
O7: La Roche Posay | U7: Copywriting
O8: Lancôme | U8: Others
D9: Market 2 | E9: Australia / New Zealand | G9: Country 3 | H9: India | O9: L'Oréal Paris
E10: India | O10: L'Oréal Professionnel
E11: Malaysia / Singapore | G11: Country 4 | H11: Thailand | O11: Maybelline
O12: Shu Uemura
D13: Market 3 | E13: Australia / New Zealand | G13: Country 5 | H13: Vietnam | O13: Vichy
E14: India
E15: Malaysia / Singapore | G15: Country 6 | H15: Indonesia
D17: Market 4 | E17: India

Sheet Instruction
M2: Click here to access the guide (ACN)
B6: Template Name | D6: Loreal Campaign Brief Template
B7: Purpose | D7: This template is mandatory to request Content Listing/Updation and Campaign management on Marketplace
B8: Business User | D8: The Online Brand Manager (OBM) & Brand Platform Manager (BPM) is typically responsible for submitting the template
B9: Information security | D9: The template may include restricted data for pre-launch products
B10: Need Help? | D10: Confirmation needed if any support team email ID can be addedd
B12: Type of Input require | D12: Fixed | I12: Template applicable as per request
D13: *Mandatory | I13: Request type | J13: Applicable Template
D14: Optional | I14: Mega Campaign - Price Change (TB)-LZD | J14: Mega Campaign - Price Change (TB)-LZD
D15: Dropdown | I15: Promotion Mechanics -Flexi Combo-LZD | J15: Promo-Flexi Combo-LZD
I16: Promotion Mechanics - Voucher-LZD | J16: Promo-Voucher-LZD
B17: How to use the Template | I17: Promotion Mechanics -Brand Membership-LZD | J17: Promo-Brand Membership-LZD
B18: Overview | D18: Please refer Overview tab and provide all the mandatory attributes marked as * | I18: CEM-LZD | J18: CEM-LZD
D19: Select the Market, Country, Division, Brand, Archetype and Platform | I19: Visual Brief Requirements from Loreal-LZD | J19: Visual Brief Req.-LZD
D20: Please input Request Name as per the | I20: Visual A revised-LZD | J20: Visual A revised-LZD
I21: Wireframe Revised-LZD | J21: Wireframe Revised-LZD
I22: Wireframe LZD SBD MCP SIS | J22: Wireframe LZD SBD MCP SIS
I23: Launch Requirement (FG)-LZD | J23: Launch Requirement (FG)-LZD
B24: How to use the Template | I24: Launch Req. (GWP, Sample)-LZD | J24: Launch Req. (GWP, Sample)-LZD
B25: 1 | C25: Overview | D25: Go to Overview tab - Provide information for all the mandatory attributes marked as "*". Select the Market, Country, Division, Brand, Platform, Request Type, Prioritization using the dropdown.
B29: 2 | C29: Price Change | D29: Please provide any additional information using the applicable tabs. e.g. Price: For any price change request including Treasure Bowl submission Promo: For any promo setup require e.g. Voucher creation, Free Shipping setup, etc. VB: Virtual Bundle setup Visual A/Visual B: For any visual request - can use both or either one Launch Requirement: New Product listing
I30: What is request type? | J30: Request type will define the task needed to be actioned
I31: New Product Listing | J31: Listing of new product information/content on sales platform
I32: Product Update | J32: Changes needed in the existing PDP content
B33: 3 | C33: Help Needed | D33: To access the applicable teamplate refer to "Template applicable as per request" in Overview tab | I33: Mega Campaign | J33: Campaign specifically targeting on an upcoming event
I34: BAU Campaign | J34: General campaign
I35: Adhoc campaign | J35: Additional campaign
B36: 4 | C36: How to share the template? | D36: Attach the completed template in SynOps Ticket | F36: SynOps link (Can we add CXL link) | I36: CPAS | J36: Collaborative Performance Advertising Solutions (CPAS), rebranded as Collaborative Ads, are an advertising solution created by Facebook (now Meta) allowing brands and retailers to create ads together.
I39: What is Prioritisation | J39: It defines the urgency of the task/request
I40: BAU | J40: Defined SLA for each task
I41: Priority | J41: Requests which will be completed within 24 hours
I42: Super Priority | J42: Requests with minimum number of changes to be completed in few hour(1-4 hours) | L42: SLA DETAILS | M42: To include details in table once finalised
M43: Synops SLAs (UAT)

Sheet Overview
A2: Type of Input require | B2: Fixed
B3: Optional
B4: Dropdown
A7: REQUEST TYPE* | D7: Select Request Type
A8: CAMPAIGN NAME* | D8: Select Campaign Name
A9: SUBCAMPAIGN NAME | D9: Select Subcampaign Name
A10: MARKET LEVEL CAMPAIGN NAME*
A11: PRIORITISATION* | D11: Select Priority
A14: Thailand (TH)
A15: PROMOTION TYPE & DATE: | D15: PLATFORM e.g. Shopee | E15: PROMOTION TYPE e.g. Teasing | G15: START DATE e.g. 1-Sep-22 | H15: END DATE e.g. 8-Sep-22 | I15: REMARKS | K15: 4.4 Raya (D-Day)
D16: Select Platforms | E16: Derma Campaign | G16: 45220 | H16: 45221 | K16: CPAS - 22-Mar go live, Publicis receive brief 6-Mar, visual 3-4 working days (16-mar, actual)
D17: Select Platforms | K17: SIS -
D18: Select Platforms | K18: PDP (Hero) - 22-Mar go live
D19: Select Platforms | K19: MMT need 24-48 hrs to upload
D20: Select Platforms | K20: Promo plan: 20 Feb 80%
A21: SELLER CENTRE SETUP e.g. MECHANICS & USP FOR VISUALS | D21: SC SETUP / MECHANICS TYPE | E21: LAZADA
E22: PPROMO (Y/N) | F22: VISUAL KEY MESSAGING | G22: REMARKS
C23: 1 | D23: Price Change - TB | E23: Yes
C24: 2 | D24: Price Change - TB - FS | E24: Yes
C25: 3 | D25: Price Change - SIS - FS | E25: No
C26: 4 | D26: Promotion - Flexi Combo | E26: Yes
C27: 5 | D27: Promotion - Voucher | E27: Yes
C28: 6 | D28: Promotion - Brand Membership | E28: No
C29: 7 | D29: CEM | E29: No
C30: 8 | D30: Feed | E30: No
C31: 9 | D31: Visual Brief | E31: No
C32: 10 | D32: Visibility Brief | E32: No
C33: 11 | D33: Wireframe | E33: No
C34: 12 | D34: New Product Listing (NPD) | E34: No
... C36: 14 | D36: Virtual Bundle (VB) Listing | E36: No
A38: SINGAPORE (SG)
A39: PROMOTION TYPE & DATE: | D39: PLATFORM e.g. Shopee | E39: PROMOTION TYPE e.g. Teasing | G39: START DATE e.g. 1-Sep-22 | H39: END DATE e.g. 8-Sep-22 | I39: REMARKS
D40: Select Platforms
D41: Select Platforms
D42: Select Platforms
D43: Select Platforms
D44: Select Platforms
A45: SELLER CENTRE SETUP e.g. MECHANICS & USP FOR VISUALS | D45: SC SETUP / MECHANICS TYPE | E45: LAZADA | H45: SHOPEE
E46: PPROMO (Y/N) | F46: VISUAL KEY MESSAGING | G46: REMARKS | H46: PPROMO (Y/N) | I46: VISUAL KEY MESSAGING | J46: REMARKS
C47: 1 | D47: PRICE CHANGE - Promo, Flash, etc. | E47: Yes | H47: Select from Dropdown
C48: 2 | D48: PROMO SETUP - Voucher | E48: Select from Dropdown | H48: Select from Dropdown
C49: 3 | D49: PROMO SETUP - Free Shipping | E49: Select from Dropdown | H49: Select from Dropdown
C50: 4 | D50: PROMO SETUP - Flexi Combo, Add-On, GWP | E50: Select from Dropdown | H50: Select from Dropdown
C51: 5 | D51: PROMO SETUP - Brand Membership | E51: Select from Dropdown | H51: Select from Dropdown
C52: 6 | D52: PROMO SETUP - Others | E52: Select from Dropdown | H52: Select from Dropdown
C53: 7 | D53: VB - Virtual Bundle | E53: Select from Dropdown | H53: Select from Dropdown
C54: 8 | D54: SIS UPDATE | E54: Select from Dropdown | H54: Select from Dropdown
C55: 9
C56: 10

Sheet Brief Guide
A1: No | B1: Tab Name | C1: Details | D1: Output
A2: 1 | B2: Instruction | C2: Instruction/guide for L'Oreal on how to fill-up brief template | D2: Input Accuracy
A3: 2 | B3: Overview | C3: To capture important fields for the request: 1) Market 2) Country 3) Division 4) Brand 5) Archetype 6) Platform 7) Request Name 8) Theme 9) Asstes Link 10) Elements 11) Promotion Type & Date 12) Mechanics & USP for Visual 13) Assets Deliverables | D3: - Request details: Market, Country, Division, Brand, Archetype, Platform, Request Name, Theme, Asstes Link - Delivery date, Go-Live date - Mechanics for Seller Centre Setup - Type of assets
A4: 3 | B4: Promo | C4: Mechanics for Seller Centre Setup | D4: Creation below mechanic on Seller Centre - Voucher - Free Shipping - Flexi Combo - Brand Membership
A5: 4 | B5: Virtual Bundle (VB) | C5: Virtual Bundle details for Seller Centre Setup | D5: Creation of Virtual Bundle on Seller Centre
A6: 5 | B6: Price | C6: Price change/submission | D6: Price change/submission on Seller Centre
A7: 6 | B7: Visual A | C7: Submission of visual request and copywriting on assets if require | D7: Type of assets and its content
A8: 7 | B8: Visual B | C8: Visual request and copywriting (if require) - copy paste wireframe | D8: Type of assets and its content

Sheet Price Change (SIS-FS) -LZD
B1: Type of Input require | C1: *Mandatory Fields | E1: Changes done as per feedback | I1: Key Notes
C2: Optional Fields | I2: 1. Kindly duplicate the table for additional campaigns that you may want to add for any month
C3: Dropdown
B4: *Please take note for any input with double pricing with same date/duration, SVC will submit the lowest price
B6: Promotion Type: Mega Day (applicable for campaign with no specific timing) | J6: Promotion Type: BAU only (applicable for campaign with no specific timing) | R6: Promotion Type: Flash etc (applicable for campaign with specific timing) | AA6: Promotion Type: Flash, BMO, etc (applicable for campaign with specific timing)
B7: Campaign Name* | D7: Name of the campaign | J7: Campaign Name* | L7: Name of the campaign | R7: Campaign Name* | T7: Name of the campaign | AA7: Campaign Name* | AC7: Name of the campaign
B8: Start Date* | C8: Start Date | F8: Start Time* | G8: Start Time | J8: Start Date* | K8: Start Date | N8: Start Time* | O8: Start Time | R8: Start Date* | S8: Start Date | V8: Start Time* | W8: Start Time | AA8: Start Date* | AB8: Start Date | AE8: Start Time* | AF8: Start Time
B9: End Date* | C9: End Date | F9: End Time* | G9: End Time | J9: End Date* | K9: End Date | N9: End Time* | O9: End Time | R9: End Date* | S9: End Date | V9: End Time* | W9: End Time | AA9: End Date* | AB9: End Date | AE9: End Time* | AF9: End Time
B10: Platform* | C10: Lazada SKU* | D10: EAN* | E10: Product Name | F10: Current Price - RSP (THB) | G10: Discount (%) (Optional - for validation) | H10: Price (Campaign Price)* | I10: Remarks | J10: Platform* | K10: Lazada SKU* | L10: EAN* | M10: Product Name | N10: Current Price - RSP (THB) | O10: Discount (%) (Optional - for validation) | P10: Price (Campaign Price)* | Q10: Remarks | R10: Platform* | S10: Lazada SKU* | T10: EAN* | U10: Product Name | V10: Current Price - RSP (THB) | W10: Discount (%) (Optional - for validation) | X10: Rebate (for CPD division) | Y10: Offer Price (Campaign Price)* | Z10: Remarks | AA10: Platform* | AB10: Lazada SKU* | AC10: EAN* | AD10: Product Name | AE10: Current Price - RSP (THB) | AF10: Discount (%) (Optional - for validation) | AG10: Price (Campaign Price)* | AH10: Remarks
A11: Example | B11: Lazada | C11: 830914469_TH-1974242308 | D11: 6902395827375 | E11: Maybelline City Mini Palette Eyeshadow - Uncaged Limited Edition | H11: 99.00 | J11: Lazada | K11: 830914469_TH-1974242308 | L11: 6902395827375 | M11: Maybelline City Mini Palette Eyeshadow - Uncaged Limited Edition | P11: 99.00 | R11: Lazada | S11: 830914469_TH-1974242308 | T11: 6902395827375 | U11: Maybelline City Mini Palette Eyeshadow - Uncaged Limited Edition | Y11: 99.00 | AA11: Lazada | AB11: 830914469_TH-1974242308 | AC11: 6902395827375 | AD11: Maybelline City Mini Palette Eyeshadow - Uncaged Limited Edition | AG11: 99.00

Sheet Dropdown list
A1: Campaign Type | B1: Platform | C1: Campaign Tiering | D1: Voucher Type | E1: Brand Membership - Discount Type | F1: Voucher - Discount Type | G1: Type of Members | H1: Member Group | I1: Type of Mechanics | J1: Type of Add-on Promotion | K1: NA | L1: GWP - FlexiComboMechanics | M1: StorewidevsSpecific | N1: MoneyorDiscount | O1: Main Product or GWP | P1: Product Type | Q1: Combobuy | R1: FixedPrice | S1: DealCriteria | T1: SIS Time slot | U1: Stackable/ Unstackable | V1: VBOM/Single/Bundle | W1: Platform | X1: Ad Type | Y1: Concate - Ad Type | Z1: Banner Placement | AA1: Platform | AB1: Ad Type | AC1: Concate - Ad Type | AD1: Banner Placement | AF1: Banner Placement | AG1: Banner Size | AH1: Service Center | AK1: CEM-Pool Choice | AL1: CEM-Target Audience
A2: Select Campaign Type | B2: Select Platform | C2: Select from below Campaign | D2: Select from Dropdown | E2: Select Discount Type | F2: Select Discount Type | G2: Select type of Member | H2: Select from Dropdown | I2: Select from Dropdown | J2: Select from Dropdown | K2: Select from Dropdown | L2: Select from Dropdown | M2: Select from Dropdown | N2: Select from Dropdown | O2: Select from Dropdown | P2: Select from Dropdown | Q2: Select from Dropdown | R2: Select from Dropdown | S2: Select from Dropdown | T2: Select from Dropdown | U2: Select from Dropdown | V2: Select from Dropdown | W2: Lazada | X2: Off-Platform | Y2: LazadaOff-Platform | Z2: FB Post (Collection Ads) | AA2: Shoppe | AB2: Off-Platform | AC2: ShopeeOff-Platform | AD2: FB Post | AE2: Lazada | AF2: FB Post (Collection Ads) | AG2: 1000 x 1000 | AH2: Select Status | AK2: Select Input | AL2: Select Input
A3: Mega | B3: Shopee | C3: SBD | D3: LZD - Store Follower | E3: Voucher - Percentage | F3: Percentage | G3: Welcome | H3: Silver and above | I3: LZD -Welcome Vouhcer | J3: Price | K3: NA | L3: Percentage | M3: Store-wide | N3: Money Value Off | O3: Main | P3: FG | Q3: Percentage Discount Off & Free Gift(s) | R3: NA | S3: Any Item Quantity + Order Value Reaches X | T3: 00:00 - 08:00 | U3: Yes | V3: Single | X3: On-Platform | Y3: LazadaOn-Platform | Z3: IG Story | AB3: On-Platform | AC3: ShopeeOn-Platform | AD3: IG Story | AF3: IG Story | AG3: 1080 x 1920 | AH3: Awaiting Confirmation | AK3: Remind Cart Item | AL3: All Follower
A4: Medium | B4: Lazada | C4: Mega (Double day) | D4: LZD - Regular | E4: Voucher - Fixed Price | F4: Fixed Price | G4: Regular | H4: Gold and above | I4: LZD - Linked Member Voucher | J4: Discount off | L4: Money Off | M4: Specific SKUs | N4: Percentage Discount Off | O4: GWP | P4: Sample | Q4: Money Value Off & Free Gift(s) | S4: Order Value Reaches X | T4: 08:00 - 12:00 | U4: No | V4: Physical Bundle | Z4: Affliate - LZ | AD4: Affliate - SH | AF4: Affliate - LZ | AG4: 1200 x 628, 120 x 600, 320 x 50, 300 x 250, 600 x 600 | AH4: Pending | AK4: Share New Arrival | AL4: Brand Membership
A5: Small | C5: Payday | D5: LZD - New Buyer | E5: CCB - Percentage | H5: Platinum and above | I5: LZD - Welcome Product Offer | L5: Free gift/sample | P5: Other | Q5: Percentage Discount Off & Free Sample(s) | S5: Item Quantity Reaches X | T5: 12:00 - 18:00 | V5: Virtual Bundle | Z5: FEED | AD5: FEED | AF5: FEED | AG5: 600 x 600 (Perfect square) | AH5: On Hold | AK5: Offer Voucher | AL5: Shop Follower
C6: Category Campaign | D6: LZD - Live Stream | E6: CCB - Fixed Price | H6: Diamond Only | I6: LZD - Linked Member Product Offer | L6: Combo buy (Percentage and gift) | Q6: Money Value Off & Free Sample(s) | S6: Any Item Quantity Reaches X | T6: 18:00 - 20:00 | Z6: Carousel Banner (Shop-in-Shop) | AD6: Video | AF6: Carousel Banner (Shop-in-Shop) | AG6: 1200 x 568 | AH6: Completed | AK6: Inform Promotion
C7: BAU | D7: LZD - Others (Unique voucher) | E7: Member Price - Percentage | H7: All Members | I7: LZD - New Member Voucher | L7: Combo buy (Fixed price and gift) | S7: Buy Any X, Get Any GWP | T7: 20:00 - 22:00 | Z7: Top Banner (Shop-in-Shop) | AD7: Carousel | AF7: Top Banner (Shop-in-Shop) | AG7: 1200 x 600 | AH7: Cancelled | AK7: Custom Message
D8: LZD - Co-Funded Voucher | E8: Gift | I8: LZD - Member-exclusive Voucher | T8: 22:00 - 24:00 | Z8: Middle Banner (Shop-in-Shop) | AD8: Multiple Images | AF8: Middle Banner (Shop-in-Shop) | AG8: 1200 x 353
D9: SHP - Shop Voucher | E9: Points Multiplier | I9: LZD - Points Redeemable Voucher | Z9: Bottom Banner (Shop-in-Shop) | AD9: Banner and Category | AF9: Bottom Banner (Shop-in-Shop) | AG9: 1200 x 600
D10: SHP - Product Voucher | E10: Sign on Bonus | I10: LZD - New Member Product Offer | Z10: Followers Banner (Shop-in-Shop) | AD10: Single Image | AF10: Followers Banner (Shop-in-Shop) | AG10: 1200 x 288
D11: SHP - Private Voucher | E11: Member Exclusive Price | I11: LZD - Member Product Offer | L11: Money (tiering) /Discount % | M11: MoneyorDiscount | Z11: Category Banner (Shop-in-Shop) | AD11: Multiple Clickable Ares | AF11: Category Banner (Shop-in-Shop) | AG11: 1200 x 150
D12: SHP - Live Voucher | I12: LZD - Points Redeemable Product | L12: Free gift/sample | M12: Freegiftorsample | Z12: Homepage Banner 1 | AD12: Image Category List | AF12: Homepage Banner 1 | AG12: 796 x 235
D13: SHP - Video Voucher | I13: SHP - Welcome Voucher | L13: Combo buy (discount and free gift) | M13: Combobuy | Z13: Homepage Banner 2 | AD13: Homepage Banner 1 | AF13: Homepage Banner 2 | AG13: 398 x 115
D14: SHP - New Buyer Voucher | I14: SHP - Welcome Gift | L14: Fixed price | M14: FixedPrice | Z14: Homepage Banner 3 | AD14: Homepage Banner 2 | AF14: Homepage Banner 3 | AG14: 398 x 115
D15: SHP - Repeat Buyer Voucher | I15: SHP - Sign-on Points Multiplier | Z15: Lazada Mall (Homepage Banner) | AD15: Homepage Banner 3 | AF15: Lazada Mall (Homepage Banner) | AG15: 390 x 463
D16: SHP - Follow Prize Voucher | I16: SHP - Exclusive Voucher | Z16: Shopee Mall (Homepage Banner) | AD16: Shopee Mall (Homepage Banner) | AF16: Shopee Mall (Homepage Banner) | AG16: 1200 x 600, 1200 x 969
D17: SHP - Exclusive Streamer Voucher | I17: SHP - Member Repeat Buyer | Z17: Lazada Category Banner | AD17: Shopee Mall (Homepage Banner) | AF17: Lazada Category Banner | AG17: 1360 x 480
I18: SHP - Member Exclusive Price | Z18: Livestream Banner | AD18: Shopee Groceries Category Banner (Category Homepage) | AF18: Livestream Banner | AG18: 500 x 500
I19: SHP - Gift Redemption | AD19: Livestream Banner | AF19: FB Post | AG19: 1000 x 1000
I20: SHP - Voucher Redemption | AF20: Affliate - SH | AG20: 1080 x 1080, 1080 x 1920, 160 x 600, 210 x 600, 250 x 300 , 300 x 250, 300 x 50, 320 x 50, 320 x 480, 728 x 90
I21: SHP - Points Multiplier Campaign | AF21: FEED | AG21: Perfect square 600 x 600 (Content similar to SIS Main Banner)
I22: SHP - Member Exclusive Product | AF22: Video | AG22: Max Width 1280px Max Height 1280px
AF23: Carousel | AG23: Max Width 2000px Max Height 2000px
AF24: Multiple Images | AG24: Max Width 2000px Max Height 2000px
A25: Hero/Non Hero | B25: Market | C25: Yes/No | D25: Division | E25: Single/VBOM/Bundle | G25: BRAND | H25: Dropdown | I25: Subsidy | J25: Request Type | K25: PRIORITISATION | L25: Main/Subproduct | M25: CPD | N25: PPD | P25: LLD | Q25: LDB | AF25: Banner and Category | AG25: Max Width 1200px Max Height 100px - 900px
A26: Hero | B26: Select Market | C26: Select from Dropdown | D26: Select Division | E26: Single | G26: Select Brand | H26: Select Promo Type | I26: Select from Dropdown | J26: Select Request Type | K26: Select Priority | L26: Select Product type | M26: OAP | N26: LORP | P26: LAN | Q26: LRP | AF26: Single Image | AG26: Max Width 1200px Max Height 100px - 2200px
A27: Non-Hero | B27: Thailand | C27: Yes | D27: CPD | E27: VBOM | G27: Garnier | H27: PROMO | I27: Partial | J27: New product Listing | K27: BAU | L27: Main Product | M27: MNY | N27: KER | P27: BIO | Q27: VIC | AF27: Multiple Clickable Ares | AG27: Max Width 1200px Max Height 100px - 2200px
C28: No | D28: PPD | E28: Bundle | G28: L'Oreal Paris | H28: FLASH | I28: Full | J28: Product Update | K28: Priority | L28: Sub-Product | M28: GAR | P28: SHU | Q28: CRV | AF28: Image Category List | AG28: Max Width 300px Max Height 300px
D29: LDB | G29: Maybelline | H29: CBMO | J29: Mega Campaign | K29: Super Priority | P29: KIE | Q29: SKC | AF29: Shopee Mall (Homepage Banner) | AG29: 390 x 463
D30: LLD | G30: 3CE | H30: BMO | J30: BAU Campaign | P30: ITC | AF30: Shopee Mall (Homepage Banner) | AG30: 1200 x 600 1200 x 969
G31: Lancome | H31: Others | J31: Adhoc Campaign | AF31: Shopee Groceries Category Banner (Category Homepage) | AG31: 1200 x 360
G32: Shu Uemura | J32: CPAS
G33: Kiehl's
G34: Biotherm
G35: It Cosmetics
G36: L'Oreal Professional
G37: Kerastase
G38: La Roche Posay
G39: Cerave
G40: Skinceuticals
G41: Vichy
G42: Matrix Biolage
D43: CPD
D44: PPD
D45: LDB | G45: CPD_Brands
D46: LLD | G46: PPD_Brands
G47: LDB_Brands
G48: LLD_Brands
D114: Regular: Price
D115: Regular: Gift Redemption
D116: Regular: Points Multiplier
D117: Regular: Exclusive Voucher

Sheet Data Quality Checklist
B2: Sheet | C2: Column | D2: Column Letter | E2: Rule | F2: Message | G2: Formula | H2: Error Check Type
B3: Campaign Calendar | C3: Start Date | D3: E | E3: DQ Rule # 3 : Start Date & End Date should follow dd-mmm-yyyy | F3: Formating Error. Please re-format as dd-mmm-yyyy e.g 01-Dec-2024 | G3: ISNUMBER(DATEVALUE(TEXT(A1,"dd-mmm-yy"))) | H3: Data Validation - Format
B4: Campaign Calendar | C4: End Date | D4: F | E4: DQ Rule # 3 : Start Date & End Date should follow dd-mmm-yyyy | F4: Formating Error. Please re-format as dd-mmm-yyyy e.g 01-Dec-2024 | G4: ISNUMBER(DATEVALUE(TEXT(A1,"dd-mmm-yy"))) | H4: Data Validation - Format
B5: Campaign Calendar | C5: Start Time | D5: G | E5: DQ Rule # 6 : Start Time & End Time should be formatted as h:mm. | F5: Formating Error. Please re-format as hh : mm AM / PM e.g 12 : 00 AM | G5: AND(ISNUMBER(TIMEVALUE(TEXT(A1,"hh:mm AM/PM"))),HOUR(A1)>=0,HOUR(A1)<24) | H5: Data Validation - Format
B6: Campaign Calendar | C6: End Time | D6: H | E6: DQ Rule # 6 : Start Time & End Time should be formatted as h:mm. | F6: Formating Error. Please re-format as hh : mm AM / PM e.g 12 : 00 AM | G6: AND(ISNUMBER(TIMEVALUE(TEXT(A1,"hh:mm AM/PM"))),HOUR(A1)>=0,HOUR(A1)<24) | H6: Data Validation - Format
B7: Campaign Calendar | C7: Campaign Type | D7: J | E7: DQ Rule # 7 : Campaign Type should follow defined categorical values. | F7: Please select from drop-down menu. To add more options, go to the Dropdown list tab and add the new option under Campaign Type | G7: NA | H7: Data Validation - List
B8: Campaign Calendar | C8: Campaign Tiering | D8: K | E8: DQ Rule # 7 : Campaign Type should follow defined categorical values. | F8: Please select from drop-down menu. To add more options, go to the Dropdown list tab and add the new option under Campaign Tiering | G8: NA | H8: Data Validation - List
B9: Price Change | C9: EAN Code | D9: B | E9: DQ Rule # 10 : EAN Code should only contain digits (0-9), not alphabets or special characters. | F9: EAN, Product and Variation code MUST only contain digits (0-9), non alphabets or special characters | G9: NA | H9: Data Validation - Whole Number
B10: Price Change | C10: EAN Code | D10: B | E10: DQ Rule # 11 : There should only be 1 row per EAN code (i.e. EAN codes should not be repeated/duplicated) | F10: Red Highlight | G10: NA | H10: Conditional Formatting - Duplication
B11: Price Change | C11: Variation ID | D11: E | E11: DQ Rule # 11 : There should only be 1 row per EAN code (i.e. EAN codes should not be repeated/duplicated) | F11: Red Highlight | G11: NA | H11: Conditional Formatting - Duplication
B12: Price Change | C12: Product ID | D12: D | E12: DQ Rule # 12 : Product ID & Variation ID should only contain digits (0-9), no alphabets or special characters. | F12: EAN, Product and Variation code MUST only contain digits (0-9), non alphabets or special characters | G12: NA | H12: Data Validation - Whole Number
B13: Price Change | C13: Variation ID | D13: E | E13: DQ Rule # 12 : Product ID & Variation ID should only contain digits (0-9), no alphabets or special characters. | F13: EAN, Product and Variation code MUST only contain digits (0-9), non alphabets or special characters | G13: NA | H13: Data Validation - Whole Number
... B16: Price Change | C16: Promo Discount % | D16: S | E16: DQ Rule 18 : Promo Discount % should be: 0 <= Promo Discount % < 1 | F16: Price Discount must be within 0 % to 70%. Please validate the L'Oreal Recommended Price, Discount or Campaign Price | G16: AND(A1>=0, A1<0.7) | H16: Data Validation - Custom

Sheet Campaign Calendar
C1: Type of Input require | D1: *Mandatory Fields | M1: SVC Use Only >>> Status of Data Entry
D2: Optional Fields | M2: Awaiting Confirmation | N2: =COUNTIF($L11:$L53, M2) / COUNTIF($J11:$J53,"<>")
D3: Dropdown | M3: Pending | N3: =COUNTIF($L11:$L53, M3) / COUNTIF($J11:$J53,"<>")
M4: On Hold | N4: =COUNTIF($L11:$L53, M4) / COUNTIF($J11:$J53,"<>")
M5: Completed | N5: =COUNTIF($L11:$L53, M5) / COUNTIF($J11:$J53,"<>")
M6: Cancelled | N6: =COUNTIF($L11:$L53, M6) / COUNTIF($J11:$J53,"<>")
D7: Dropdown | E7: DQ - Format | F7: DQ - Format | G7: DQ - Format | H7: DQ - Format | I7: DQ - Duplicate
C8: PLEASE INPUT ALL MANDATORY FIELDS FOR DROP-DOWN & AUTOFILLS
C9: Select from drop-down menu | D9: Enter full brand name | E9: Enter Start Date as dd-MMM-yyyy e.g 03-Apr-2024 | F9: Enter End Date as dd-MMM-yyyy e.g 03-Apr-2024 | G9: Enter Start time as hh:mm:ss e.g 23:59:59 | H9: Enter End time as hh:mm:ss e.g 23:59:59 | I9: Enter Unique Campaign Name. Must not be duplicated to avoid errors in price change. E.g Payday 25 Apr, Payday 26-31 Apr | J9: Enter Generic Campaign Type Name E.g Double Date, Teasing, Payday | K9: Enter Tiers that will be applied for the campaign. E.g "MG", "T1, 2.5 , T3 + 5.-", "10%" | L9: For Service center use only.
C10: Platform | D10: Brand | E10: Start Date | F10: End Date | G10: Start Time | H10: End Time | I10: Campaign Name | J10: Campaign Type | K10: Campaign Tiering | L10: Price Change Status
C11: Lazada | D11: Loreal Paris | E11: 46082 | F11: 46112 | G11: 0 | H11: 0.99930556 | I11: BAU Full Day | J11: BAU
C12: Lazada | D12: Loreal Paris | E12: 46082 | F12: 46112 | G12: 0 | H12: 0.99930556 | I12: BAU Laz Flash | J12: BAU
C13: Lazada | D13: Loreal Paris | E13: 46082 | F13: 46112 | G13: 0 | H13: 0.99930556 | I13: Mar Membership | J13: Members
C14: Lazada | D14: Loreal Paris | E14: 46083 | F14: 46086 | G14: 0.83333333 | H14: 0.99930556 | I14: 3.3 Sale x Raya Full Day | J14: Double Digit (Mega)
C15: Lazada | D15: Loreal Paris | E15: 46083 | F15: 46086 | G15: 0.83333333 | H15: 0.99930556 | I15: 3.3 Sale x Raya CBMO | J15: Double Digit (Mega)
C16: Lazada | D16: Loreal Paris | E16: 46083 | F16: 46086 | G16: 0.83333333 | H16: 0.99930556 | I16: 3.3 Sale x Raya Laz Flash | J16: Double Digit (Mega)
C17: Lazada | D17: Loreal Paris | E17: 46095 | F17: 46098 | G17: 0.83333333 | H17: 0.99930556 | I17: MMS x Raya Full Day | J17: MMS
C18: Lazada | D18: Loreal Paris | E18: 46095 | F18: 46098 | G18: 0.83333333 | H18: 0.99930556 | I18: MMS x Raya CMBO | J18: MMS
C19: Lazada | D19: Loreal Paris | E19: 46095 | F19: 46098 | G19: 0.83333333 | H19: 0.99930556 | I19: MMS x Raya Laz Flash | J19: MMS
C20: Lazada | D20: Loreal Paris | E20: 46105 | F20: 46108 | G20: 0.83333333 | H20: 0.99930556 | I20: PDS x Birthday Full Day | J20: PDS (Mega)
C21: Lazada | D21: Loreal Paris | E21: 46105 | F21: 46108 | G21: 0.83333333 | H21: 0.99930556 | I21: PDS x Birthday CMBO | J21: PDS (Mega)
C22: Lazada | D22: Loreal Paris | E22: 46105 | F22: 46108 | G22: 0.83333333 | H22: 0.99930556 | I22: PDS x Birthday Laz Flash | J22: PDS (Mega)

Sheet Price Change- NFlash+FlashTB TH
B1: Type of Input required | C1: *Mandatory Fields
C2: Optional Fields
C3: Dropdown
C4: Autofill
B5: *Please take note for any input with double pricing with same date/duration, SVC will submit the lowest price
Q16: PLANNING BY CAMPAIGN Name PLEASE SELECT CAMPAIGN NAME, CAMPAIGN TYPE & CAMPAIGN TIERING
Q17: Campaign Name* | R17: Campaign 1 | T17: Campaign Name* | U17: Campaign 2 | W17: Campaign Name* | X17: Campaign 3 | Z17: Campaign Name* | AA17: Campaign 4
Q18: Campaign Type | R18: SMG | T18: Campaign Type | U18: A+ | W18: Campaign Type | X18: BAU | Z18: Campaign Type | AA18: SMG
Q19: Campaign Tiering | R19: 1 | T19: Campaign Tiering | U19: 2 | W19: Campaign Tiering | X19: 3 | Z19: Campaign Tiering | AA19: 1
Q20: Start Date | R20: 45383 | T20: Date | U20: {=IFERROR(_xlfn.TEXTJOIN(", ", TRUE, IF((U$17='Campaign Calendar'!$I$11:$I$45)*(U$18='Campaign Calendar'!$J$11:$J$45)*(U$19='Campaign Calendar'!$K$11:$K$45),'Campaign Calendar'!#REF!, "")), "")} | W20: Date | X20: {=IFERROR(_xlfn.TEXTJOIN(", ", TRUE, IF((X$17='Campaign Calendar'!$I$11:$I$45)*(X$18='Campaign Calendar'!$J$11:$J$45)*(X$19='Campaign Calendar'!$K$11:$K$45),'Campaign Calendar'!#REF!, "")), "")} | Z20: Date | AA20: {=IFERROR(_xlfn.TEXTJOIN(", ", TRUE, IF((AA$17='Campaign Calendar'!$I$11:$I$45)*(AA$18='Campaign Calendar'!$J$11:$J$45)*(AA$19='Campaign Calendar'!$K$11:$K$45),'Campaign Calendar'!#REF!, "")), "")}
Q21: End Date | R21: 04/04/2024 | T21: Date | U21: {=IFERROR(_xlfn.TEXTJOIN(", ", TRUE, IF((U$17='Campaign Calendar'!$I$11:$I$45)*(U$18='Campaign Calendar'!$J$11:$J$45)*(U$19='Campaign Calendar'!$K$11:$K$45),'Campaign Calendar'!#REF!, "")), "")} | W21: Date | X21: {=IFERROR(_xlfn.TEXTJOIN(", ", TRUE, IF((X$17='Campaign Calendar'!$I$11:$I$45)*(X$18='Campaign Calendar'!$J$11:$J$45)*(X$19='Campaign Calendar'!$K$11:$K$45),'Campaign Calendar'!#REF!, "")), "")} | Z21: Date | AA21: {=IFERROR(_xlfn.TEXTJOIN(", ", TRUE, IF((AA$17='Campaign Calendar'!$I$11:$I$45)*(AA$18='Campaign Calendar'!$J$11:$J$45)*(AA$19='Campaign Calendar'!$K$11:$K$45),'Campaign Calendar'!#REF!, "")), "")}
Q22: Start Time | R22: 00,00 | T22: Time | U22: {=IFERROR(_xlfn.TEXTJOIN(", ", TRUE, IF((U$17='Campaign Calendar'!$I$11:$I$45)*(U$18='Campaign Calendar'!$J$11:$J$45)*(U$19='Campaign Calendar'!$K$11:$K$45),'Campaign Calendar'!#REF!, "")), "")} | W22: Time | X22: {=IFERROR(_xlfn.TEXTJOIN(", ", TRUE, IF((X$17='Campaign Calendar'!$I$11:$I$45)*(X$18='Campaign Calendar'!$J$11:$J$45)*(X$19='Campaign Calendar'!$K$11:$K$45),'Campaign Calendar'!#REF!, "")), "")} | Z22: Time | AA22: {=IFERROR(_xlfn.TEXTJOIN(", ", TRUE, IF((AA$17='Campaign Calendar'!$I$11:$I$45)*(AA$18='Campaign Calendar'!$J$11:$J$45)*(AA$19='Campaign Calendar'!$K$11:$K$45),'Campaign Calendar'!#REF!, "")), "")}
Q23: End Time | R23: 02,00 | T23: Time | U23: {=IFERROR(_xlfn.TEXTJOIN(", ", TRUE, IF((U$17='Campaign Calendar'!$I$11:$I$45)*(U$18='Campaign Calendar'!$J$11:$J$45)*(U$19='Campaign Calendar'!$K$11:$K$45),'Campaign Calendar'!#REF!, "")), "")} | W23: Time | X23: {=IFERROR(_xlfn.TEXTJOIN(", ", TRUE, IF((X$17='Campaign Calendar'!$I$11:$I$45)*(X$18='Campaign Calendar'!$J$11:$J$45)*(X$19='Campaign Calendar'!$K$11:$K$45),'Campaign Calendar'!#REF!, "")), "")} | Z23: Time | AA23: {=IFERROR(_xlfn.TEXTJOIN(", ", TRUE, IF((AA$17='Campaign Calendar'!$I$11:$I$45)*(AA$18='Campaign Calendar'!$J$11:$J$45)*(AA$19='Campaign Calendar'!$K$11:$K$45),'Campaign Calendar'!#REF!, "")), "")}
Q24: Treasure Bowl Name* | T24: Treasure Bowl Name* | W24: Treasure Bowl Name* | Z24: Treasure Bowl Name*
Q25: Treasure Bowl ID* | T25: Treasure Bowl ID* | W25: Treasure Bowl ID* | Z25: Treasure Bowl ID*
Q26: Promotion Plan File/Folder* | R26: Share the relevant Link | T26: Promotion Plan File/Folder* | U26: Share the relevant Link | W26: Promotion Plan File/Folder* | X26: Share the relevant Link | Z26: Promotion Plan File/Folder* | AA26: Share the relevant Link
Q27: Relevant files for SVC | T27: Relevant files for SVC | W27: Relevant files for SVC | Z27: Relevant files for SVC
B28: EAN Code | C28: Product ID | D28: Variation ID | E28: Product Name | F28: Brand | G28: VBOM/Single/Bundle | H28: Product Url | I28: Lowest Sales Price(30day) | J28: Average Sales Price (30day) | K28: Lowest Onsite Price(30day) | L28: Average Onsite Price(30day) | M28: Category Name | N28: Lazada Recommend | O28: Stock | P28: L'Oreal recommended Price (list price) | Q28: Campaign Price | R28: Promo Discount % | S28: Tier | T28: Campaign Price | U28: Promo Discount % | V28: Tier | W28: Campaign Price | X28: Promo Discount % | Y28: Tier | Z28: Campaign Price | AA28: Promo Discount % | AB28: Tier
G29: Select from Dropdown
G30: Select from Dropdown
G31: Select from Dropdown
G32: Select from Dropdown
G33: Select from Dropdown
G34: Select from Dropdown
G35: Select from Dropdown
G36: Select from Dropdown
G37: Select from Dropdown
G38: Select from Dropdown
G39: Select from Dropdown
G40: Select from Dropdown
... G297: Select from Dropdown

Sheet Price Change - draft
B1: Type of Input require | C1: *Mandatory Fields | F1: Changes done as per feedback
C2: Optional Fields
C3: Dropdown
B4: *Please take note for any input with double pricing with same date/duration, SVC will submit the lowest price
R13: Flash Sale Pricing
R14: Promotion Type: BAU | T14: Promotion Type: CP | V14: Promotion Type: MG | X14: Promotion Type: SMG
R15: Campaign Name* | S15: BAU | T15: Campaign Name* | U15: CP | V15: Campaign Name* | W15: MG | X15: Campaign Name* | Y15: SMG
R16: Campaign Type | T16: Campaign Type | V16: Campaign Type | X16: Campaign Type
R17: Campaign Tiering | T17: Campaign Tiering | V17: Campaign Tiering | X17: Campaign Tiering
R18: Platform | S18: Lazada | T18: Platform | U18: Lazada | V18: Platform | W18: Lazada | X18: Platform | Y18: Lazada
R19: Treasure Bowl Name* | T19: Treasure Bowl Name* | V19: Treasure Bowl Name* | X19: Treasure Bowl Name*
R20: Treasure Bowl ID* | T20: Treasure Bowl ID* | V20: Treasure Bowl ID* | X20: Treasure Bowl ID*
R21: Promotion Plan File/Folder* | S21: Share the relevant Link | T21: Promotion Plan File/Folder* | U21: Share the relevant Link | V21: Promotion Plan File/Folder* | W21: Share the relevant Link | X21: Promotion Plan File/Folder* | Y21: Share the relevant Link
R22: Relevant files for SVC | T22: Relevant files for SVC | V22: Relevant files for SVC | X22: Relevant files for SVC
R23: Duration (Redemption Date) | S23: Mar 22 - 23 ; Mar 27 - 28 | T23: Duration | U23: List of dates | V23: Duration | W23: List of dates | X23: Duration | Y23: List of dates
R24: Live Date (Collection Date)
R25: Times | S25: 12pm - 12am | T25: Times | U25: List of hours | V25: Times | W25: List of hours | X25: Times | Y25: List of hours
B26: EAN Code | C26: Product ID | D26: Brand | E26: Variation ID | F26: Product Name | G26: Product Url | H26: Lowest Sales Price(30day) | I26: Average Sales Price (30day) | J26: Lowest Onsite Price(30day) | K26: Average Onsite Price(30day) | L26: Category Name | M26: Lazada Recommend | N26: Campaign Stock | O26: Current Stock | P26: Purchase Limit | Q26: L'Oreal recommended Price (list price) | R26: Campaign Price | S26: Promo Discount % | T26: Campaign Price | U26: Promo Discount % | V26: Campaign Price | W26: Promo Discount % | X26: Campaign Price | Y26: Promo Discount %
B27: 6902395841531 | C27: 252026229 | E27: 333654656 | J27: 200 | K27: 250 | M27: 200 | Q27: 240 | R27: 230 | S27: =1-R27/Q27 | T27: 200 | U27: =1-T27/Q27 | V27: 180 | W27: =1-V27/Q27 | X27: 230 | Y27: =1-X27/Q27
S28: =1-Q28/N28 | U28: =1-S28/R28 | W28: =1-U28/T28 | Y28: =1-W28/V28
S29: =1-Q29/N29 | U29: =1-S29/R29 | W29: =1-U29/T29 | Y29: =1-W29/V29
S30: =1-Q30/N30 | U30: =1-S30/R30 | W30: =1-U30/T30 | Y30: =1-W30/V30
S31: =1-Q31/N31 | U31: =1-S31/R31 | W31: =1-U31/T31 | Y31: =1-W31/V31
S32: =1-Q32/N32 | U32: =1-S32/R32 | W32: =1-U32/T32 | Y32: =1-W32/V32
S33: =1-Q33/N33 | U33: =1-S33/R33 | W33: =1-U33/T33 | Y33: =1-W33/V33
S34: =1-Q34/N34 | U34: =1-S34/R34 | W34: =1-U34/T34 | Y34: =1-W34/V34
S35: =1-Q35/N35 | U35: =1-S35/R35 | W35: =1-U35/T35 | Y35: =1-W35/V35
S36: =1-Q36/N36 | U36: =1-S36/R36 | W36: =1-U36/T36 | Y36: =1-W36/V36
S37: =1-Q37/N37 | U37: =1-S37/R37 | W37: =1-U37/T37 | Y37: =1-W37/V37
S38: =1-Q38/N38 | U38: =1-S38/R38 | W38: =1-U38/T38 | Y38: =1-W38/V38
S39: =1-Q39/N39 | U39: =1-S39/R39 | W39: =1-U39/T39 | Y39: =1-W39/V39
... S222: =1-Q222/N222 | U222: =1-S222/R222 | W222: =1-U222/T222 | Y222: =1-W222/V222

Sheet Price Change sample
D1: Mar'23 | H1: COLOR = general promo depth -> | I1: 1-31th March BAU
H2: DATES -> | I2: BAU
A3: Product ID | B3: Variation ID | C3: EAN | D3: Product Name | E3: Q1'22 SALES | F3: SIGNATURE | G3: SUB-CAT | H3: RSP | I3: Discount % | J3: Selling Price (RM)
A4: 9397537065 | B4: 133126149553 | C4: 6902395827375 | D4: Maybelline City Mini Palette Eyeshadow - Uncaged Limited Edition | E4: 67.647 | F4: MNY | G4: #N/A | H4: 49.90 | I4: 0.15 | J4: 42.42
A5: 948488398 | B5: 21398836447 | C5: 6923700958621 | D5: L’Oreal Paris Revitalift Triple Action Renewing Anti Aging Serum 30ml | E5: 34.75 | F5: OAP | G5: Dermacare | H5: 111.00 | I5: 0.2 | J5: 88.80
A6: 11855541892 | B6: 112868167378 | C6: 9557534757043 | D6: Maybelline Cushion Matte Midnight Strike Limited Edition Liquid Lipstick Gift Box | E6: 16.883 | F6: MNY | G6: #N/A | H6: 39.90 | I6: 0.1 | J6: 35.91
A7: 265677745 | B7: 70099846367 | C7: 6902395439967 | D7: Maybelline The Blushed Nudes Eyeshadow Palette | E7: 9.452 | F7: MNY | G7: Eyes | H7: 72.90 | I7: 0.05 | J7: 69.26
A8: 11278765734 | B8: 123136166329 | C8: 6902395827405 | D8: Maybelline Color Sensational Cushion Matte Liquid Lipstick Limited Edition | E8: 13.26 | F8: MNY | G8: #N/A | H8: 36.90 | I8: 0.15 | J8: 31.37
A9: 11278765734 | B9: 123136166330 | C9: 6902395827382 | D9: Maybelline Color Sensational Cushion Matte Liquid Lipstick Limited Edition | E9: 13.26 | F9: MNY | G9: #N/A | H9: 36.90 | I9: 0.15 | J9: 31.37
A10: 11278765734 | B10: 123136166331 | C10: 6902395827399 | D10: Maybelline Color Sensational Cushion Matte Liquid Lipstick Limited Edition | E10: 7.471 | F10: MNY | G10: #N/A | H10: 36.90 | I10: 0.15 | J10: 31.37
A11: 266124670 | B11: 174238536 | C11: 6902395336112 | D11: Maybelline Lip And Eye Makeup Remover (Makeup Remover, Make Up Remover) | E11: 17.225 | F11: MNY | G11: Makeup Removers | H11: 35.90 | I11: 0.05 | J11: 34.11
A12: 4158297552 | B12: 41461315230 | C12: 9557534752871 | D12: L'Oreal Paris Revitalift Hyaluronic Acid Plumping Serum (Plump, Smooth, Radiance) 30mlx2 | E12: 15.892 | F12: OAP | G12: Dermacare | H12: 209.80 | I12: 0.3 | J12: 146.86
A13: 3841446650 | B13: 60223940597 | C13: 9557534751454 | D13: L'Oreal Paris Revitalift Anti Aging Day & Night Cream Skincare Set (50ml) | E13: 57.605 | F13: OAP | G13: Facial Moisturizers | H13: 161.00 | I13: 0.3 | J13: 112.70
A14: 5475936549 | B14: 53328264466 | C14: 6923700969245 | D14: L'Oreal Paris Revitalift Filler Hyaluronic Acid Eye Cream for Face | E14: 49.159 | F14: OAP | G14: Eye Treatment | H14: 244.50 | I14: 0.2 | J14: 195.60
A15: 5441350840 | B15: 60223983681 | C15: 9557534751379 | D15: L'Oreal Paris Elseve Extraordinary Oil Hair Treatment Set - Pink (100ml) | E15: 36.998 | F15: OAP | G15: Hair Care | H15: 115.00 | I15: 0.15 | J15: 97.75
A16: 266279479 | B16: 50442650214 | C16: 6928820034088 | D16: Maybelline Micellar Water Makeup Remover (400ml) | E16: - | F16: MNY | G16: Makeup Removers | H16: 36.90 | I16: 0.05 | J16: 35.06
A17: 309019438 | B17: 73686525064 | C17: 6902395774419 | D17: Maybelline Fit Me Matte + Poreless Liquid Foundation SPF 22 30ml (Fit Me Foundation, Maybelline Foundation, Fit Me) | E17: - | F17: MNY | G17: Face | H17: 56.90 | I17: 0.2 | J17: 45.52
A18: 309019438 | B18: 16694366230 | C18: 6902395774259 | D18: Maybelline Fit Me Matte + Poreless Liquid Foundation SPF 22 30ml (Fit Me Foundation, Maybelline Foundation, Fit Me) | E18: 183.031 | F18: MNY | G18: Face | H18: 56.90 | I18: 0.2 | J18: 45.52
A19: 309019438 | B19: 16694366235 | C19: 6902395774310 | D19: Maybelline Fit Me Matte + Poreless Liquid Foundation SPF 22 30ml (Fit Me Foundation, Maybelline Foundation, Fit Me) | E19: 183.031 | F19: MNY | G19: Face | H19: 56.90 | I19: 0.2 | J19: 45.52
A20: 309019438 | B20: 16694366227 | C20: 6902395774228 | D20: Maybelline Fit Me Matte + Poreless Liquid Foundation SPF 22 30ml (Fit Me Foundation, Maybelline Foundation, Fit Me) | E20: 183.031 | F20: MNY | G20: Face | H20: 56.90 | I20: 0.2 | J20: 45.52
A21: 309019438 | B21: 16694366232 | C21: 6902395774280 | D21: Maybelline Fit Me Matte + Poreless Liquid Foundation SPF 22 30ml (Fit Me Foundation, Maybelline Foundation, Fit Me) | E21: 183.031 | F21: MNY | G21: Face | H21: 56.90 | I21: 0.2 | J21: 45.52
A22: 309019438 | B22: 16694366231 | C22: 6902395774273 | D22: Maybelline Fit Me Matte + Poreless Liquid Foundation SPF 22 30ml (Fit Me Foundation, Maybelline Foundation, Fit Me) | E22: 183.031 | F22: MNY | G22: Face | H22: 56.90 | I22: 0.2 | J22: 45.52
A23: 309019438 | B23: 16694366229 | C23: 6902395774242 | D23: Maybelline Fit Me Matte + Poreless Liquid Foundation SPF 22 30ml (Fit Me Foundation, Maybelline Foundation, Fit Me) | E23: 183.031 | F23: MNY | G23: Face | H23: 56.90 | I23: 0.2 | J23: 45.52
A24: 309019438 | B24: 16694366226 | C24: 6902395774211 | D24: Maybelline Fit Me Matte + Poreless Liquid Foundation SPF 22 30ml (Fit Me Foundation, Maybelline Foundation, Fit Me) | E24: 183.031 | F24: MNY | G24: Face | H24: 56.90 | I24: 0.2 | J24: 45.52
A25: 309019438 | B25: 17095752848 | C25: 6902395774426 | D25: Maybelline Fit Me Matte + Poreless Liquid Foundation SPF 22 30ml (Fit Me Foundation, Maybelline Foundation, Fit Me) | E25: 183.031 | F25: MNY | G25: Face | H25: 56.90 | I25: 0.2 | J25: 45.52
A26: 309019438 | B26: 17095752849 | C26: 6902395774433 | D26: Maybelline Fit Me Matte + Poreless Liquid Foundation SPF 22 30ml (Fit Me Foundation, Maybelline Foundation, Fit Me) | E26: 183.031 | F26: MNY | G26: Face | H26: 56.90 | I26: 0.2 | J26: 45.52
A27: 309019438 | B27: 16692848450 | C27: 6902395774204 | D27: Maybelline Fit Me Matte + Poreless Liquid Foundation SPF 22 30ml (Fit Me Foundation, Maybelline Foundation, Fit Me) | E27: 183.031 | F27: MNY | G27: Face | H27: 56.90 | I27: 0.2 | J27: 45.52
A28: 309019438 | B28: 16694366233 | C28: 6902395774297 | D28: Maybelline Fit Me Matte + Poreless Liquid Foundation SPF 22 30ml (Fit Me Foundation, Maybelline Foundation, Fit Me) | E28: 183.031 | F28: MNY | G28: Face | H28: 56.90 | I28: 0.2 | J28: 45.52
A29: 309019438 | B29: 17095752843 | C29: 6902395774389 | D29: Maybelline Fit Me Matte + Poreless Liquid Foundation SPF 22 30ml (Fit Me Foundation, Maybelline Foundation, Fit Me) | E29: 183.031 | F29: MNY | G29: Face | H29: 56.90 | I29: 0.2 | J29: 45.52
... A59: 265748568 | B59: 70442656336 | C59: 6902395420934 | D59: Maybelline Hypersharp Power Black Liquid Eyeliner - Black | E59: 79.05 | F59: MNY | G59: Eyes | H59: 33.90 | I59: 0.2 | J59: 27.12
A60: 977370760 | B60: 829500919 | C60: 6902395629511 | D60: Maybelline The City Mini Palette Eyeshadow | E60: 15.265 | F60: MNY | G60: #N/A | H60: 51.90 | I60: 0.2 | J60: 41.52
A61: 977370760 | B61: 2380981835 | C61: 6902395697350 | D61: Maybelline The City Mini Palette Eyeshadow | E61: 3.11 | F61: MNY | G61: Makeup Palettes & Sets | H61: 51.90 | I61: 0.2 | J61: 41.52
A62: 2078672226 | B62: 3758068279 | C62: 6902395685708 | D62: Maybelline Superstay 24H Full Coverage Foundation 30ml (Makeup, Face Makeup, Matte Foundation) | E62: 61.62 | F62: MNY | G62: Face | H62: 65.90 | I62: 0.2 | J62: 52.72
A63: 2078672226 | B63: 3758068280 | C63: 6902395685715 | D63: Maybelline Superstay 24H Full Coverage Foundation 30ml (Makeup, Face Makeup, Matte Foundation) | E63: 61.62 | F63: MNY | G63: Face | H63: 65.90 | I63: 0.2 | J63: 52.72
A64: 4847103325 | B64: 60638042447 | C64: 9557534752192 | D64: L'Oreal Paris Revitalift Crystal Micro Essence Set of 2 (130ml) Glowing skin Lotion Brightening Essence Loreal Paris | E64: 19.851 | F64: OAP | G64: Dermacare | H64: 182.00 | I64: 0.2 | J64: 145.60
A65: 2078672226 | B65: 3758068278 | C65: 6902395685692 | D65: Maybelline Superstay 24H Full Coverage Foundation 30ml (Makeup, Face Makeup, Matte Foundation) | E65: 61.62 | F65: MNY | G65: Face | H65: 65.90 | I65: 0.2 | J65: 52.72
A66: 2078672226 | B66: 3758068282 | C66: 6902395685739 | D66: Maybelline Superstay 24H Full Coverage Foundation 30ml (Makeup, Face Makeup, Matte Foundation) | E66: 61.62 | F66: MNY | G66: Face | H66: 65.90 | I66: 0.2 | J66: 52.72
A67: 2078672226 | B67: 3758068284 | C67: 6902395685753 | D67: Maybelline Superstay 24H Full Coverage Foundation 30ml (Makeup, Face Makeup, Matte Foundation) | E67: 61.62 | F67: MNY | G67: Face | H67: 65.90 | I67: 0.2 | J67: 52.72
A68: 2078672226 | B68: 3758068283 | C68: 6902395685746 | D68: Maybelline Superstay 24H Full Coverage Foundation 30ml (Makeup, Face Makeup, Matte Foundation) | E68: 61.62 | F68: MNY | G68: Face | H68: 65.90 | I68: 0.2 | J68: 52.72
A69: 1955202226 | B69: 212512442109 | C69: 6902395839903 | D69: Maybelline Superstay Matte Ink 16H Long Wear Liquid Lipstick Free Fire Edition | F69: MNY | G69: #N/A | H69: 42.90 | I69: 0.3 | J69: 30.03
A70: 1955202226 | B70: 212512442110 | C70: 6902395839910 | D70: Maybelline Superstay Matte Ink 16H Long Wear Liquid Lipstick Free Fire Edition | F70: MNY | G70: #N/A | H70: 42.90 | I70: 0.3 | J70: 30.03
A71: 6747103220 | B71: 50638128974 | C71: 9557534752208 | D71: L'Oreal Paris Revitalift Anti Aging Day Cream SPF35 Set of 2 (50ml) | E71: 15.249 | F71: OAP | G71: Facial Moisturizers | H71: 150.00 | I71: 0.2 | J71: 120.00
A72: 2384341833 | B72: 4865367568 | C72: 6923700934458 | D72: L'Oreal Paris Revitalift Crystal Micro Essence 65ml/130ml | E72: 47.092 | F72: OAP | G72: Dermacare | H72: 91.00 | I72: 0.2 | J72: 72.80
A73: 3792009544 | B73: 55963826005 | C73: 6923700981209 | D73: L'Oréal Paris Revitalift Hyaluronic Acid Plumping Day Cream-Face Cream/Moisturizer | E73: 44.042 | F73: OAP | G73: Facial Moisturizers | H73: 97.90 | I73: 0.2 | J73: 78.32
A74: 948567186 | B74: 70442650952 | C74: 6955818247106 | D74: L'Oreal Paris Aura Perfect Clinical Derm Aura Serum | E74: 37.966 | F74: OAP | G74: Dermacare | H74: 100.00 | I74: 0.2 | J74: 80.00
A75: 16256455064 | B75: 162189947187 | C75: 6923700974379 | D75: L’Oreal Paris Youth Code Skin Activating Ferment Pre-Essence (30ml) | E75: 35.172 | F75: OAP | G75: Dermacare | H75: 193.00 | I75: 0.2 | J75: 154.40
A76: 5348531519 | B76: 30739413678 | C76: 6923700966701 | D76: L'Oreal Paris Revitalift Hyaluronic Acid Plumping Serum (Plump, Smooth, Radiance) | E76: 68.09 | F76: OAP | G76: Dermacare | H76: 104.90 | I76: 0.3 | J76: 73.43
A77: 14455424857 | B77: 160320773972 | C77: 6923700970593 | D77: L'Oreal Paris Revitalift Centella Micro-Essence Water (130ml) - Serum | E77: 18.745 | F77: OAP | G77: Dermacare | H77: 86.90 | I77: 0.1 | J77: 78.21
A78: 8819751162 | B78: 63890082609 | C78: 9557534754899 | D78: L'Oreal Paris Revitalift Hyaluronic Acid Plumping Fresh Mix Serum Mask x5 | E78: 12.529 | F78: OAP | G78: Face Mask & Packs | H78: 78.50 | I78: 0.2 | J78: 62.80
A79: 948567185 | B79: 50442657503 | C79: 8994993009763 | D79: L’Oreal Paris Revitalift Triple Action Anti-Aging Day Cream 50ml | E79: 20.266 | F79: OAP | G79: Facial Moisturizers | H79: 98.00 | I79: 0.2 | J79: 78.40
A80: 11910069788 | B80: 65849351931 | C80: 6902395807346 | D80: L’Oréal Paris Chiffon Signature Velvet Soft-Matte Liquid Lipstick | E80: 29.552 | F80: OAP | G80: Lips | H80: 57.90 | I80: 0.2 | J80: 46.32
A81: 11910069788 | B81: 65849351932 | C81: 6902395807407 | D81: L’Oréal Paris Chiffon Signature Velvet Soft-Matte Liquid Lipstick | E81: 29.552 | F81: OAP | G81: Lips | H81: 54.90 | I81: 0.2 | J81: 43.92
A82: 11910069788 | B82: 65849351933 | C82: 6902395807353 | D82: L’Oréal Paris Chiffon Signature Velvet Soft-Matte Liquid Lipstick | E82: 29.552 | F82: OAP | G82: Lips | H82: 57.90 | I82: 0.2 | J82: 46.32
... A96: 2078366828 | B96: 60148622345 | C96: 6902395784388 | D96: L'Oreal Paris Rouge Signature Matte Liquid Lipstick (Lip Matte, Matte Lipstick) | E96: 55.599 | F96: OAP | G96: Lips | H96: 57.90 | I96: 0.2 | J96: 46.32
A97: 1955202226 | B97: 212512442111 | C97: 6902395839934 | D97: Maybelline Superstay Matte Ink 16H Long Wear Liquid Lipstick Free Fire Edition | F97: MNY | G97: #N/A | H97: 42.90 | I97: 0.3 | J97: 30.03
A98: 1955202226 | B98: 212512442112 | C98: 6902395837862 | D98: Maybelline Superstay Matte Ink 16H Long Wear Liquid Lipstick Free Fire Edition | F98: MNY | G98: #N/A | H98: 42.90 | I98: 0.3 | J98: 30.03
A99: 1955202226 | B99: 212512442113 | C99: 6902395837848 | D99: Maybelline Superstay Matte Ink 16H Long Wear Liquid Lipstick Free Fire Edition | F99: MNY | G99: #N/A | H99: 42.90 | I99: 0.3 | J99: 30.03
A100: 6195347782 | B100: 66579131450 | C100: 6902395806431 | D100: NEW Maybelline Fit Me Matte + Poreless Powder Foundation | E100: 75.516 | F100: MNY | G100: Face | H100: 59.90 | I100: 0.15 | J100: 50.92
A101: 2078366828 | B101: 60148622346 | C101: 6902395784357 | D101: L'Oreal Paris Rouge Signature Matte Liquid Lipstick (Lip Matte, Matte Lipstick) | E101: 55.599 | F101: OAP | G101: Lips | H101: 57.90 | I101: 0.2 | J101: 46.32
A102: 2078366828 | B102: 60148622347 | C102: 6902395784340 | D102: L'Oreal Paris Rouge Signature Matte Liquid Lipstick (Lip Matte, Matte Lipstick) | E102: 55.599 | F102: OAP | G102: Lips | H102: 57.90 | I102: 0.2 | J102: 46.32
A103: 2078366828 | B103: 60148622348 | C103: 6902395784333 | D103: L'Oreal Paris Rouge Signature Matte Liquid Lipstick (Lip Matte, Matte Lipstick) | E103: 55.599 | F103: OAP | G103: Lips | H103: 57.90 | I103: 0.2 | J103: 46.32
A104: 2078366828 | B104: 60148622349 | C104: 6902395784371 | D104: L'Oreal Paris Rouge Signature Matte Liquid Lipstick (Lip Matte, Matte Lipstick) | E104: 55.599 | F104: OAP | G104: Lips | H104: 57.90 | I104: 0.2 | J104: 46.32
A105: 948488307 | B105: 40442656930 | C105: 4992944111576 | D105: L'Oreal Paris Elseve Extraordinary Oil Gold 100ml (All Hair Types, Hair Treatment, Hair Oil) | E105: 50.008 | F105: OAP | G105: Hair Care | H105: 59.90 | I105: 0.2 | J105: 47.92
A106: 948488327 | B106: 40442656920 | C106: 4935421260053 | D106: L'Oreal Paris Elseve Extraordinary Oil Pink 100ml (Very Dry Hair, Hair Treatment, Hair Oil) | E106: 16.352 | F106: OAP | G106: Hair Care | H106: 59.90 | I106: 0.2 | J106: 47.92
A107: 15146069460 | B107: 142167351287 | C107: 9557534759320 | D107: L'Oreal Paris Glyco Bright Instant Glowing Serum Mask x5 | E107: - | F107: OAP | G107: Face Mask & Packs | H107: 67.50 | I107: 0.2 | J107: 54.00
A108: 2384341833 | B108: 4865367567 | C108: 6923700934489 | D108: L'Oreal Paris Revitalift Crystal Micro Essence 65ml/130ml | E108: 47.092 | F108: OAP | G108: Dermacare | H108: 56.50 | I108: 0.2 | J108: 45.20
A109: 6678045117 | B109: 73551963070 | C109: 6923700914047 | D109: L'Oreal Paris Extraordinary Oil Premium Shampoo (Sleek) - 440ml | E109: 10.473 | F109: OAP | G109: Hair Care | H109: 53.50 | I109: 0.07 | J109: 49.76
A110: 4878035483 | B110: 43551973541 | C110: 6923700909005 | D110: L'Oreal Paris Extraordinary Oil Premium Conditioner (Sleek) - 440ml | E110: 8.145 | F110: OAP | G110: Hair Care | H110: 53.50 | I110: 0.07 | J110: 49.76
A111: 7378033697 | B111: 90803376208 | C111: 6923700913941 | D111: L'Oreal Paris Extraordinary Oil Premium Shampoo (Shine) - 440ml | E111: 2.916 | F111: OAP | G111: Hair Care | H111: 53.50 | I111: 0.07 | J111: 49.76
A112: 6195347782 | B112: 66579131451 | C112: 6902395806455 | D112: NEW Maybelline Fit Me Matte + Poreless Powder Foundation | E112: 75.516 | F112: MNY | G112: Face | H112: 59.90 | I112: 0.15 | J112: 50.92
A113: 6195347782 | B113: 66579131452 | C113: 6902395806479 | D113: NEW Maybelline Fit Me Matte + Poreless Powder Foundation | E113: 75.516 | F113: MNY | G113: Face | H113: 59.90 | I113: 0.15 | J113: 50.92
A114: 6195347782 | B114: 66579131453 | C114: 6902395806493 | D114: NEW Maybelline Fit Me Matte + Poreless Powder Foundation | E114: 75.516 | F114: MNY | G114: Face | H114: 59.90 | I114: 0.15 | J114: 50.92
A115: 6195347782 | B115: 66579131454 | C115: 6902395806509 | D115: NEW Maybelline Fit Me Matte + Poreless Powder Foundation | E115: 75.516 | F115: MNY | G115: Face | H115: 59.90 | I115: 0.15 | J115: 50.92
A116: 6195347782 | B116: 66579131455 | C116: 6902395806516 | D116: NEW Maybelline Fit Me Matte + Poreless Powder Foundation | E116: 75.516 | F116: MNY | G116: Face | H116: 59.90 | I116: 0.15 | J116: 50.92
A117: 6195347782 | B117: 66579131456 | C117: 6902395806523 | D117: NEW Maybelline Fit Me Matte + Poreless Powder Foundation | E117: 75.516 | F117: MNY | G117: Face | H117: 59.90 | I117: 0.15 | J117: 50.92
A118: 6195347782 | B118: 66579131457 | C118: 6902395806530 | D118: NEW Maybelline Fit Me Matte + Poreless Powder Foundation | E118: #N/A | F118: MNY | G118: Face | H118: 59.90 | I118: 0.15 | J118: 50.92
A119: 1372819732 | B119: 1871231894 | C119: 6902395682875 | D119: Maybelline Superstay Matte Ink Liquid Lipstick (Lipstick Matte Lipstick Lipstick Maybelline Liquid Lipstick) | E119: #N/A | F119: MNY | G119: Lips | H119: 42.90 | I119: 0.3 | J119: 30.03
A120: 1372819732 | B120: 1871231890 | C120: 6902395682882 | D120: Maybelline Superstay Matte Ink Liquid Lipstick (Lipstick Matte Lipstick Lipstick Maybelline Liquid Lipstick) | E120: #N/A | F120: MNY | G120: Lips | H120: 42.90 | I120: 0.3 | J120: 30.03
A121: 1372819732 | B121: 13251631365 | C121: 6902395771739 | D121: Maybelline Superstay Matte Ink Liquid Lipstick (Lipstick Matte Lipstick Lipstick Maybelline Liquid Lipstick) | E121: #N/A | F121: MNY | G121: Lips | H121: 42.90 | I121: 0.3 | J121: 30.03
A122: 1372819732 | B122: 1871231891 | C122: 6902395682806 | D122: Maybelline Superstay Matte Ink Liquid Lipstick (Lipstick Matte Lipstick Lipstick Maybelline Liquid Lipstick) | E122: #N/A | F122: MNY | G122: Lips | H122: 42.90 | I122: 0.3 | J122: 30.03
A123: 1372819732 | B123: 1871231892 | C123: 6902395682820 | D123: Maybelline Superstay Matte Ink Liquid Lipstick (Lipstick Matte Lipstick Lipstick Maybelline Liquid Lipstick) | E123: #N/A | F123: MNY | G123: Lips | H123: 42.90 | I123: 0.3 | J123: 30.03
A124: 1372819732 | B124: 13251631364 | C124: 6902395771722 | D124: Maybelline Superstay Matte Ink Liquid Lipstick (Lipstick Matte Lipstick Lipstick Maybelline Liquid Lipstick) | E124: #N/A | F124: MNY | G124: Lips | H124: 42.90 | I124: 0.3 | J124: 30.03
A125: 1372819732 | B125: 13251631361 | C125: 6902395771685 | D125: Maybelline Superstay Matte Ink Liquid Lipstick (Lipstick Matte Lipstick Lipstick Maybelline Liquid Lipstick) | E125: #N/A | F125: MNY | G125: Lips | H125: 42.90 | I125: 0.3 | J125: 30.03
A126: 1955202226 | B126: 3386041594 | C126: 6902395706564 | D126: Maybelline Superstay Matte Ink Liquid Lipstick (Matte Lipstick,Lipstick,Lipstick Maybelline,Superstay,Liquid Lipstick) | E126: 70.953 | F126: MNY | G126: Lips | H126: 42.90 | I126: 0.3 | J126: 30.03
A127: 1955202226 | B127: 3386041598 | C127: 6902395706410 | D127: Maybelline Superstay Matte Ink Liquid Lipstick (Matte Lipstick,Lipstick,Lipstick Maybelline,Superstay,Liquid Lipstick) | E127: 70.953 | F127: MNY | G127: Lips | H127: 42.90 | I127: 0.3 | J127: 30.03
A128: 1955202226 | B128: 3386041595 | C128: 6902395706663 | D128: Maybelline Superstay Matte Ink Liquid Lipstick (Matte Lipstick,Lipstick,Lipstick Maybelline,Superstay,Liquid Lipstick) | E128: 70.953 | F128: MNY | G128: Lips | H128: 42.90 | I128: 0.3 | J128: 30.03
A129: 1955202226 | B129: 3386041597 | C129: 6902395706311 | D129: Maybelline Superstay Matte Ink Liquid Lipstick (Matte Lipstick,Lipstick,Lipstick Maybelline,Superstay,Liquid Lipstick) | E129: 70.953 | F129: MNY | G129: Lips | H129: 42.90 | I129: 0.3 | J129: 30.03
A130: 1955202226 | B130: 3386041596 | C130: 6902395706366 | D130: Maybelline Superstay Matte Ink Liquid Lipstick (Matte Lipstick,Lipstick,Lipstick Maybelline,Superstay,Liquid Lipstick) | E130: 70.953 | F130: MNY | G130: Lips | H130: 42.90 | I130: 0.3 | J130: 30.03
A131: 1955202226 | B131: 3386041599 | C131: 6902395706465 | D131: Maybelline Superstay Matte Ink Liquid Lipstick (Matte Lipstick,Lipstick,Lipstick Maybelline,Superstay,Liquid Lipstick) | E131: 70.953 | F131: MNY | G131: Lips | H131: 42.90 | I131: 0.3 | J131: 30.03
A132: 1955202226 | B132: 3386041593 | C132: 6902395707066 | D132: Maybelline Superstay Matte Ink Liquid Lipstick (Matte Lipstick,Lipstick,Lipstick Maybelline,Superstay,Liquid Lipstick) | E132: 70.953 | F132: MNY | G132: Lips | H132: 42.90 | I132: 0.3 | J132: 30.03
A133: 1955202226 | B133: 3386041600 | C133: 6902395707011 | D133: Maybelline Superstay Matte Ink Liquid Lipstick (Matte Lipstick,Lipstick,Lipstick Maybelline,Superstay,Liquid Lipstick) | E133: 70.953 | F133: MNY | G133: Lips | H133: 42.90 | I133: 0.3 | J133: 30.03
A134: 1955202226 | B134: 3386041601 | C134: 6902395706618 | D134: Maybelline Superstay Matte Ink Liquid Lipstick (Matte Lipstick,Lipstick,Lipstick Maybelline,Superstay,Liquid Lipstick) | E134: 70.953 | F134: MNY | G134: Lips | H134: 42.90 | I134: 0.3 | J134: 30.03
A135: 1063580459 | B135: 987899269 | C135: 6902395682998 | D135: Maybelline Superstay Matte Ink Liquid Lipstick (Lipstick Matte Lipstick Lipstick Maybelline Liquid Lipstick) | E135: 61.236 | F135: MNY | G135: #N/A | H135: 42.90 | I135: 0.3 | J135: 30.03
A136: 1063580459 | B136: 987899271 | C136: 6902395682974 | D136: Maybelline Superstay Matte Ink Liquid Lipstick (Lipstick Matte Lipstick Lipstick Maybelline Liquid Lipstick) | E136: 61.236 | F136: MNY | G136: Lips | H136: 42.90 | I136: 0.3 | J136: 30.03
A137: 1063580459 | B137: 987899266 | C137: 6902395682950 | D137: Maybelline Superstay Matte Ink Liquid Lipstick (Lipstick Matte Lipstick Lipstick Maybelline Liquid Lipstick) | E137: 61.236 | F137: MNY | G137: Lips | H137: 42.90 | I137: 0.3 | J137: 30.03
A138: 1955202226 | B138: 3386041592 | C138: 6902395706717 | D138: Maybelline Superstay Matte Ink Liquid Lipstick (Matte Lipstick,Lipstick,Lipstick Maybelline,Superstay,Liquid Lipstick) | E138: 4.463 | F138: MNY | G138: Lips | H138: 42.90 | I138: 0.3 | J138: 30.03
A139: 13058415119 | B139: 150652924898 | C139: 6902395821069 | D139: Maybelline Fit Me Matte + Poreless Setting Spray 24HR Oil Control Face Makeup | E139: 25.537 | F139: MNY | G139: Face | H139: 42.90 | I139: 0.25 | J139: 32.18
A140: 266124670 | B140: 174238537 | C140: 6923492569159 | D140: Maybelline Lip And Eye Makeup Remover (Makeup Remover, Make Up Remover) | E140: 2.893 | F140: MNY | G140: Makeup Removers | H140: 22.90 | I140: 0.05 | J140: 21.76
A141: 8483158522 | B141: 101185628848 | C141: 6902395781660 | D141: [NEW LAUNCH] Maybelline Falsies Lash Lift Mascara- Long & Lifted Lashes Instantly - Black (Maskara/Lengthening/Salon) | E141: 28.714 | F141: MNY | G141: Eyes | H141: 53.90 | I141: 0.15 | J141: 45.82
A142: 3878142733 | B142: 53551906214 | C142: 6923700908954 | D142: L'Oreal Paris Extraordinary Oil Premium Conditioner (Shine) - 440ml | E142: 2.678 | F142: OAP | G142: Hair Care | H142: 53.50 | I142: 0.07 | J142: 49.76
...

Sheet Price Change-Flash TH Proposal
E1: Type of Input required | F1: *Mandatory Fields
F2: Optional Fields
F3: Dropdown
F4: Autofill
E5: *Please take note for any input with double pricing with same date/duration, SVC will submit the lowest price
T16: PLANNING BY FLASH ONLY PLEASE SELECT CAMPAIGN TIERING
T17: Campaign Name | X17: Campaign Name | AB17: Campaign Name | AF17: Campaign Name
T18: Campaign Type | X18: Campaign Type | AB18: Campaign Type | AF18: Campaign Type
T19: Campaign Tiering | U19: 1 | X19: Campaign Tiering | Y19: 2 | AB19: Campaign Tiering | AC19: 3 | AF19: Campaign Tiering
T20: Date | U20: {=IFERROR(_xlfn.TEXTJOIN(", ", TRUE, IF((U$19='Campaign Calendar'!$K$11:$K$45),'Campaign Calendar'!#REF!, "")), "")} | X20: Date | Y20: {=IFERROR(_xlfn.TEXTJOIN(", ", TRUE, IF((Y$19='Campaign Calendar'!$K$11:$K$45),'Campaign Calendar'!#REF!, "")), "")} | AB20: Date | AC20: {=IFERROR(_xlfn.TEXTJOIN(", ", TRUE, IF((AC$19='Campaign Calendar'!$K$11:$K$45),'Campaign Calendar'!#REF!, "")), "")} | AF20: Date | AG20: {=IFERROR(_xlfn.TEXTJOIN(", ", TRUE, IF((AG$19='Campaign Calendar'!$K$11:$K$45),'Campaign Calendar'!#REF!, "")), "")}
G21: l | T21: Time | X21: Time | Y21: {=IFERROR(_xlfn.TEXTJOIN(", ", TRUE, IF((Y$19='Campaign Calendar'!$K$11:$K$45),'Campaign Calendar'!#REF!, "")), "")} | AB21: Time | AC21: {=IFERROR(_xlfn.TEXTJOIN(", ", TRUE, IF((AC$19='Campaign Calendar'!$K$11:$K$45),'Campaign Calendar'!#REF!, "")), "")} | AF21: Time | AG21: {=IFERROR(_xlfn.TEXTJOIN(", ", TRUE, IF((AG$19='Campaign Calendar'!$K$11:$K$45),'Campaign Calendar'!#REF!, "")), "")}
T22: Treasure Bowl Name* | U22: SIS FS | X22: Treasure Bowl Name* | Y22: XXXX | AB22: Treasure Bowl Name* | AF22: Treasure Bowl Name*
T23: Treasure Bowl ID* | U23: SIS FS | X23: Treasure Bowl ID* | Y23: XXXX | AB23: Treasure Bowl ID* | AF23: Treasure Bowl ID*
T24: Promotion Plan File/Folder* | U24: Share the relevant Link | X24: Promotion Plan File/Folder* | Y24: Share the relevant Link | AB24: Promotion Plan File/Folder* | AC24: Share the relevant Link | AF24: Promotion Plan File/Folder* | AG24: Share the relevant Link
T25: Relevant files for SVC | X25: Relevant files for SVC | AB25: Relevant files for SVC | AF25: Relevant files for SVC
B26: Date | C26: Start Time | D26: End Time | E26: EAN Code | F26: Product ID | G26: Variation ID | H26: Product Name | I26: Brand | J26: VBOM/Single/Bundle | K26: Product Url | L26: Lowest Sales Price(30day) | M26: Average Sales Price (30day) | N26: Lowest Onsite Price(30day) | O26: Average Onsite Price(30day) | P26: Category Name | Q26: Lazada Recommend | R26: Stock | S26: L'Oreal recommended Price (list price) | T26: Campaign Price | U26: Promo Discount % | V26: Tier | W26: FS Stock Level | X26: Campaign Price | Y26: Promo Discount % | Z26: Tier | AA26: FS Stock Level | AB26: Campaign Price | AC26: Promo Discount % | AD26: Tier | AE26: FS Stock Level | AF26: Campaign Price | AG26: Promo Discount % | AH26: Tier | AI26: FS Stock Level
B27: 45386 | C27: 00,00 | D27: 00,02 | J27: Select from Dropdown
B28: 45386 | C28: 00,00 | D28: 00,02 | J28: Select from Dropdown
B29: 45386 | C29: 00,00 | D29: 00,02 | J29: Select from Dropdown
B30: 45386 | C30: 00,00 | D30: 00,02 | J30: Select from Dropdown
B31: 45386 | C31: 00,00 | D31: 00,02 | J31: Select from Dropdown
B32: 45386 | C32: 00,00 | D32: 00,02 | J32: Select from Dropdown
B33: 45386 | C33: 00,00 | D33: 00,02 | J33: Select from Dropdown
B34: 45386 | C34: 00,00 | D34: 00,02 | J34: Select from Dropdown
B35: 45388 | C35: 00,00 | D35: 00,02 | J35: Select from Dropdown
B36: 45386 | C36: 00,00 | D36: 00,02 | J36: Select from Dropdown
B37: 45386 | C37: 00,00 | D37: 00,02 | J37: Select from Dropdown
B38: 45386 | C38: 00,00 | D38: 00,02 | J38: Select from Dropdown
... B42: 45386 | C42: 00,00 | D42: 00,02 | J42: Select from Dropdown
J43: Select from Dropdown
J44: Select from Dropdown
J45: Select from Dropdown
J46: Select from Dropdown
J47: Select from Dropdown
J48: Select from Dropdown
J49: Select from Dropdown
J50: Select from Dropdown
J51: Select from Dropdown
J52: Select from Dropdown
J53: Select from Dropdown
J54: Select from Dropdown
... J295: Select from Dropdown

Sheet Price Change - Flash
E1: Type of Input required | F1: *Mandatory Fields
F2: Optional Fields
F3: Dropdown
F4: Autofill
E5: *Please take note for any input with double pricing with same date/duration, SVC will submit the lowest price
T16: PLANNING BY FLASH ONLY PLEASE SELECT CAMPAIGN TIERING
T17: Campaign Name | X17: Campaign Name | AB17: Campaign Name | AF17: Campaign Name
T18: Campaign Type | X18: Campaign Type | AB18: Campaign Type | AF18: Campaign Type
T19: Campaign Tiering | U19: 1 | X19: Campaign Tiering | Y19: 2 | AB19: Campaign Tiering | AC19: 3 | AF19: Campaign Tiering
T20: Date | U20: {=IFERROR(_xlfn.TEXTJOIN(", ", TRUE, IF((U$19='Campaign Calendar'!$K$11:$K$45),'Campaign Calendar'!#REF!, "")), "")} | X20: Date | Y20: {=IFERROR(_xlfn.TEXTJOIN(", ", TRUE, IF((Y$19='Campaign Calendar'!$K$11:$K$45),'Campaign Calendar'!#REF!, "")), "")} | AB20: Date | AC20: {=IFERROR(_xlfn.TEXTJOIN(", ", TRUE, IF((AC$19='Campaign Calendar'!$K$11:$K$45),'Campaign Calendar'!#REF!, "")), "")} | AF20: Date | AG20: {=IFERROR(_xlfn.TEXTJOIN(", ", TRUE, IF((AG$19='Campaign Calendar'!$K$11:$K$45),'Campaign Calendar'!#REF!, "")), "")}
G21: l | T21: Time | X21: Time | Y21: {=IFERROR(_xlfn.TEXTJOIN(", ", TRUE, IF((Y$19='Campaign Calendar'!$K$11:$K$45),'Campaign Calendar'!#REF!, "")), "")} | AB21: Time | AC21: {=IFERROR(_xlfn.TEXTJOIN(", ", TRUE, IF((AC$19='Campaign Calendar'!$K$11:$K$45),'Campaign Calendar'!#REF!, "")), "")} | AF21: Time | AG21: {=IFERROR(_xlfn.TEXTJOIN(", ", TRUE, IF((AG$19='Campaign Calendar'!$K$11:$K$45),'Campaign Calendar'!#REF!, "")), "")}
T22: Treasure Bowl Name* | X22: Treasure Bowl Name* | AB22: Treasure Bowl Name* | AF22: Treasure Bowl Name*
T23: Treasure Bowl ID* | X23: Treasure Bowl ID* | AB23: Treasure Bowl ID* | AF23: Treasure Bowl ID*
T24: Promotion Plan File/Folder* | U24: Share the relevant Link | X24: Promotion Plan File/Folder* | Y24: Share the relevant Link | AB24: Promotion Plan File/Folder* | AC24: Share the relevant Link | AF24: Promotion Plan File/Folder* | AG24: Share the relevant Link
T25: Relevant files for SVC | X25: Relevant files for SVC | AB25: Relevant files for SVC | AF25: Relevant files for SVC
B26: Date | C26: Start Time | D26: End Time | E26: EAN Code | F26: Product ID | G26: Variation ID | H26: Product Name | I26: Brand | J26: VBOM/Single/Bundle | K26: Product Url | L26: Lowest Sales Price(30day) | M26: Average Sales Price (30day) | N26: Lowest Onsite Price(30day) | O26: Average Onsite Price(30day) | P26: Category Name | Q26: Lazada Recommend | R26: Stock | S26: L'Oreal recommended Price (list price) | T26: Campaign Price | U26: Promo Discount % | V26: Tier | W26: FS Stock Level | X26: Campaign Price | Y26: Promo Discount % | Z26: Tier | AA26: FS Stock Level | AB26: Campaign Price | AC26: Promo Discount % | AD26: Tier | AE26: FS Stock Level | AF26: Campaign Price | AG26: Promo Discount % | AH26: Tier | AI26: FS Stock Level
J27: Select from Dropdown
J28: Select from Dropdown
J29: Select from Dropdown
J30: Select from Dropdown
J31: Select from Dropdown
J32: Select from Dropdown
J33: Select from Dropdown
J34: Select from Dropdown
J35: Select from Dropdown
J36: Select from Dropdown
J37: Select from Dropdown
J38: Select from Dropdown
... J295: Select from Dropdown

Sheet Sheet1
A1: 9557534800206 | B1: catId | C1: Product Name | D1: currencyCode | E1: sku.skuId | F1: status | G1: Shop SKU | H1: Price | I1: SellerSKU | J1: SpecialPrice | K1: SpecialPrice Start | L1: SpecialPrice End | M1: Quantity | N1: Variations Combo | O1: tr(s-wb-product@md5key)
A2: Optional | B2: Optional | C2: Mandatory | D2: Optional | E2: Optional | F2: Optional | G2: Optional | H2: Mandatory | I2: Optional | J2: Optional | K2: Optional | L2: Optional | M2: Mandatory | N2: Optional | O2: Optional
A3: System generated numerical ID that represents your product. One product ID is equivalent to a product page. Variations share the same product page and hence they share the same Product ID. | C3: Product name should include product brand and model. Avoid irrelevant keywords as it may cause the listing to be banned. | G3: Shop SKU is also known as Lazada SKU. This is an ID that is generated by Lazada system. It cannot be changed, and is unique. For instance, each variation will have a different Lazada SKU. | H3: Input your product price in your local currency. | I3: SKU is a unique identifier for each product variation. SKU value cannot be duplicated in a store. | J3: The Special Price of your product for promotion. | K3: The Special Price Start date is the time starting to implement your product Special Price. | L3: The Special Price End date is the end time to implement your product Special Price. | M3: Input your product stock | N3: Variations are the options available for the product. Common variations for products are colours, capacity, models etc. Variations help customers to see all available options a seller have on a single product page.
C4: *Please input 5 to 255 characters for product name. Only titles in muti-language can be deleted using Overwrite feature during Bulk Edit. | F4: Leave it blank during Bulk Edit will be considered as no change. | H4: *Only positive numbers are accepted. | I4: Please input less than 200 characters. Using Overwrite feature to delete during Bulk Edit will be given a random value by system. | J4: Input directly to update. Value can be deleted using Overwrite feature during Bulk Edit. | K4: Input in YYYY-MM-DD HH:MM:SS format to update. Can only delete the value if no Special Price is set. | L4: Input in YYYY-MM-DD HH:MM:SS format to update. Can only delete the value if no Special Price is set. | M4: *Only positive numbers are accepted.
A5: 11510537 | B5: 1610 | C5: L’Oreal Paris Excellence Creme Triple Care Hair Color - #1 Black, Water Permeable [Grey Hair, Hair Color For Home] | D5: MYR | E5: 14169107 | F5: active | G5: LO533HBAA5ZIGXANMY-12204054 | H5: 49.90 | I5: 8850434200154 | J5: 45.51 | K5: 2026-01-01 11:05:00 | L5: 2026-01-31 23:59:59 | M5: 0 | N5: Black,172 | O5: bb6572c33007609ee78a8c8d0c1f7d11
A6: 11510541 | B6: 1610 | C6: L'Oreal Paris Excellence Creme Triple Care Hair Color #3 Dark Brown, Water Permeable [Grey Hair, Hair Color For Home] | D6: MYR | E6: 14169118 | F6: active | G6: LO533HBAA5ZIH7ANMY-12204064 | H6: 49.90 | I6: 8850434200178 | J6: 45.51 | K6: 2026-01-01 11:05:00 | L6: 2026-01-31 23:59:59 | M6: 0 | N6: Dark Brown,172 | O6: edd07b36508a22197a88431276a62e7c
A7: 11510542 | B7: 1610 | C7: L'Oreal Paris Excellence Creme Triple Care Hair Color - #4 Brown, Water Permeable [Grey Hair, Hair Color For Home] | D7: MYR | E7: 14169120 | F7: active | G7: LO533HBAA5ZIHGANMY-12204074 | H7: 49.90 | I7: 8850434200215 | J7: 45.51 | K7: 2026-01-01 11:05:00 | L7: 2026-01-31 23:59:59 | M7: 0 | N7: Brown,172 | O7: 0618aad6d4b7090478b0ac2613636ac4
A8: 11510543 | B8: 1610 | C8: L'Oreal Paris Excellence Creme Triple Care Hair Color - #4.15 Frosted Brown, Water Permeable [Grey Hair, Hair Color For Home] | D8: MYR | E8: 14169122 | F8: active | G8: LO533HBAA5ZIHSANMY-12204087 | H8: 49.90 | I8: 6938181590802 | J8: 45.51 | K8: 2026-01-01 11:05:00 | L8: 2026-01-31 23:59:59 | M8: 0 | N8: Frosted Brown,172 | O8: 13ef79516e80f7c74f41ae897c9c351b
A9: 11510544 | B9: 1610 | C9: L'Oreal Paris Excellence Creme Triple Care Hair Color - #4.26 Purple Brown, Water Permeable [Grey Hair, Hair Color For Home] | D9: MYR | E9: 14169124 | F9: active | G9: LO533HBAA5ZII2ANMY-12204097 | H9: 49.90 | I9: 8991380404262 | J9: 45.51 | K9: 2026-01-01 11:05:00 | L9: 2026-01-31 23:59:59 | M9: 0 | N9: Purple Brown,172 | O9: a4752f790bb163de9221ffc75a8196ab
A10: 11510545 | B10: 1610 | C10: L'Oreal Paris Excellence Creme Triple Care Hair Color - #4.35 Dark Caramel Brown, Water Permeable [Grey Hair, Hair Color For Home] | D10: MYR | E10: 14169126 | F10: active | G10: LO533HBAA5ZIIAANMY-12204107 | H10: 49.90 | I10: 6938181569211 | J10: 45.51 | K10: 2026-01-01 11:05:00 | L10: 2026-01-31 23:59:59 | M10: 0 | N10: Dark Chocolate Brown,172 | O10: 0bcd522c4667812e103510fbcd3ea204
A11: 11510546 | B11: 1610 | C11: L'Oreal Paris Excellence Creme Triple Care Hair Color - #4.45 Mahogany Copper Brown, Water Permeable [Grey Hair, Hair Color For Home] | D11: MYR | E11: 14169128 | F11: active | G11: LO533HBAA5ZILZANMY-12204260 | H11: 49.90 | I11: 8850434200253 | J11: 45.51 | K11: 2026-01-01 11:05:00 | L11: 2026-01-31 23:59:59 | M11: 0 | N11: Mahogany Copper Brown,172 | O11: 42710da3fe993e899ac1fd00305e9a47
A12: 11510547 | B12: 1610 | C12: L'Oreal Paris Excellence Creme Triple Care Hair Color - #5 Light Brown, Water Permeable [Grey Hair, Hair Color For Home] | D12: MYR | E12: 14169129 | F12: active | G12: LO533HBAA5ZIM6ANMY-12204267 | H12: 49.90 | I12: 8850434200260 | J12: 45.51 | K12: 2026-01-01 11:05:00 | L12: 2026-01-31 23:59:59 | M12: 0 | N12: Light Brow,172 | O12: d9e706403ce2dfab107f4a215cad29c0
A13: 11510548 | B13: 1610 | C13: L'Oreal Paris Excellence Creme Triple Care Hair Color - #5.35 Chocolate Brown, Water Permeable [Grey Hair, Hair Color For Home] | D13: MYR | E13: 14169130 | F13: active | G13: LO533HBAA5ZHHUANMY-12202506 | H13: 49.90 | I13: 8991380405351 | J13: 45.51 | K13: 2026-01-01 11:05:00 | L13: 2026-01-31 23:59:59 | M13: 0 | N13: Chocolate Brown,172 | O13: 5f79f308f2f7b2020083e86416d6904b
A14: 11510549 | B14: 1610 | C14: L'Oreal Paris Excellence Creme Triple Care Hair Color - #6.30 Golden Dark Brown, Water Permeable [Grey Hair, Hair Color For Home] | D14: MYR | E14: 14169131 | F14: active | G14: LO533HBAA5XXKQANMY-12116654 | H14: 49.90 | I14: 6923492547454 | J14: 45.51 | K14: 2026-01-01 11:05:00 | L14: 2026-01-31 23:59:59 | M14: 0 | N14: Golden Dark Brown,172 | O14: ef0838dc4f780500c19732f3719c2974
A15: 11510599 | B15: 1618 | C15: LOreal Paris Elseve Extraordinary Oil Brown 100ml (Dry/Damaged hair Hair Treatment Hair Oil) | D15: MYR | E15: 14169220 | F15: active | G15: LO533HBAA5XXMIANMY-12116718 | H15: 61.90 | I15: 4992944111972 | J15: 58.81 | K15: 2026-01-01 11:05:00 | L15: 2026-01-31 23:59:59 | M15: 0 | N15: 100 | O15: e24cf8c75bf2772907b04d4428b56ec0
A16: 11510600 | B16: 1618 | C16: L’Oréal Paris ELSEVE Extraordinary Oil Gold 4x Shine Smoothen Hair Serum Hair Treatment 100ml for All Hair Types | D16: MYR | E16: 14169221 | F16: active | G16: LO533HBAA5XWI4ANMY-12115140 | H16: 61.90 | I16: 4992944111576 | J16: 49.52 | K16: 2026-01-01 11:05:00 | L16: 2026-01-31 23:59:59 | M16: 0 | N16: 100 | O16: 80debe9f90a8d2ebead836a923fd3030
... A137: 1581302325 | B137: 1610 | C137: L'Oreal Paris Excellence Fashion Hair Color (Hair Dye/ Hair Care)​ - #7.17 Matt Ash, Water Permeable [Hair Color, Pewarna rambut, Ash] | D137: MYR | E137: 5363634160 | F137: active | G137: 1581302325_MY-5363634160 | H137: 49.90 | I137: 6923700934380 | J137: 47.41 | K137: 2026-01-01 11:05:00 | L137: 2026-01-31 23:59:59 | M137: 0 | N137: Matt Ash,379 | O137: ce3a444aa6437562901f467a9e1a1286
A138: 1970546773 | B138: 10002962 | C138: [GWP - NOT FOR SALE] L'Oreal Paris Rouge Signature Matte Liquid Lipstick Mini (Lip Matte, Matte Lipstick) #121- gimmick | D138: MYR | E138: 7884742212 | F138: active | G138: 1970546773_MY-7884742212 | H138: 0.00 | I138: 6902395801764 | M138: 0 | O138: aaee8b68c7a19e4d6c2e4b259cd313a2
A139: 2021997202 | B139: 8078 | C139: L'Oreal Paris Revitalift Hyaluronic Acid Plumping Fresh Mix Serum Mask x5 | D139: MYR | E139: 8025096071 | F139: active | G139: 2021997202_MY-8025096071 | H139: 84.50 | I139: 9557534754899 | J139: 67.60 | K139: 2026-01-01 11:05:00 | L139: 2026-01-31 23:59:59 | M139: 0 | N139: Others,165 | O139: b5f79c1f667bb52b1abc767176e32232
A140: 2083322737 | B140: 1605 | C140: L'Oreal Paris Extraordinary Oil Premium Shampoo (Smooth) 440ML | D140: MYR | E140: 8340163557 | F140: active | G140: 2083322737_MY-8340163557 | H140: 53.50 | I140: 6923700914047 | J140: 50.83 | K140: 2026-01-01 11:05:00 | L140: 2026-01-31 23:59:59 | M140: 0 | N140: 440 | O140: 41f033ede205d316001043a5021e6613
A141: 2153919871 | B141: 10100737 | C141: L’Oréal Paris Revitalift Hyaluronic Acid Line Filling Water Face Cream Moisturizer for Hydrates and Plumps Skin 50ml | D141: MYR | E141: 8941684052 | F141: active | G141: 2153919871_MY-8941684052 | H141: 97.90 | I141: 6923700981209 | J141: 93.01 | K141: 2026-01-01 11:05:00 | L141: 2026-01-31 23:59:59 | M141: 0 | N141: 50 | O141: 3f58343316ac2ca5f478251c8970ea50
A142: 2197856549 | B142: 8080 | C142: L'Oreal Paris Revitalift Hyaluronic Acid Hydrating Gel Face Cleanser for Plumpy & Hydrates Skin 100ml | D142: MYR | E142: 9241605350 | F142: active | G142: 2197856549_MY-9241605350 | H142: 43.90 | I142: 8994993016013 | J142: 37.91 | K142: 2026-01-01 11:05:00 | L142: 2026-01-31 23:59:59 | M142: 0 | N142: 100,Others | O142: 73aaebf53656327e8f7cd7e2a4233061
A143: 2241072675 | B143: 8084 | C143: L'Oreal Paris UV Defender Daily Sunscreen Serum Protector SPF50+ Glow Up 50ml for All Skin Types | D143: MYR | E143: 9497084524 | F143: active | G143: 2241072675_MY-9497084524 | H143: 79.90 | I143: 8994993014668 | J143: 73.06 | K143: 2026-01-01 11:05:00 | L143: 2026-01-31 23:59:59 | M143: 0 | N143: 50 | O143: 2ca4619a1b77b6f9120aaf0db50bcb23
A144: 2241125459 | B144: 8084 | C144: L'Oreal Paris UV Defender Daily Sunscreen Serum Protector SPF50+ Moist & Fresh for Dry Skin 50ml | D144: MYR | E144: 9497074861 | F144: active | G144: 2241125459_MY-9497074861 | H144: 86.80 | I144: 8994993014743 | J144: 82.46 | K144: 2026-01-01 11:05:00 | L144: 2026-01-31 23:59:59 | M144: 0 | N144: 50 | O144: 5168cf22dd882fc75cec12fd97239740
A145: 2241194122 | B145: 8084 | C145: L'Oreal Paris UV Defender Daily Sunscreen Serum Protector SPF50+ Fresh Matte for Oily Skin 50ml | D145: MYR | E145: 9497183088 | F145: active | G145: 2241194122_MY-9497183088 | H145: 79.90 | I145: 8994993014705 | J145: 73.06 | K145: 2026-01-01 11:05:00 | L145: 2026-01-31 23:59:59 | M145: 0 | N145: 50 | O145: dcc4cc78ec9f42b37e9e6a6409fc16f3
A146: 2241210047 | B146: 8084 | C146: L'Oreal Paris UV Defender Daily Sunscreen Serum Protector SPF50+ Correct & Protect for Dull Skin 50ml | D146: MYR | E146: 9497158179 | F146: active | G146: 2241210047_MY-9497158179 | H146: 86.80 | I146: 8994993014682 | J146: 82.46 | K146: 2026-01-01 11:05:00 | L146: 2026-01-31 23:59:59 | M146: 0 | N146: 50 | O146: d025c6bf4d0a4c7eca678a05c89c3989
A147: 2245058026 | B147: 1605 | C147: L'Oreal Paris Elseve Fall Resist 3X Anti-Dandruff Shampoo 280ml | D147: MYR | E147: 9520946084 | F147: active | G147: 2245058026_MY-9520946084 | H147: 18.90 | I147: 8994993011841 | J147: 17.96 | K147: 2026-01-01 11:05:00 | L147: 2026-01-31 23:59:59 | M147: 0 | N147: 280 | O147: 17ff144e591ccc0a9e73e7a6054f0528
A148: 2300971910 | B148: 1605 | C148: L'Oreal Paris Elseve Extraordinary Oil 6 Oil Ultra Nourishing Shampoo for Softer Hair (265ml / 620ml) | D148: MYR | E148: 9788824708 | F148: active | G148: 2300971910_MY-9788824708 | H148: 18.90 | I148: 8994993012459 | J148: 17.96 | K148: 2026-01-01 11:05:00 | L148: 2026-01-31 23:59:59 | M148: 0 | N148: 265 | O148: 88741a73a4d7150aa6e697a0dbcbe6c4
A149: 2300971910 | B149: 1605 | C149: L'Oreal Paris Elseve Extraordinary Oil 6 Oil Ultra Nourishing Shampoo for Softer Hair (265ml / 620ml) | D149: MYR | E149: 9788824707 | F149: active | G149: 2300971910_MY-9788824707 | H149: 36.90 | I149: 8994993012367 | J149: 35.06 | K149: 2026-01-01 11:05:00 | L149: 2026-01-31 23:59:59 | M149: 0 | N149: 620 | O149: 18bdc1ef54b864bd5237cb3711cc764f
A150: 2300988548 | B150: 1605 | C150: L'Oreal Paris Elseve Fall Resist 3X Anti-Hair Fall Shampoo Scalp + Hair for Nourishes Hair Reduced Breakage (280ML/620ML) | D150: MYR | E150: 9788720544 | F150: inactive | G150: 2300988548_MY-9788720544 | H150: 18.90 | I150: 8994993012497 | J150: 17.96 | K150: 2026-01-01 11:05:00 | L150: 2026-01-31 23:59:59 | M150: 0 | N150: 280 | O150: 52b7a748f12a4fc7b5aae1d26b7cd52f
... A169: 2463522229 | B169: 1610 | C169: L'Oreal Paris Excellence Fashion Ash Hair Color (Hair Dye/ Hair Care)​ [Hair Color, Pewarna rambut, Ash] | D169: MYR | E169: 10745821028 | F169: active | G169: 2463522229_MY-10745821028 | H169: 49.90 | I169: 6923700985757 | J169: 47.41 | K169: 2026-01-01 11:05:00 | L169: 2026-01-31 23:59:59 | M169: 0 | N169: Smokey Ash,172 | O169: 92d410c73704a62efd65efa2d8ae98ab
A170: 2580974424 | B170: 8086 | C170: L'Oreal Paris Revitalift Hyaluronic Acid Regime Set | D170: MYR | E170: 11531688880 | F170: active | G170: 2580974424_MY-11531688880 | H170: 230.30 | I170: 9557534757630 | J170: 207.27 | K170: 2026-01-01 11:05:00 | L170: 2026-01-31 23:59:59 | O170: a90fbd277ceab10358a8c45d817c3514
A171: 2608873388 | B171: 8086 | C171: L'Oreal Paris Youth Code Regime Bundle | D171: MYR | E171: 11732473959 | F171: active | G171: 2608873388_MY-11732473959 | H171: 369.00 | I171: 9557534758866 | J171: 332.10 | K171: 2026-01-01 11:05:00 | L171: 2026-01-31 23:59:59 | O171: 5cef85ddc9b0bbd9b5d9fb0312242edf
A172: 2753964681 | B172: 1537 | C172: L'Oreal Paris Revitalift Hyaluronic Micellar Water 400ml | D172: MYR | E172: 13057709093 | F172: active | G172: 2753964681_MY-13057709093 | H172: 61.50 | I172: 6923700987782 | J172: 58.43 | K172: 2026-01-01 11:05:00 | L172: 2026-01-31 23:59:59 | M172: 0 | N172: 400 | O172: 20a9b7d4b1e1c38d44b5d891123dfddb
A173: 2817522007 | B173: 8086 | C173: L'Oreal Paris Revitalift Anti Aging Centella Micro-Essence Water (130ml) | D173: MYR | E173: 13515060970 | F173: active | G173: 2817522007_MY-13515060970 | H173: 86.90 | I173: 6923700970593 | J173: 82.56 | K173: 2026-01-01 11:05:00 | L173: 2026-01-31 23:59:59 | M173: 0 | N173: 130 | O173: e956069f4226da27298cb7a3e32dece0
A174: 2867142991 | B174: 8086 | C174: L’Oréal Paris Glycolic Bright 8% [Melasyl™+ Glycolic + Niacinamide] Face Serum for Dark Spot & Brightening 30ml | D174: MYR | E174: 13830011127 | F174: active | G174: 2867142991_MY-13830011127 | H174: 94.90 | I174: 8994993016587 | J174: 75.92 | K174: 2026-01-01 11:05:00 | L174: 2026-01-31 23:59:59 | M174: 0 | N174: 30 ml | O174: 50744db4dc275e7e35c74816128d5a85
A175: 2867148924 | B175: 8080 | C175: L’Oréal Paris Glycolic Bright Glowing Daily Face Cleanser Foam, Remove Dulless & Exfoliates for Growing Skin 100ml | D175: MYR | E175: 13830009148 | F175: active | G175: 2867148924_MY-13830009148 | H175: 43.90 | I175: 8994993016532 | J175: 37.91 | K175: 2026-01-01 11:05:00 | L175: 2026-01-31 23:59:59 | M175: 0 | N175: 100,Others | O175: 0bc5532691364bd2dae591b934320de3
A176: 2867186628 | B176: 10100737 | C176: L’Oréal Paris Glycolic Bright Overnight Glowing Night Cream Moisturizer to Reduce Dark Spots for Glowing Skin 50ml | D176: MYR | E176: 13829984177 | F176: active | G176: 2867186628_MY-13829984177 | H176: 94.90 | I176: 8994993016563 | J176: 75.92 | K176: 2026-01-01 11:05:00 | L176: 2026-01-31 23:59:59 | M176: 0 | N176: 50 | O176: 4ede83112cd96bdc6ea97d6eb06a8152
A177: 2867230371 | B177: 10100737 | C177: L’Oréal Paris Glycolic Bright Glowing Day Face Cream / Moisturizer SPF30 Brighten and Reduce Dark Spots 50ml | D177: MYR | E177: 13829933705 | F177: active | G177: 2867230371_MY-13829933705 | H177: 94.90 | I177: 8994993016525 | J177: 71.12 | K177: 2026-01-01 11:05:00 | L177: 2026-01-31 23:59:59 | M177: 0 | N177: 50 | O177: 421cdc523f374fc7a6120e1904a3ffa4
A178: 2908740568 | B178: 10002962 | C178: [GWP - NOT FOR SALE] L'Oreal Paris Extraordinary Oil Premium Shampoo 100ml - gimmick | D178: MYR | E178: 14107207638 | F178: active | G178: 2908740568_MY-14107207638 | H178: 0.00 | I178: 6923700978865 | M178: 0 | O178: 651879c94ce99792c84c838f3b250e94
A179: 2908803074 | B179: 10002962 | C179: [GWP - NOT FOR SALE] L'Oreal Paris Extraordinary Oil Premium Conditioner 100ml - gimmick | D179: MYR | E179: 14107224535 | F179: active | G179: 2908803074_MY-14107224535 | H179: 0.00 | I179: 6923700973402 | M179: 0 | O179: bb2c49b0c235867426384dd954dac580
A180: 2951605508 | B180: 8086 | C180: L’Oreal Paris Youth Code Skin Activating Ferment Pre-Essence 30ml | D180: MYR | E180: 14428532895 | F180: active | G180: 2951605508_MY-14428532895 | H180: 193.00 | I180: 6923700974379 | J180: 183.35 | K180: 2026-01-01 11:05:00 | L180: 2026-01-31 23:59:59 | M180: 0 | N180: 30 | O180: ff5d735832f77db1bea8e6c51400f787
A181: 3180417552 | B181: 10002962 | C181: [GWP - NOT FOR SALE] L'Oreal Paris Glycolic Bright Serum 7.5ml Tube - gimmick | D181: MYR | E181: 16109653939 | F181: active | G181: 3180417552_MY-16109653939 | H181: 0.00 | I181: 8994993016594 | M181: 0 | O181: 8be9ce2cc8d99d1d2a865b998a1b8ba9
A182: 3324043358 | B182: 1508 | C182: L’Oréal Paris Infaillible Longwear 24H Fresh Wear Foundation In A Powder Oil-Free, Fresh Matte Full Coverage, Waterproof | D182: MYR | E182: 17805629946 | F182: active | G182: 3324043358_MY-17805629946 | H182: 89.90 | I182: 3600523951291 | J182: 85.41 | K182: 2026-01-01 11:05:00 | L182: 2026-01-31 23:59:59 | M182: 0 | N182: 20 - Ivory | O182: 915138d6505f5b8b1f08c68706f4e874
A183: 3324043358 | B183: 1508 | C183: L’Oréal Paris Infaillible Longwear 24H Fresh Wear Foundation In A Powder Oil-Free, Fresh Matte Full Coverage, Waterproof | D183: MYR | E183: 17805629947 | F183: active | G183: 3324043358_MY-17805629947 | H183: 89.90 | I183: 3600523951444 | J183: 85.41 | K183: 2026-01-01 11:05:00 | L183: 2026-01-31 23:59:59 | M183: 0 | N183: 120 - Vanilla | O183: 2d2a947e3248ce020d35feb3eaa7024c
A184: 3324043358 | B184: 1508 | C184: L’Oréal Paris Infaillible Longwear 24H Fresh Wear Foundation In A Powder Oil-Free, Fresh Matte Full Coverage, Waterproof | D184: MYR | E184: 17805629948 | F184: active | G184: 3324043358_MY-17805629948 | H184: 89.90 | I184: 3600523951543 | J184: 85.41 | K184: 2026-01-01 11:05:00 | L184: 2026-01-31 23:59:59 | M184: 0 | N184: 130 - True Beige | O184: ad7248e0dc93c234b7588dafd2519b45
A185: 3324043358 | B185: 1508 | C185: L’Oréal Paris Infaillible Longwear 24H Fresh Wear Foundation In A Powder Oil-Free, Fresh Matte Full Coverage, Waterproof | D185: MYR | E185: 17805629949 | F185: active | G185: 3324043358_MY-17805629949 | H185: 89.90 | I185: 3600523951598 | J185: 85.41 | K185: 2026-01-01 11:05:00 | L185: 2026-01-31 23:59:59 | M185: 0 | N185: 140 - Golden Beige | O185: 0f200b698a7b344f92c601378c4e1a95
A186: 3324043358 | B186: 1508 | C186: L’Oréal Paris Infaillible Longwear 24H Fresh Wear Foundation In A Powder Oil-Free, Fresh Matte Full Coverage, Waterproof | D186: MYR | E186: 17805629950 | F186: active | G186: 3324043358_MY-17805629950 | H186: 89.90 | I186: 3600523951741 | J186: 85.41 | K186: 2026-01-01 11:05:00 | L186: 2026-01-31 23:59:59 | M186: 0 | N186: 180 - Rose Sand | O186: d5e68accd2ec07dd0e8ac3521f36aaa8
A187: 3324043358 | B187: 1508 | C187: L’Oréal Paris Infaillible Longwear 24H Fresh Wear Foundation In A Powder Oil-Free, Fresh Matte Full Coverage, Waterproof | D187: MYR | E187: 17805629951 | F187: inactive | G187: 3324043358_MY-17805629951 | H187: 89.90 | I187: 3600523951895 | J187: 85.41 | K187: 2026-01-01 11:05:00 | L187: 2026-01-31 23:59:59 | M187: 0 | N187: 220 - Sand | O187: a249ced0c07d99135291388ff4f57586
A188: 3324043358 | B188: 1508 | C188: L’Oréal Paris Infaillible Longwear 24H Fresh Wear Foundation In A Powder Oil-Free, Fresh Matte Full Coverage, Waterproof | D188: MYR | E188: 17805629952 | F188: active | G188: 3324043358_MY-17805629952 | H188: 89.90 | I188: 3600523951949 | J188: 85.41 | K188: 2026-01-01 11:05:00 | L188: 2026-01-31 23:59:59 | M188: 0 | N188: 245 - Golden Honey | O188: 685b40b0d672257e23de6fb9b647a7da
A189: 3405209800 | B189: 8085 | C189: L’Oréal Paris Glycolic Bright 5% Glycolic Acid Glowing Peeling Toner Clinic-Inspired Glowy, Smooth Skin 65ml/128ml | D189: MYR | E189: 18315898507 | F189: active | G189: 3405209800_MY-18315898507 | H189: 89.90 | I189: 6941594509156 | J189: 85.41 | K189: 2026-01-01 11:05:00 | L189: 2026-01-31 23:59:59 | M189: 0 | N189: 128 | O189: c5a7c6ce746f35aedf189212a2fe3bdb
A190: 3405209800 | B190: 8085 | C190: L’Oréal Paris Glycolic Bright 5% Glycolic Acid Glowing Peeling Toner Clinic-Inspired Glowy, Smooth Skin 65ml/128ml | D190: MYR | E190: 18315898508 | F190: active | G190: 3405209800_MY-18315898508 | H190: 59.90 | I190: 6941594509170 | J190: 56.91 | K190: 2026-01-01 11:05:00 | L190: 2026-01-31 23:59:59 | M190: 0 | N190: 65 | O190: bf4c14681b74a0ddd2c1e340fb7eb26c
A191: 3424920923 | B191: 1605 | C191: L’Oréal Paris Elseve Full Resist Shampoo|Anti Hair Loss/Anti Dandruff/Hair Fall Control 440ml | D191: MYR | E191: 18482573437 | F191: active | G191: 3424920923_MY-18482573437 | H191: 53.50 | I191: 6923700980288 | J191: 42.80 | K191: 2026-01-01 11:05:00 | L191: 2026-01-31 23:59:59 | M191: 0 | N191: 440 | O191: 64a42e4d56d7d8d099c2ff06dce9bf22
A192: 3424977459 | B192: 10002070 | C192: L'Oreal Paris Elseve Full Resist Conditioner 440ml (Anti Hair Loss/Anti Dandruff/Hair Fall Control) | D192: MYR | E192: 18482454723 | F192: active | G192: 3424977459_MY-18482454723 | H192: 53.50 | I192: 6923700980271 | J192: 42.80 | K192: 2026-01-01 11:05:00 | L192: 2026-01-31 23:59:59 | M192: 0 | N192: 440 | O192: 17e5b0416e73eea63eb965a209c06135
A193: 3491075659 | B193: 10002962 | C193: [GWP - NOT FOR SALE] L'OREAL PARIS Elseve Full Resist Anti Hair Fall Shampoo and Conditioner 100ml - gimmick | D193: MYR | E193: 19195476926 | F193: active | G193: 3491075659_MY-19195476926 | H193: 0.00 | I193: 8886458694372 | M193: 0 | O193: 9a958ff1324af5eaf7c8b058bce27e7c
A194: 3517259221 | B194: 10100735 | C194: L’Oréal Paris Revitalift 2.5% Hyaluronic Acid & Caffeine Eye Serum 4% Niacinamide, Hydrate, Depuff,Targets Dark Circles & Fine Lines, Skin Care 20ml | D194: MYR | E194: 19416153125 | F194: active | G194: 3517259221_MY-19416153125 | H194: 107.90 | I194: 8994993017980 | J194: 102.51 | K194: 2026-01-01 11:05:00 | L194: 2026-01-31 23:59:59 | M194: 0 | N194: 20 | O194: b48db289fcec909c85287372bda5490b
A195: 3559969099 | B195: 1522 | C195: L’Oréal Paris Color Riche Intense Volume Matte Lipstick for 16H Long-lasting Hydrated Matte Lips | D195: MYR | E195: 19876846752 | F195: active | G195: 3559969099_MY-19876846752 | H195: 63.50 | I195: 6902395848929 | J195: 60.33 | K195: 2026-01-01 11:05:00 | L195: 2026-01-31 23:59:59 | M195: 0 | N195: 276 - LA LEATHER LIBERATED | O195: 87e36fc2f6dbf236bfc1683cec0c2c40
A196: 3559969099 | B196: 1522 | C196: L’Oréal Paris Color Riche Intense Volume Matte Lipstick for 16H Long-lasting Hydrated Matte Lips | D196: MYR | E196: 19876846753 | F196: active | G196: 3559969099_MY-19876846753 | H196: 63.50 | I196: 6902395848943 | J196: 60.33 | K196: 2026-01-01 11:05:00 | L196: 2026-01-31 23:59:59 | M196: 0 | N196: 339 - LE WOOD BRULANT | O196: 3868a0019a8b33e23d9e0a79f835af85
A197: 3559969099 | B197: 1522 | C197: L’Oréal Paris Color Riche Intense Volume Matte Lipstick for 16H Long-lasting Hydrated Matte Lips | D197: MYR | E197: 19876846754 | F197: active | G197: 3559969099_MY-19876846754 | H197: 63.50 | I197: 6902395848974 | J197: 60.33 | K197: 2026-01-01 11:05:00 | L197: 2026-01-31 23:59:59 | M197: 0 | N197: 666 - I WIN | O197: 3581db10b167449f1c7d739e29f971ed
A198: 3559969099 | B198: 1522 | C198: L’Oréal Paris Color Riche Intense Volume Matte Lipstick for 16H Long-lasting Hydrated Matte Lips | D198: MYR | E198: 21972184045 | F198: active | G198: 3559969099_MY-21972184045 | H198: 63.50 | I198: 6902395851028 | J198: 60.33 | K198: 2026-01-01 11:05:00 | L198: 2026-01-31 23:59:59 | M198: 0 | N198: 610 - LIGHT OOLONG | O198: d59416012a76a85ccfdc1a6494bef828
A199: 3559969099 | B199: 1522 | C199: L’Oréal Paris Color Riche Intense Volume Matte Lipstick for 16H Long-lasting Hydrated Matte Lips | D199: MYR | E199: 21856729321 | F199: active | G199: 3559969099_MY-21856729321 | H199: 63.50 | I199: 6902395851066 | J199: 60.33 | K199: 2026-01-01 11:05:00 | L199: 2026-01-31 23:59:59 | M199: 0 | N199: 614 - SWEET PAPAYA | O199: 1866846a531f218ecae701756fbb88de
A200: 3559969099 | B200: 1522 | C200: L’Oréal Paris Color Riche Intense Volume Matte Lipstick for 16H Long-lasting Hydrated Matte Lips | D200: MYR | E200: 21971990676 | F200: active | G200: 3559969099_MY-21971990676 | H200: 63.50 | I200: 6902395851035 | J200: 60.33 | K200: 2026-01-01 11:05:00 | L200: 2026-01-31 23:59:59 | M200: 0 | N200: 611 - NAKED HAWTHORN | O200: ca9679538a6a1e533ae68c9a0f0eeb8c
A201: 3559969099 | B201: 1522 | C201: L’Oréal Paris Color Riche Intense Volume Matte Lipstick for 16H Long-lasting Hydrated Matte Lips | D201: MYR | E201: 22839266054 | F201: active | G201: 3559969099_MY-22839266054 | H201: 63.50 | I201: 6902395970842 | J201: 60.33 | K201: 2026-01-01 11:05:00 | L201: 2026-01-31 23:59:59 | M201: 0 | N201: 520 - DEFIANT | O201: 15c9cd6f768ae3280f7a9ac10ca43a64
A202: 3559969099 | B202: 1522 | C202: L’Oréal Paris Color Riche Intense Volume Matte Lipstick for 16H Long-lasting Hydrated Matte Lips | D202: MYR | E202: 23169381973 | F202: active | G202: 3559969099_MY-23169381973 | H202: 63.50 | I202: 6902395971399 | J202: 60.33 | K202: 2026-01-01 11:05:00 | L202: 2026-01-31 23:59:59 | M202: 0 | N202: 667 - WIN | O202: 92e257c692afc8782c9df1f3b8a4a45e
A203: 3559969099 | B203: 1522 | C203: L’Oréal Paris Color Riche Intense Volume Matte Lipstick for 16H Long-lasting Hydrated Matte Lips | D203: MYR | E203: 22839266055 | F203: active | G203: 3559969099_MY-22839266055 | H203: 63.50 | I203: 6902395970859 | J203: 60.33 | K203: 2026-01-01 11:05:00 | L203: 2026-01-31 23:59:59 | M203: 0 | N203: 540 - UNSTOPPABLE | O203: 7dfe66cf6f1a4fb3363a2777a9823b97
A204: 3559969099 | B204: 1522 | C204: L’Oréal Paris Color Riche Intense Volume Matte Lipstick for 16H Long-lasting Hydrated Matte Lips | D204: MYR | E204: 23169381972 | F204: active | G204: 3559969099_MY-23169381972 | H204: 63.50 | I204: 6902395971382 | J204: 60.33 | K204: 2026-01-01 11:05:00 | L204: 2026-01-31 23:59:59 | M204: 0 | N204: 340 - WOOD | O204: 73d28ef4b56893036e838c7aed9a9a46
A205: 3559969099 | B205: 1522 | C205: L’Oréal Paris Color Riche Intense Volume Matte Lipstick for 16H Long-lasting Hydrated Matte Lips | D205: MYR | E205: 23169381975 | F205: active | G205: 3559969099_MY-23169381975 | H205: 63.50 | I205: 6902395971412 | J205: 60.33 | K205: 2026-01-01 11:05:00 | L205: 2026-01-31 23:59:59 | M205: 0 | N205: 616 - HAWTHORN | O205: 5d00b64e797c093cc4e54285b6f03413
... A219: 3577109565 | B219: 8086 | C219: L’Oreal Paris Youth Code Skin Activating Ferment Pre-Essence 30ml x 2 (Twinpack) | D219: MYR | E219: 20074850168 | F219: active | G219: 3577109565_MY-20074850168 | H219: 386.00 | I219: 9557534762627 | J219: 289.50 | K219: 2026-01-01 11:05:00 | L219: 2026-01-31 23:59:59 | M219: 0 | N219: 60 ml | O219: f8061df22f4e89edfd9b085b43e935fd
A220: 3599947760 | B220: 8081 | C220: [GLOW CHANGER] L'Oreal Paris Glycolic-Bright Glowing + Brighter Skin Starter Pack (Set of 3) | D220: MYR | E220: 20303484808 | F220: active | G220: 3599947760_MY-20303484808 | H220: 213.70 | I220: 9557534774545 | J220: 192.33 | K220: 2026-01-01 11:05:00 | L220: 2026-01-31 23:59:59 | M220: 0 | O220: 60befdd1af08b53f3c849649e2c325e4
A221: 3606585661 | B221: 1618 | C221: L'Oreal Paris Elseve Extraordinary Oil Pink 100ml (Very Dry Hair, Hair Treatment, Hair Oil) | D221: MYR | E221: 20358871036 | F221: active | G221: 3606585661_MY-20358871036 | H221: 61.90 | I221: 6923700950632 | J221: 58.81 | K221: 2026-01-01 11:05:00 | L221: 2026-01-31 23:59:59 | M221: 0 | N221: 100 | O221: dd54aaa87906cf8ea9aefade1543f447
A222: 3779667747 | B222: 10002962 | C222: [GWP - NOT FOR SALE] L'OREAL PARIS Glycolic Bright Serum 7.5mlx4 Tube - gimmick | D222: MYR | E222: 21761901349 | F222: active | G222: 3779667747_MY-21761901349 | H222: 0.00 | I222: 9557534781062 | M222: 0 | O222: ad2769448025c5d0457477a5a9ad39ab
A223: 3786667844 | B223: 10100735 | C223: L’Oréal Paris Glycolic Bright 3% [Glycolic Acid + Vitamin CG + Niacinamide] Reduce Dark Circle Eye Serum 20ml | D223: MYR | E223: 21845333055 | F223: active | G223: 3786667844_MY-21845333055 | H223: 89.90 | I223: 8994993020362 | J223: 85.41 | K223: 2026-01-01 11:05:00 | L223: 2026-01-31 23:59:59 | M223: 0 | N223: 20 ml | O223: 2d00cf0d72b19999311deef5ad09b43b
A224: 3802488377 | B224: 8084 | C224: L’Oréal Paris UV Defender Sun Repair / Sunscreen Invisible Serum SPF50+ Repair Dark Spots, Lines & Uneven Tone 30ml | D224: MYR | E224: 22003471052 | F224: active | G224: 3802488377_MY-22003471052 | H224: 89.90 | I224: 8994993020836 | J224: 85.41 | K224: 2026-01-01 11:05:00 | L224: 2026-01-31 23:59:59 | M224: 0 | N224: 30 | O224: 757c55462e0867aa72cc7b784cfdbf1e
A225: 3803819530 | B225: 1610 | C225: L'Oréal Paris Excellence Fashion Hair Color - #9.11 Silver Ash, Water Permeable (Hair Dye) | D225: MYR | E225: 22014352628 | F225: active | G225: 3803819530_MY-22014352628 | H225: 49.90 | I225: 6923700934403 | J225: 47.41 | K225: 2026-01-01 11:05:00 | L225: 2026-01-31 23:59:59 | M225: 0 | N225: Silver Ash,172 | O225: fa77c6d4a35f8f2e86b2ab6599af0093
A226: 3803884337 | B226: 1610 | C226: L'Oréal Paris Excellence Bleach Supreme Hair Color | D226: MYR | E226: 22014384470 | F226: active | G226: 3803884337_MY-22014384470 | H226: 53.90 | I226: 6923700985177 | J226: 51.21 | K226: 2026-01-01 11:05:00 | L226: 2026-01-31 23:59:59 | M226: 0 | N226: Bleach,174 | O226: db82a07a980950770a011d716869fea2
A227: 3804840309 | B227: 10002962 | C227: [GWP - NOT FOR SALE] L’Oréal Paris Exclusive 11 Piece Worth It Set - gimmick | D227: MYR | E227: 22022298742 | F227: active | G227: 3804840309_MY-22022298742 | H227: 0.00 | I227: 9557534782311 | M227: 0 | O227: fe28ba25c5bb32a568db84d223a96a6c
A228: 3820897663 | B228: 1519 | C228: L’Oréal Paris Infallible Matte Resistance Liquid Lipstick for 16H Long Lasting Matte Lips, Transfer and Smudge Proof | D228: MYR | E228: 24092549090 | F228: active | G228: 3820897663_MY-24092549090 | H228: 67.90 | I228: 6902395970958 | J228: 64.51 | K228: 2026-01-01 11:05:00 | L228: 2026-01-31 23:59:59 | M228: 0 | N228: 601 - WORTH IT | O228: 53b2736dfe20c28119f6ca65f770ce79
A229: 3820897663 | B229: 1519 | C229: L’Oréal Paris Infallible Matte Resistance Liquid Lipstick for 16H Long Lasting Matte Lips, Transfer and Smudge Proof | D229: MYR | E229: 24092549091 | F229: active | G229: 3820897663_MY-24092549091 | H229: 67.90 | I229: 6902395970965 | J229: 64.51 | K229: 2026-01-01 11:05:00 | L229: 2026-01-31 23:59:59 | M229: 0 | N229: 625 - Summer Fling | O229: 03dce4bb7b053a2fb407ee55532a6c56
A230: 3820897663 | B230: 1519 | C230: L’Oréal Paris Infallible Matte Resistance Liquid Lipstick for 16H Long Lasting Matte Lips, Transfer and Smudge Proof | D230: MYR | E230: 24092549088 | F230: active | G230: 3820897663_MY-24092549088 | H230: 67.90 | I230: 6902395970989 | J230: 64.51 | K230: 2026-01-01 11:05:00 | L230: 2026-01-31 23:59:59 | M230: 0 | N230: 635 - WORTH IT MEDIUM | O230: df6aee2e3cca58a98a83a5eb3df8ef35
A231: 3820897663 | B231: 1519 | C231: L’Oréal Paris Infallible Matte Resistance Liquid Lipstick for 16H Long Lasting Matte Lips, Transfer and Smudge Proof | D231: MYR | E231: 24092549089 | F231: active | G231: 3820897663_MY-24092549089 | H231: 67.90 | I231: 6902395970996 | J231: 64.51 | K231: 2026-01-01 11:05:00 | L231: 2026-01-31 23:59:59 | M231: 0 | N231: 645 - Crush Alert | O231: acff93f895ba221b61ea98c8e54c55fc
A232: 3820897663 | B232: 1519 | C232: L’Oréal Paris Infallible Matte Resistance Liquid Lipstick for 16H Long Lasting Matte Lips, Transfer and Smudge Proof | D232: MYR | E232: 22146489273 | F232: active | G232: 3820897663_MY-22146489273 | H232: 67.90 | I232: 6902395853312 | J232: 64.51 | K232: 2026-01-01 11:05:00 | L232: 2026-01-31 23:59:59 | M232: 0 | N232: 230 - SHOPPING SPREE​ | O232: 7ae6b49521359c74934d2174fa4ff0cd
A233: 3820897663 | B233: 1519 | C233: L’Oréal Paris Infallible Matte Resistance Liquid Lipstick for 16H Long Lasting Matte Lips, Transfer and Smudge Proof | D233: MYR | E233: 22146489272 | F233: active | G233: 3820897663_MY-22146489272 | H233: 67.90 | I233: 6902395853305 | J233: 64.51 | K233: 2026-01-01 11:05:00 | L233: 2026-01-31 23:59:59 | M233: 0 | N233: 210 - TROPICAL VACAY​ | O233: c830950dd6bffebc93c61deb91b30c89
A234: 3820897663 | B234: 1519 | C234: L’Oréal Paris Infallible Matte Resistance Liquid Lipstick for 16H Long Lasting Matte Lips, Transfer and Smudge Proof | D234: MYR | E234: 22146489275 | F234: active | G234: 3820897663_MY-22146489275 | H234: 67.90 | I234: 6902395853367 | J234: 64.51 | K234: 2026-01-01 11:05:00 | L234: 2026-01-31 23:59:59 | M234: 0 | N234: 420 - LE ROUGE PARIS | O234: b872f4f38eb414303962eb27c6c6bf20
A235: 3820897663 | B235: 1519 | C235: L’Oréal Paris Infallible Matte Resistance Liquid Lipstick for 16H Long Lasting Matte Lips, Transfer and Smudge Proof | D235: MYR | E235: 22146489274 | F235: active | G235: 3820897663_MY-22146489274 | H235: 67.90 | I235: 6902395853336 | J235: 64.51 | K235: 2026-01-01 11:05:00 | L235: 2026-01-31 23:59:59 | M235: 0 | N235: 245 - FRENCH KISS | O235: 83b7d7a9c5d28c48516683a261392b1c
A236: 3820897663 | B236: 1519 | C236: L’Oréal Paris Infallible Matte Resistance Liquid Lipstick for 16H Long Lasting Matte Lips, Transfer and Smudge Proof | D236: MYR | E236: 22146489269 | F236: active | G236: 3820897663_MY-22146489269 | H236: 67.90 | I236: 6902395853268 | J236: 64.51 | K236: 2026-01-01 11:05:00 | L236: 2026-01-31 23:59:59 | M236: 0 | N236: 105 - Breakfast in Bed | O236: 66facd26992d8a6e874cda4c267f0eb9
A237: 3820897663 | B237: 1519 | C237: L’Oréal Paris Infallible Matte Resistance Liquid Lipstick for 16H Long Lasting Matte Lips, Transfer and Smudge Proof | D237: MYR | E237: 22146489271 | F237: active | G237: 3820897663_MY-22146489271 | H237: 67.90 | I237: 6902395853282 | J237: 64.51 | K237: 2026-01-01 11:05:00 | L237: 2026-01-31 23:59:59 | M237: 0 | N237: 120 - MAJOR CRUSH​ | O237: afd0e9a25d930216a2a497552c98d12b
A238: 3820897663 | B238: 1519 | C238: L’Oréal Paris Infallible Matte Resistance Liquid Lipstick for 16H Long Lasting Matte Lips, Transfer and Smudge Proof | D238: MYR | E238: 22146489270 | F238: active | G238: 3820897663_MY-22146489270 | H238: 67.90 | I238: 6902395853275 | J238: 64.51 | K238: 2026-01-01 11:05:00 | L238: 2026-01-31 23:59:59 | M238: 0 | N238: 115 - SNOOZE YOUR ALARM​ | O238: eb576392164a680b87a8da7b4f6fec3a
A239: 3820897663 | B239: 1519 | C239: L’Oréal Paris Infallible Matte Resistance Liquid Lipstick for 16H Long Lasting Matte Lips, Transfer and Smudge Proof | D239: MYR | E239: 24092549087 | F239: active | G239: 3820897663_MY-24092549087 | H239: 67.90 | I239: 6902395970972 | J239: 64.51 | K239: 2026-01-01 11:05:00 | L239: 2026-01-31 23:59:59 | M239: 0 | N239: 630 - ROSÉ HEAT | O239: 52acd17ec270e1b1d7a0263145a2c5b9
A240: 3841233843 | B240: 10002962 | C240: [GWP - NOT FOR SALE] L’Oréal Paris Worth It Make Up Pouch - gimmick | D240: MYR | E240: 22203691706 | F240: active | G240: 3841233843_MY-22203691706 | H240: 0.00 | I240: 9557534782946 | M240: 0 | O240: 6af810fe20376c81c22f65a6a340163b
A241: 3854794414 | B241: 1618 | C241: L'Oreal Paris Elseve Extraordinary Oil Hair Treatment Set - Pink (100ml x 2) | D241: MYR | E241: 22247330660 | F241: active | G241: 3854794414_MY-22247330660 | H241: 123.80 | I241: 9557534776907 | J241: 92.85 | K241: 2026-01-01 11:05:00 | L241: 2026-01-31 23:59:59 | M241: 0 | N241: 200 | O241: 9d222ea61f8b42d11972e22fbc44671f
A242: 3865731543 | B242: 8081 | C242: L'Oréal Paris (2-3pcs Skincare Set) Cleanser + Serum + Moisturizer with Hyaluronic Acid or Glycolic Acid | D242: MYR | E242: 22334737556 | F242: active | G242: 3865731543_MY-22334737556 | H242: 137.80 | I242: 9557534782076 | J242: 124.02 | K242: 2026-01-01 11:05:00 | L242: 2026-01-31 23:59:59 | N242: HA Foam + Cream | O242: 13330bafd7bcfd26895024f3393c2830
A243: 3865731543 | B243: 8081 | C243: L'Oréal Paris (2-3pcs Skincare Set) Cleanser + Serum + Moisturizer with Hyaluronic Acid or Glycolic Acid | D243: MYR | E243: 22334737557 | F243: active | G243: 3865731543_MY-22334737557 | H243: 208.90 | I243: 9557534782069 | J243: 188.01 | K243: 2026-01-01 11:05:00 | L243: 2026-01-31 23:59:59 | N243: Glyco 3pcs Bundle | O243: 855b9c4a754619d5ae969aea783fc30b
A244: 3865731543 | B244: 8081 | C244: L'Oréal Paris (2-3pcs Skincare Set) Cleanser + Serum + Moisturizer with Hyaluronic Acid or Glycolic Acid | D244: MYR | E244: 22334737558 | F244: active | G244: 3865731543_MY-22334737558 | H244: 178.80 | I244: 9557534782052 | J244: 160.92 | K244: 2026-01-01 11:05:00 | L244: 2026-01-31 23:59:59 | N244: Glyco Day + Night | O244: 34b162a1610f77b4b28dc520c452a666
A245: 3865731543 | B245: 8081 | C245: L'Oréal Paris (2-3pcs Skincare Set) Cleanser + Serum + Moisturizer with Hyaluronic Acid or Glycolic Acid | D245: MYR | E245: 22334737559 | F245: active | G245: 3865731543_MY-22334737559 | H245: 123.80 | I245: 9557534782083 | J245: 111.42 | K245: 2026-01-01 11:05:00 | L245: 2026-01-31 23:59:59 | N245: Glyco Foam + Day | O245: 473aeba0f7d57f534bd4fdf84d17c7a2
A246: 3865731543 | B246: 8081 | C246: L'Oréal Paris (2-3pcs Skincare Set) Cleanser + Serum + Moisturizer with Hyaluronic Acid or Glycolic Acid | D246: MYR | E246: 22373407273 | F246: active | G246: 3865731543_MY-22373407273 | H246: 202.80 | I246: 9557534782366 | J246: 182.52 | K246: 2026-01-01 11:05:00 | L246: 2026-01-31 23:59:59 | N246: HA Serum + Day Cream | O246: 0e3a1027551595181be0c1a05716f098
A247: 3865731543 | B247: 8081 | C247: L'Oréal Paris (2-3pcs Skincare Set) Cleanser + Serum + Moisturizer with Hyaluronic Acid or Glycolic Acid | D247: MYR | E247: 22334737560 | F247: active | G247: 3865731543_MY-22334737560 | H247: 173.80 | I247: 9557534782342 | J247: 156.42 | K247: 2026-01-01 11:05:00 | L247: 2026-01-31 23:59:59 | N247: GB Serum + Day | O247: 27f46d24eb43439ab452014eb5da233f
A248: 3865860885 | B248: 8081 | C248: L'Oréal Paris (4pcs Skincare Set) Cleanser + Serum + Moisturizer with Hyaluronic Acid or Glycolic Acid | D248: MYR | E248: 22334807570 | F248: active | G248: 3865860885_MY-22334807570 | H248: 308.60 | I248: 9557534782137 | J248: 216.02 | K248: 2026-01-01 11:05:00 | L248: 2026-01-31 23:59:59 | N248: (4pcs Bundle) Glyco | O248: b62fc6e1ef57eb9f850c847dc618c4ca
A249: 3865860885 | B249: 8081 | C249: L'Oréal Paris (4pcs Skincare Set) Cleanser + Serum + Moisturizer with Hyaluronic Acid or Glycolic Acid | D249: MYR | E249: 22334807569 | F249: active | G249: 3865860885_MY-22334807569 | H249: 242.70 | I249: 9557534782168 | J249: 174.74 | K249: 2026-01-01 11:05:00 | L249: 2026-01-31 23:59:59 | N249: (3pcs Bundle) HA | O249: 0a49b37c6bfa7b24bfc8ec33f64b09f7
A250: 3866026128 | B250: 8081 | C250: L'Oréal Paris Best Selling (2pcs Skincare Set) Dual Serum/Toner + Serum with Hyaluronic Acid or Glycolic Acid | D250: MYR | E250: 22373482279 | F250: active | G250: 3866026128_MY-22373482279 | H250: 179.80 | I250: 9557534782335 | J250: 134.85 | K250: 2026-01-01 11:05:00 | L250: 2026-01-31 23:59:59 | N250: GB Eye Serum + Serum | O250: a1b660c2d2258c3b0ebd30c9bd9e2976
A251: 3866026128 | B251: 8081 | C251: L'Oréal Paris Best Selling (2pcs Skincare Set) Dual Serum/Toner + Serum with Hyaluronic Acid or Glycolic Acid | D251: MYR | E251: 22334998837 | F251: active | G251: 3866026128_MY-22334998837 | H251: 194.80 | I251: 9557534782144 | J251: 146.10 | K251: 2026-01-01 11:05:00 | L251: 2026-01-31 23:59:59 | N251: HA + Glyco Serum | O251: a1f9ec6d5cc513cf7a9cfb4295a573b6
...

Sheet Price Change - non Flash
A1: Type of Input required | B1: *Mandatory Fields
B2: Optional Fields
B3: Dropdown
B4: Autofill
A5: *Please take note for any input with double pricing with same date/duration, SVC will submit the lowest price
P15: Automated | S15: Automated | T15: Automated | W15: Automated | X15: Automated | AA15: Automated | AB15: Automated | AE15: Automated | AF15: Automated | AI15: Automated | AJ15: Automated | AM15: Automated | AN15: Automated | AQ15: Automated | AR15: Automated | AU15: Automated | AV15: Automated | AY15: Automated | AZ15: Automated | BC15: Automated | BD15: Automated | BG15: Automated | BH15: Automated | BK15: Automated | BP15: Automated | BS15: Automated
P16: PLEASE SELECT CAMPAIGN NAME TO AUTO-FILL CELLS FROM CAMPAIGN CALENDAR | BL16: PLEASE SELECT CAMPAIGN NAME TO AUTO-FILL CELLS FROM CAMPAIGN CALENDAR
P17: =IF(R18 = "", "", R18) | T17: =IF(V18 = "", "", V18) | X17: =IF(Z18 = "", "", Z18) | AB17: =IF(AD18 = "", "", AD18) | AF17: =IF(AH18 = "", "", AH18) | AJ17: =IF(AL18 = "", "", AL18) | AN17: =IF(AP18 = "", "", AP18) | AR17: =IF(AT18 = "", "", AT18) | AV17: =IF(AX18 = "", "", AX18) | AZ17: =IF(BB18 = "", "", BB18) | BD17: =IF(BF18 = "", "", BF18) | BH17: =IF(BJ18 = "", "", BJ18) | BL17: =IF(BN18 = "", "", BN18) | BP17: =IF(BR18 = "", "", BR18)
O18: Input Row | Q18: Campaign Name | R18: BAU Full Day | U18: Campaign Name | V18: BAU Laz Flash | Y18: Campaign Name | Z18: 3.3 Sale x Raya Full Day | AC18: Campaign Name | AD18: 3.3 Sale x Raya CBMO | AG18: Campaign Name | AH18: 3.3 Sale x Raya Laz Flash | AK18: Campaign Name | AL18: MMS x Raya Full Day | AO18: Campaign Name | AP18: MMS x Raya CMBO | AS18: Campaign Name | AT18: MMS x Raya Laz Flash | AW18: Campaign Name | AX18: PDS x Birthday Full Day | BA18: Campaign Name | BB18: PDS x Birthday CMBO | BE18: Campaign Name | BF18: PDS x Birthday Laz Flash | BI18: Campaign Name | BM18: Campaign Name | BN18: Campaign Name | BQ18: Campaign Name | BR18: Campaign Name
O19: Automated | Q19: Campaign Type | R19: {=IF(R$18="","", IFERROR(_xlfn.TEXTJOIN(CHAR(10), TRUE, IF((R$18='Campaign Calendar'!$I$11:$I$45),'Campaign Calendar'!$J$11:$J$45, "")), ""))} | U19: Campaign Type | V19: {=IF(V$18="","", IFERROR(_xlfn.TEXTJOIN(CHAR(10), TRUE, IF((V$18='Campaign Calendar'!$I$11:$I$45),'Campaign Calendar'!$J$11:$J$45, "")), ""))} | Y19: Campaign Type | Z19: {=IF(Z$18="","", IFERROR(_xlfn.TEXTJOIN(CHAR(10), TRUE, IF((Z$18='Campaign Calendar'!$I$11:$I$45),'Campaign Calendar'!$J$11:$J$45, "")), ""))} | AC19: Campaign Type | AD19: {=IF(AD$18="","", IFERROR(_xlfn.TEXTJOIN(CHAR(10), TRUE, IF((AD$18='Campaign Calendar'!$I$11:$I$45),'Campaign Calendar'!$J$11:$J$45, "")), ""))} | AG19: Campaign Type | AH19: {=IF(AH$18="","", IFERROR(_xlfn.TEXTJOIN(CHAR(10), TRUE, IF((AH$18='Campaign Calendar'!$I$11:$I$45),'Campaign Calendar'!$J$11:$J$45, "")), ""))} | AK19: Campaign Type | AL19: {=IF(AL$18="","", IFERROR(_xlfn.TEXTJOIN(CHAR(10), TRUE, IF((AL$18='Campaign Calendar'!$I$11:$I$45),'Campaign Calendar'!$J$11:$J$45, "")), ""))} | AO19: Campaign Type | AP19: {=IF(AP$18="","", IFERROR(_xlfn.TEXTJOIN(CHAR(10), TRUE, IF((AP$18='Campaign Calendar'!$I$11:$I$45),'Campaign Calendar'!$J$11:$J$45, "")), ""))} | AS19: Campaign Type | AT19: {=IF(AT$18="","", IFERROR(_xlfn.TEXTJOIN(CHAR(10), TRUE, IF((AT$18='Campaign Calendar'!$I$11:$I$45),'Campaign Calendar'!$J$11:$J$45, "")), ""))} | AW19: Campaign Type | AX19: {=IF(AX$18="","", IFERROR(_xlfn.TEXTJOIN(CHAR(10), TRUE, IF((AX$18='Campaign Calendar'!$I$11:$I$45),'Campaign Calendar'!$J$11:$J$45, "")), ""))} | BA19: Campaign Type | BB19: {=IF(BB$18="","", IFERROR(_xlfn.TEXTJOIN(CHAR(10), TRUE, IF((BB$18='Campaign Calendar'!$I$11:$I$45),'Campaign Calendar'!$J$11:$J$45, "")), ""))} | BE19: Campaign Type | BF19: {=IF(BF$18="","", IFERROR(_xlfn.TEXTJOIN(CHAR(10), TRUE, IF((BF$18='Campaign Calendar'!$I$11:$I$45),'Campaign Calendar'!$J$11:$J$45, "")), ""))} | BI19: Campaign Type | BJ19: {=IF(BJ$18="","", IFERROR(_xlfn.TEXTJOIN(CHAR(10), TRUE, IF((BJ$18='Campaign Calendar'!$I$11:$I$45),'Campaign Calendar'!$J$11:$J$45, "")), ""))} | BM19: Campaign Type | BN19: {=IF(BN$18="","", IFERROR(_xlfn.TEXTJOIN(CHAR(10), TRUE, IF((BN$18='Campaign Calendar'!$I$11:$I$45),'Campaign Calendar'!$J$11:$J$45, "")), ""))} | BQ19: Campaign Type | BR19: {=IF(BR$18="","", IFERROR(_xlfn.TEXTJOIN(CHAR(10), TRUE, IF((BR$18='Campaign Calendar'!$I$11:$I$45),'Campaign Calendar'!$J$11:$J$45, "")), ""))}
O20: Automated | Q20: Campaign Tiering | R20: {=IF(R$18="","",IFERROR(_xlfn.TEXTJOIN(CHAR(10), TRUE, IF((R$18='Campaign Calendar'!$I$11:$I$45),'Campaign Calendar'!$K$11:$K$45, "")), ""))} | U20: Campaign Tiering | V20: {=IF(V$18="","",IFERROR(_xlfn.TEXTJOIN(CHAR(10), TRUE, IF((V$18='Campaign Calendar'!$I$11:$I$45),'Campaign Calendar'!$K$11:$K$45, "")), ""))} | Y20: Campaign Tiering | Z20: {=IF(Z$18="","",IFERROR(_xlfn.TEXTJOIN(CHAR(10), TRUE, IF((Z$18='Campaign Calendar'!$I$11:$I$45),'Campaign Calendar'!$K$11:$K$45, "")), ""))} | AC20: Campaign Tiering | AD20: {=IF(AD$18="","",IFERROR(_xlfn.TEXTJOIN(CHAR(10), TRUE, IF((AD$18='Campaign Calendar'!$I$11:$I$45),'Campaign Calendar'!$K$11:$K$45, "")), ""))} | AG20: Campaign Tiering | AH20: {=IF(AH$18="","",IFERROR(_xlfn.TEXTJOIN(CHAR(10), TRUE, IF((AH$18='Campaign Calendar'!$I$11:$I$45),'Campaign Calendar'!$K$11:$K$45, "")), ""))} | AK20: Campaign Tiering | AL20: {=IF(AL$18="","",IFERROR(_xlfn.TEXTJOIN(CHAR(10), TRUE, IF((AL$18='Campaign Calendar'!$I$11:$I$45),'Campaign Calendar'!$K$11:$K$45, "")), ""))} | AO20: Campaign Tiering | AP20: {=IF(AP$18="","",IFERROR(_xlfn.TEXTJOIN(CHAR(10), TRUE, IF((AP$18='Campaign Calendar'!$I$11:$I$45),'Campaign Calendar'!$K$11:$K$45, "")), ""))} | AS20: Campaign Tiering | AT20: {=IF(AT$18="","",IFERROR(_xlfn.TEXTJOIN(CHAR(10), TRUE, IF((AT$18='Campaign Calendar'!$I$11:$I$45),'Campaign Calendar'!$K$11:$K$45, "")), ""))} | AW20: Campaign Tiering | AX20: {=IF(AX$18="","",IFERROR(_xlfn.TEXTJOIN(CHAR(10), TRUE, IF((AX$18='Campaign Calendar'!$I$11:$I$45),'Campaign Calendar'!$K$11:$K$45, "")), ""))} | BA20: Campaign Tiering | BB20: {=IF(BB$18="","",IFERROR(_xlfn.TEXTJOIN(CHAR(10), TRUE, IF((BB$18='Campaign Calendar'!$I$11:$I$45),'Campaign Calendar'!$K$11:$K$45, "")), ""))} | BE20: Campaign Tiering | BF20: {=IF(BF$18="","",IFERROR(_xlfn.TEXTJOIN(CHAR(10), TRUE, IF((BF$18='Campaign Calendar'!$I$11:$I$45),'Campaign Calendar'!$K$11:$K$45, "")), ""))} | BI20: Campaign Tiering | BJ20: {=IF(BJ$18="","",IFERROR(_xlfn.TEXTJOIN(CHAR(10), TRUE, IF((BJ$18='Campaign Calendar'!$I$11:$I$45),'Campaign Calendar'!$K$11:$K$45, "")), ""))} | BM20: Campaign Tiering | BN20: {=IF(BN$18="","",IFERROR(_xlfn.TEXTJOIN(CHAR(10), TRUE, IF((BN$18='Campaign Calendar'!$I$11:$I$45),'Campaign Calendar'!$K$11:$K$45, "")), ""))} | BQ20: Campaign Tiering | BR20: {=IF(BR$18="","",IFERROR(_xlfn.TEXTJOIN(CHAR(10), TRUE, IF((BR$18='Campaign Calendar'!$I$11:$I$45),'Campaign Calendar'!$K$11:$K$45, "")), ""))}
O21: Automated | Q21: Start Date | R21: {=IF(R$18="","",IFERROR(_xlfn.TEXTJOIN(CHAR(10), TRUE, IF((R$18='Campaign Calendar'!$I$11:$I$45),TEXT('Campaign Calendar'!$E$11:$E$45, "dd-MMM-yyyy"), "")), ""))} | U21: Start Date | V21: {=IF(V$18="","",IFERROR(_xlfn.TEXTJOIN(CHAR(10), TRUE, IF((V$18='Campaign Calendar'!$I$11:$I$45),TEXT('Campaign Calendar'!$E$11:$E$45, "dd-MMM-yyyy"), "")), ""))} | Y21: Start Date | Z21: {=IF(Z$18="","",IFERROR(_xlfn.TEXTJOIN(CHAR(10), TRUE, IF((Z$18='Campaign Calendar'!$I$11:$I$45),TEXT('Campaign Calendar'!$E$11:$E$45, "dd-MMM-yyyy"), "")), ""))} | AC21: Start Date | AD21: {=IF(AD$18="","",IFERROR(_xlfn.TEXTJOIN(CHAR(10), TRUE, IF((AD$18='Campaign Calendar'!$I$11:$I$45),TEXT('Campaign Calendar'!$E$11:$E$45, "dd-MMM-yyyy"), "")), ""))} | AG21: Start Date | AH21: {=IF(AH$18="","",IFERROR(_xlfn.TEXTJOIN(CHAR(10), TRUE, IF((AH$18='Campaign Calendar'!$I$11:$I$45),TEXT('Campaign Calendar'!$E$11:$E$45, "dd-MMM-yyyy"), "")), ""))} | AK21: Start Date | AL21: {=IF(AL$18="","",IFERROR(_xlfn.TEXTJOIN(CHAR(10), TRUE, IF((AL$18='Campaign Calendar'!$I$11:$I$45),TEXT('Campaign Calendar'!$E$11:$E$45, "dd-MMM-yyyy"), "")), ""))} | AO21: Start Date | AP21: {=IF(AP$18="","",IFERROR(_xlfn.TEXTJOIN(CHAR(10), TRUE, IF((AP$18='Campaign Calendar'!$I$11:$I$45),TEXT('Campaign Calendar'!$E$11:$E$45, "dd-MMM-yyyy"), "")), ""))} | AS21: Start Date | AT21: {=IF(AT$18="","",IFERROR(_xlfn.TEXTJOIN(CHAR(10), TRUE, IF((AT$18='Campaign Calendar'!$I$11:$I$45),TEXT('Campaign Calendar'!$E$11:$E$45, "dd-MMM-yyyy"), "")), ""))} | AW21: Start Date | AX21: {=IF(AX$18="","",IFERROR(_xlfn.TEXTJOIN(CHAR(10), TRUE, IF((AX$18='Campaign Calendar'!$I$11:$I$45),TEXT('Campaign Calendar'!$E$11:$E$45, "dd-MMM-yyyy"), "")), ""))} | BA21: Start Date | BB21: {=IF(BB$18="","",IFERROR(_xlfn.TEXTJOIN(CHAR(10), TRUE, IF((BB$18='Campaign Calendar'!$I$11:$I$45),TEXT('Campaign Calendar'!$E$11:$E$45, "dd-MMM-yyyy"), "")), ""))} | BE21: Start Date | BF21: {=IF(BF$18="","",IFERROR(_xlfn.TEXTJOIN(CHAR(10), TRUE, IF((BF$18='Campaign Calendar'!$I$11:$I$45),TEXT('Campaign Calendar'!$E$11:$E$45, "dd-MMM-yyyy"), "")), ""))} | BI21: Start Date | BJ21: {=IF(BJ$18="","",IFERROR(_xlfn.TEXTJOIN(CHAR(10), TRUE, IF((BJ$18='Campaign Calendar'!$I$11:$I$45),TEXT('Campaign Calendar'!$E$11:$E$45, "dd-MMM-yyyy"), "")), ""))} | BM21: Start Date | BN21: {=IF(BN$18="","",IFERROR(_xlfn.TEXTJOIN(CHAR(10), TRUE, IF((BN$18='Campaign Calendar'!$I$11:$I$45),TEXT('Campaign Calendar'!$E$11:$E$45, "dd-MMM-yyyy"), "")), ""))} | BQ21: Start Date | BR21: {=IF(BR$18="","",IFERROR(_xlfn.TEXTJOIN(CHAR(10), TRUE, IF((BR$18='Campaign Calendar'!$I$11:$I$45),TEXT('Campaign Calendar'!$E$11:$E$45, "dd-MMM-yyyy"), "")), ""))}
O22: Automated | Q22: End Date | R22: {=IF(R$18="","",IFERROR(_xlfn.TEXTJOIN(CHAR(10), TRUE, IF((R$18='Campaign Calendar'!$I$11:$I$45),TEXT('Campaign Calendar'!$F$11:$F$45, "dd-MMM-yyyy"), "")), ""))} | U22: End Date | V22: {=IF(V$18="","",IFERROR(_xlfn.TEXTJOIN(CHAR(10), TRUE, IF((V$18='Campaign Calendar'!$I$11:$I$45),TEXT('Campaign Calendar'!$F$11:$F$45, "dd-MMM-yyyy"), "")), ""))} | Y22: End Date | Z22: {=IF(Z$18="","",IFERROR(_xlfn.TEXTJOIN(CHAR(10), TRUE, IF((Z$18='Campaign Calendar'!$I$11:$I$45),TEXT('Campaign Calendar'!$F$11:$F$45, "dd-MMM-yyyy"), "")), ""))} | AC22: End Date | AD22: {=IF(AD$18="","",IFERROR(_xlfn.TEXTJOIN(CHAR(10), TRUE, IF((AD$18='Campaign Calendar'!$I$11:$I$45),TEXT('Campaign Calendar'!$F$11:$F$45, "dd-MMM-yyyy"), "")), ""))} | AG22: End Date | AH22: {=IF(AH$18="","",IFERROR(_xlfn.TEXTJOIN(CHAR(10), TRUE, IF((AH$18='Campaign Calendar'!$I$11:$I$45),TEXT('Campaign Calendar'!$F$11:$F$45, "dd-MMM-yyyy"), "")), ""))} | AK22: End Date | AL22: {=IF(AL$18="","",IFERROR(_xlfn.TEXTJOIN(CHAR(10), TRUE, IF((AL$18='Campaign Calendar'!$I$11:$I$45),TEXT('Campaign Calendar'!$F$11:$F$45, "dd-MMM-yyyy"), "")), ""))} | AO22: End Date | AP22: {=IF(AP$18="","",IFERROR(_xlfn.TEXTJOIN(CHAR(10), TRUE, IF((AP$18='Campaign Calendar'!$I$11:$I$45),TEXT('Campaign Calendar'!$F$11:$F$45, "dd-MMM-yyyy"), "")), ""))} | AS22: End Date | AT22: {=IF(AT$18="","",IFERROR(_xlfn.TEXTJOIN(CHAR(10), TRUE, IF((AT$18='Campaign Calendar'!$I$11:$I$45),TEXT('Campaign Calendar'!$F$11:$F$45, "dd-MMM-yyyy"), "")), ""))} | AW22: End Date | AX22: {=IF(AX$18="","",IFERROR(_xlfn.TEXTJOIN(CHAR(10), TRUE, IF((AX$18='Campaign Calendar'!$I$11:$I$45),TEXT('Campaign Calendar'!$F$11:$F$45, "dd-MMM-yyyy"), "")), ""))} | BA22: End Date | BB22: {=IF(BB$18="","",IFERROR(_xlfn.TEXTJOIN(CHAR(10), TRUE, IF((BB$18='Campaign Calendar'!$I$11:$I$45),TEXT('Campaign Calendar'!$F$11:$F$45, "dd-MMM-yyyy"), "")), ""))} | BE22: End Date | BF22: {=IF(BF$18="","",IFERROR(_xlfn.TEXTJOIN(CHAR(10), TRUE, IF((BF$18='Campaign Calendar'!$I$11:$I$45),TEXT('Campaign Calendar'!$F$11:$F$45, "dd-MMM-yyyy"), "")), ""))} | BI22: End Date | BJ22: {=IF(BJ$18="","",IFERROR(_xlfn.TEXTJOIN(CHAR(10), TRUE, IF((BJ$18='Campaign Calendar'!$I$11:$I$45),TEXT('Campaign Calendar'!$F$11:$F$45, "dd-MMM-yyyy"), "")), ""))} | BM22: End Date | BN22: {=IF(BN$18="","",IFERROR(_xlfn.TEXTJOIN(CHAR(10), TRUE, IF((BN$18='Campaign Calendar'!$I$11:$I$45),TEXT('Campaign Calendar'!$F$11:$F$45, "dd-MMM-yyyy"), "")), ""))} | BQ22: End Date | BR22: {=IF(BR$18="","",IFERROR(_xlfn.TEXTJOIN(CHAR(10), TRUE, IF((BR$18='Campaign Calendar'!$I$11:$I$45),TEXT('Campaign Calendar'!$F$11:$F$45, "dd-MMM-yyyy"), "")), ""))}
O23: Automated | Q23: Start Time | R23: {=IF(R$18="","",IFERROR(_xlfn.TEXTJOIN(CHAR(10), TRUE, IF((R$18='Campaign Calendar'!$I$11:$I$45),TEXT('Campaign Calendar'!$G$11:$G$45, "hh:mm:ss"), "")), ""))} | U23: Start Time | V23: {=IF(V$18="","",IFERROR(_xlfn.TEXTJOIN(CHAR(10), TRUE, IF((V$18='Campaign Calendar'!$I$11:$I$45),TEXT('Campaign Calendar'!$G$11:$G$45, "hh:mm:ss"), "")), ""))} | Y23: Start Time | Z23: {=IF(Z$18="","",IFERROR(_xlfn.TEXTJOIN(CHAR(10), TRUE, IF((Z$18='Campaign Calendar'!$I$11:$I$45),TEXT('Campaign Calendar'!$G$11:$G$45, "hh:mm:ss"), "")), ""))} | AC23: Start Time | AD23: {=IF(AD$18="","",IFERROR(_xlfn.TEXTJOIN(CHAR(10), TRUE, IF((AD$18='Campaign Calendar'!$I$11:$I$45),TEXT('Campaign Calendar'!$G$11:$G$45, "hh:mm:ss"), "")), ""))} | AG23: Start Time | AH23: {=IF(AH$18="","",IFERROR(_xlfn.TEXTJOIN(CHAR(10), TRUE, IF((AH$18='Campaign Calendar'!$I$11:$I$45),TEXT('Campaign Calendar'!$G$11:$G$45, "hh:mm:ss"), "")), ""))} | AK23: Start Time | AL23: {=IF(AL$18="","",IFERROR(_xlfn.TEXTJOIN(CHAR(10), TRUE, IF((AL$18='Campaign Calendar'!$I$11:$I$45),TEXT('Campaign Calendar'!$G$11:$G$45, "hh:mm:ss"), "")), ""))} | AO23: Start Time | AP23: {=IF(AP$18="","",IFERROR(_xlfn.TEXTJOIN(CHAR(10), TRUE, IF((AP$18='Campaign Calendar'!$I$11:$I$45),TEXT('Campaign Calendar'!$G$11:$G$45, "hh:mm:ss"), "")), ""))} | AS23: Start Time | AT23: {=IF(AT$18="","",IFERROR(_xlfn.TEXTJOIN(CHAR(10), TRUE, IF((AT$18='Campaign Calendar'!$I$11:$I$45),TEXT('Campaign Calendar'!$G$11:$G$45, "hh:mm:ss"), "")), ""))} | AW23: Start Time | AX23: {=IF(AX$18="","",IFERROR(_xlfn.TEXTJOIN(CHAR(10), TRUE, IF((AX$18='Campaign Calendar'!$I$11:$I$45),TEXT('Campaign Calendar'!$G$11:$G$45, "hh:mm:ss"), "")), ""))} | BA23: Start Time | BB23: {=IF(BB$18="","",IFERROR(_xlfn.TEXTJOIN(CHAR(10), TRUE, IF((BB$18='Campaign Calendar'!$I$11:$I$45),TEXT('Campaign Calendar'!$G$11:$G$45, "hh:mm:ss"), "")), ""))} | BE23: Start Time | BF23: {=IF(BF$18="","",IFERROR(_xlfn.TEXTJOIN(CHAR(10), TRUE, IF((BF$18='Campaign Calendar'!$I$11:$I$45),TEXT('Campaign Calendar'!$G$11:$G$45, "hh:mm:ss"), "")), ""))} | BI23: Start Time | BJ23: {=IF(BJ$18="","",IFERROR(_xlfn.TEXTJOIN(CHAR(10), TRUE, IF((BJ$18='Campaign Calendar'!$I$11:$I$45),TEXT('Campaign Calendar'!$G$11:$G$45, "hh:mm:ss"), "")), ""))} | BM23: Start Time | BN23: {=IF(BN$18="","",IFERROR(_xlfn.TEXTJOIN(CHAR(10), TRUE, IF((BN$18='Campaign Calendar'!$I$11:$I$45),TEXT('Campaign Calendar'!$G$11:$G$45, "hh:mm:ss"), "")), ""))} | BQ23: Start Time | BR23: {=IF(BR$18="","",IFERROR(_xlfn.TEXTJOIN(CHAR(10), TRUE, IF((BR$18='Campaign Calendar'!$I$11:$I$45),TEXT('Campaign Calendar'!$G$11:$G$45, "hh:mm:ss"), "")), ""))}
O24: Automated | Q24: End Time | R24: {=IF(R$18="","",IFERROR(_xlfn.TEXTJOIN(CHAR(10), TRUE, IF((R$18='Campaign Calendar'!$I$11:$I$45),TEXT('Campaign Calendar'!$H$11:$H$45, "hh:mm:ss "), "")), ""))} | U24: End Time | V24: {=IF(V$18="","",IFERROR(_xlfn.TEXTJOIN(CHAR(10), TRUE, IF((V$18='Campaign Calendar'!$I$11:$I$45),TEXT('Campaign Calendar'!$H$11:$H$45, "hh:mm:ss"), "")), ""))} | Y24: End Time | Z24: {=IF(Z$18="","",IFERROR(_xlfn.TEXTJOIN(CHAR(10), TRUE, IF((Z$18='Campaign Calendar'!$I$11:$I$45),TEXT('Campaign Calendar'!$H$11:$H$45, "hh:mm:ss"), "")), ""))} | AC24: End Time | AD24: {=IF(AD$18="","",IFERROR(_xlfn.TEXTJOIN(CHAR(10), TRUE, IF((AD$18='Campaign Calendar'!$I$11:$I$45),TEXT('Campaign Calendar'!$H$11:$H$45, "hh:mm:ss"), "")), ""))} | AG24: End Time | AH24: {=IF(AH$18="","",IFERROR(_xlfn.TEXTJOIN(CHAR(10), TRUE, IF((AH$18='Campaign Calendar'!$I$11:$I$45),TEXT('Campaign Calendar'!$H$11:$H$45, "hh:mm:ss"), "")), ""))} | AK24: End Time | AL24: {=IF(AL$18="","",IFERROR(_xlfn.TEXTJOIN(CHAR(10), TRUE, IF((AL$18='Campaign Calendar'!$I$11:$I$45),TEXT('Campaign Calendar'!$H$11:$H$45, "hh:mm:ss"), "")), ""))} | AO24: End Time | AP24: {=IF(AP$18="","",IFERROR(_xlfn.TEXTJOIN(CHAR(10), TRUE, IF((AP$18='Campaign Calendar'!$I$11:$I$45),TEXT('Campaign Calendar'!$H$11:$H$45, "hh:mm:ss"), "")), ""))} | AS24: End Time | AT24: {=IF(AT$18="","",IFERROR(_xlfn.TEXTJOIN(CHAR(10), TRUE, IF((AT$18='Campaign Calendar'!$I$11:$I$45),TEXT('Campaign Calendar'!$H$11:$H$45, "hh:mm:ss"), "")), ""))} | AW24: End Time | AX24: {=IF(AX$18="","",IFERROR(_xlfn.TEXTJOIN(CHAR(10), TRUE, IF((AX$18='Campaign Calendar'!$I$11:$I$45),TEXT('Campaign Calendar'!$H$11:$H$45, "hh:mm:ss"), "")), ""))} | BA24: End Time | BB24: {=IF(BB$18="","",IFERROR(_xlfn.TEXTJOIN(CHAR(10), TRUE, IF((BB$18='Campaign Calendar'!$I$11:$I$45),TEXT('Campaign Calendar'!$H$11:$H$45, "hh:mm:ss"), "")), ""))} | BE24: End Time | BF24: {=IF(BF$18="","",IFERROR(_xlfn.TEXTJOIN(CHAR(10), TRUE, IF((BF$18='Campaign Calendar'!$I$11:$I$45),TEXT('Campaign Calendar'!$H$11:$H$45, "hh:mm:ss"), "")), ""))} | BI24: End Time | BJ24: {=IF(BJ$18="","",IFERROR(_xlfn.TEXTJOIN(CHAR(10), TRUE, IF((BJ$18='Campaign Calendar'!$I$11:$I$45),TEXT('Campaign Calendar'!$H$11:$H$45, "hh:mm:ss"), "")), ""))} | BM24: End Time | BN24: {=IF(BN$18="","",IFERROR(_xlfn.TEXTJOIN(CHAR(10), TRUE, IF((BN$18='Campaign Calendar'!$I$11:$I$45),TEXT('Campaign Calendar'!$H$11:$H$45, "hh:mm:ss"), "")), ""))} | BQ24: End Time | BR24: {=IF(BR$18="","",IFERROR(_xlfn.TEXTJOIN(CHAR(10), TRUE, IF((BR$18='Campaign Calendar'!$I$11:$I$45),TEXT('Campaign Calendar'!$H$11:$H$45, "hh:mm:ss"), "")), ""))}
O25: Automated | Q25: Completion | R25: {=IF(R$18="","",IFERROR(_xlfn.TEXTJOIN(CHAR(10), TRUE, IF((R$18='Campaign Calendar'!$I$11:$I$45),'Campaign Calendar'!$L$11:$L$45, "")), ""))} | U25: Completion | V25: {=IF(V$18="","",IFERROR(_xlfn.TEXTJOIN(CHAR(10), TRUE, IF((V$18='Campaign Calendar'!$I$11:$I$45),'Campaign Calendar'!$L$11:$L$45, "")), ""))} | Y25: Completion | Z25: {=IF(Z$18="","",IFERROR(_xlfn.TEXTJOIN(CHAR(10), TRUE, IF((Z$18='Campaign Calendar'!$I$11:$I$45),'Campaign Calendar'!$L$11:$L$45, "")), ""))} | AC25: Completion | AD25: {=IF(AD$18="","",IFERROR(_xlfn.TEXTJOIN(CHAR(10), TRUE, IF((AD$18='Campaign Calendar'!$I$11:$I$45),'Campaign Calendar'!$L$11:$L$45, "")), ""))} | AG25: Completion | AH25: {=IF(AH$18="","",IFERROR(_xlfn.TEXTJOIN(CHAR(10), TRUE, IF((AH$18='Campaign Calendar'!$I$11:$I$45),'Campaign Calendar'!$L$11:$L$45, "")), ""))} | AK25: Completion | AL25: {=IF(AL$18="","",IFERROR(_xlfn.TEXTJOIN(CHAR(10), TRUE, IF((AL$18='Campaign Calendar'!$I$11:$I$45),'Campaign Calendar'!$L$11:$L$45, "")), ""))} | AO25: Completion | AP25: {=IF(AP$18="","",IFERROR(_xlfn.TEXTJOIN(CHAR(10), TRUE, IF((AP$18='Campaign Calendar'!$I$11:$I$45),'Campaign Calendar'!$L$11:$L$45, "")), ""))} | AS25: Completion | AT25: {=IF(AT$18="","",IFERROR(_xlfn.TEXTJOIN(CHAR(10), TRUE, IF((AT$18='Campaign Calendar'!$I$11:$I$45),'Campaign Calendar'!$L$11:$L$45, "")), ""))} | AW25: Completion | AX25: {=IF(AX$18="","",IFERROR(_xlfn.TEXTJOIN(CHAR(10), TRUE, IF((AX$18='Campaign Calendar'!$I$11:$I$45),'Campaign Calendar'!$L$11:$L$45, "")), ""))} | BA25: Completion | BB25: {=IF(BB$18="","",IFERROR(_xlfn.TEXTJOIN(CHAR(10), TRUE, IF((BB$18='Campaign Calendar'!$I$11:$I$45),'Campaign Calendar'!$L$11:$L$45, "")), ""))} | BE25: Completion | BF25: {=IF(BF$18="","",IFERROR(_xlfn.TEXTJOIN(CHAR(10), TRUE, IF((BF$18='Campaign Calendar'!$I$11:$I$45),'Campaign Calendar'!$L$11:$L$45, "")), ""))} | BI25: Completion | BJ25: {=IF(BJ$18="","",IFERROR(_xlfn.TEXTJOIN(CHAR(10), TRUE, IF((BJ$18='Campaign Calendar'!$I$11:$I$45),'Campaign Calendar'!$L$11:$L$45, "")), ""))} | BM25: Completion | BN25: {=IF(BN$18="","",IFERROR(_xlfn.TEXTJOIN(CHAR(10), TRUE, IF((BN$18='Campaign Calendar'!$I$11:$I$45),'Campaign Calendar'!$L$11:$L$45, "")), ""))} | BQ25: Completion | BR25: {=IF(BR$18="","",IFERROR(_xlfn.TEXTJOIN(CHAR(10), TRUE, IF((BR$18='Campaign Calendar'!$I$11:$I$45),'Campaign Calendar'!$L$11:$L$45, "")), ""))}
Q26: Treasure Bowl Name* | U26: Treasure Bowl Name* | Y26: Treasure Bowl Name* | AC26: Treasure Bowl Name* | AG26: Treasure Bowl Name* | AK26: Treasure Bowl Name* | AO26: Treasure Bowl Name* | AS26: Treasure Bowl Name* | AW26: Treasure Bowl Name* | BA26: Treasure Bowl Name* | BE26: Treasure Bowl Name* | BI26: Treasure Bowl Name* | BM26: Treasure Bowl Name* | BQ26: Treasure Bowl Name*
B27: DQ - Format | D27: DQ - Format | E27: DQ - Format | G27: Dropdown | N27: Dropdown | O27: DQ - Format | Q27: Treasure Bowl ID* | U27: Treasure Bowl ID* | Y27: Treasure Bowl ID* | AC27: Treasure Bowl ID* | AG27: Treasure Bowl ID* | AK27: Treasure Bowl ID* | AO27: Treasure Bowl ID* | AS27: Treasure Bowl ID* | AW27: Treasure Bowl ID* | BA27: Treasure Bowl ID* | BE27: Treasure Bowl ID* | BI27: Treasure Bowl ID* | BM27: Treasure Bowl ID* | BQ27: Treasure Bowl ID*
D28: Product ID / Seller SKU | E28: Model ID | P28: =IF(R18 = "", "", R18) | T28: =IF(V18 = "", "", V18) | X28: =IF(Z18 = "", "", Z18) | AB28: =IF(AD18 = "", "", AD18) | AF28: =IF(AH18 = "", "", AH18) | AJ28: =IF(AL18 = "", "", AL18) | AN28: =IF(AP18 = "", "", AP18) | AR28: =IF(AT18 = "", "", AT18) | AV28: =IF(AX18 = "", "", AX18) | AZ28: =IF(BB18 = "", "", BB18) | BD28: =IF(BF18 = "", "", BF18) | BH28: =IF(BJ18 = "", "", BJ18) | BL28: =IF(BN18 = "", "", BN18) | BP28: =IF(BR18 = "", "", BR18)
B29: EAN Code | C29: SKU SHOP ID | D29: Product ID | E29: Variation ID | F29: Product Name | G29: Hero/Non-Hero | H29: Product Short Name - Variation Name | I29: Brand | J29: Ranking | K29: Category | L29: Franchise | M29: Selling Status | N29: VBOM/Single/Bundle | O29: L'Oreal recommended Price (list price) | P29: Campaign Name | Q29: Tier | R29: Campaign Price | S29: Promo Discount % | T29: Campaign Name | U29: Tier | V29: Campaign Price | W29: Promo Discount % | X29: Campaign Name | Y29: Tier | Z29: Campaign Price | AA29: Promo Discount % | AB29: Campaign Name | AC29: Tier | AD29: Campaign Price | AE29: Promo Discount % | AF29: Campaign Name | AG29: Tier | AH29: Campaign Price | AI29: Promo Discount % | AJ29: Campaign Name | AK29: Tier | AL29: Campaign Price | AM29: Promo Discount % | AN29: Campaign Name | AO29: Tier | AP29: Campaign Price | AQ29: Promo Discount % | AR29: Campaign Name | AS29: Tier | AT29: Campaign Price | AU29: Promo Discount % | AV29: Campaign Name | AW29: Tier | AX29: Campaign Price | AY29: Promo Discount % | AZ29: Campaign Name | BA29: Tier | BB29: Campaign Price | BC29: Promo Discount % | BD29: Campaign Name | BE29: Tier | BF29: Campaign Price | BG29: Promo Discount % | BH29: Campaign Name | BI29: Tier | BJ29: Campaign Price | BK29: Promo Discount % | BL29: Campaign Name | BM29: Tier | BN29: Campaign Price | BO29: Promo Discount % | BP29: Campaign Name | BQ29: Tier | BR29: Campaign Price | BS29: Promo Discount %
B30: 9557534782113 | C30: 3869848181_MY-22367431335 | D30: 3869848181 | F30: L'Oréal Paris (2-3pcs Haircare Set) Shampoo + Conditioners with Anti Hairfall & Anti Dry Hair | N30: VBOM | O30: 107 | P30: =IF($O30 = "", "", R$18) | Q30: =IF($O30="","",R$20) | R30: 80.25 | S30: =IF(R30 = 0, "", 1-R30/$O30) | T30: =IF($O30 = "", "", V$18) | U30: =IF($O30="","",V$20) | V30: 69.55 | W30: =IF(V30 = 0, "", 1-V30/$O30) | X30: =IF($O30 = "", "", Z$18) | Y30: =IF($O30="","",Z$20) | Z30: 64.2 | AA30: =IF(Z30 = 0, "", 1-Z30/$O30) | AB30: =IF($O30 = "", "", AD$18) | AC30: =IF($O30="","",AD$20) | AD30: 58.85 | AE30: =IF(AD30 = 0, "", 1-AD30/$O30) | AF30: =IF($O30 = "", "", AH$18) | AG30: =IF($O30="","",AH$20) | AH30: 53.5 | AI30: =IF(AH30 = 0, "", 1-AH30/$O30) | AJ30: =IF($O30 = "", "", AL$18) | AK30: =IF($O30="","",AL$20) | AL30: 74.9 | AM30: =IF(AL30 = 0, "", 1-AL30/$O30) | AN30: =IF($O30 = "", "", AP$18) | AO30: =IF($O30="","",AP$20) | AP30: 69.55 | AQ30: =IF(AP30 = 0, "", 1-AP30/$O30) | AR30: =IF($O30 = "", "", AT$18) | AS30: =IF($O30="","",AT$20) | AT30: 64.2 | AU30: =IF(AT30 = 0, "", 1-AT30/$O30) | AV30: =IF($O30 = "", "", AX$18) | AW30: =IF($O30="","",AX$20) | AX30: 64.2 | AY30: =IF(AX30 = 0, "", 1-AX30/$O30) | AZ30: =IF($O30 = "", "", BB$18) | BA30: =IF($O30="","",BB$20) | BB30: 58.85 | BC30: =IF(BB30 = 0, "", 1-BB30/$O30) | BD30: =IF($O30 = "", "", BF$18) | BE30: =IF($O30="","",BF$20) | BF30: 53.5 | BG30: =IF(BF30 = 0, "", 1-BF30/$O30) | BH30: =IF($O30 = "", "", BJ$18) | BI30: =IF($O30="","",BJ$20) | BK30: =IF(BJ30 = 0, "", 1-BJ30/$O30) | BL30: =IF($O30 = "", "", BN$18) | BM30: =IF($O30="","",BN$20) | BO30: =IF(BN30 = 0, "", 1-BN30/$O30) | BP30: =IF($O30 = "", "", BR$18) | BQ30: =IF($O30="","",BR$20) | BS30: =IF(BR30 = 0, "", 1-BR30/$O30)
B31: 9557534782090 | C31: 3869848181_MY-22367431340 | D31: 3869848181 | F31: L'Oréal Paris (2-3pcs Haircare Set) Shampoo + Conditioners with Anti Hairfall & Anti Dry Hair | N31: VBOM | O31: 71 | P31: =IF($O31 = "", "", R$18) | Q31: =IF($O31="","",R$20) | R31: 53.25 | S31: =IF(R31 = 0, "", 1-R31/$O31) | T31: =IF($O31 = "", "", V$18) | U31: =IF($O31="","",V$20) | V31: 46.15 | W31: =IF(V31 = 0, "", 1-V31/$O31) | X31: =IF($O31 = "", "", Z$18) | Y31: =IF($O31="","",Z$20) | Z31: 42.6 | AA31: =IF(Z31 = 0, "", 1-Z31/$O31) | AB31: =IF($O31 = "", "", AD$18) | AC31: =IF($O31="","",AD$20) | AD31: 39.05 | AE31: =IF(AD31 = 0, "", 1-AD31/$O31) | AF31: =IF($O31 = "", "", AH$18) | AG31: =IF($O31="","",AH$20) | AH31: 35.5 | AI31: =IF(AH31 = 0, "", 1-AH31/$O31) | AJ31: =IF($O31 = "", "", AL$18) | AK31: =IF($O31="","",AL$20) | AL31: 49.7 | AM31: =IF(AL31 = 0, "", 1-AL31/$O31) | AN31: =IF($O31 = "", "", AP$18) | AO31: =IF($O31="","",AP$20) | AP31: 46.15 | AQ31: =IF(AP31 = 0, "", 1-AP31/$O31) | AR31: =IF($O31 = "", "", AT$18) | AS31: =IF($O31="","",AT$20) | AT31: 42.6 | AU31: =IF(AT31 = 0, "", 1-AT31/$O31) | AV31: =IF($O31 = "", "", AX$18) | AW31: =IF($O31="","",AX$20) | AX31: 42.6 | AY31: =IF(AX31 = 0, "", 1-AX31/$O31) | AZ31: =IF($O31 = "", "", BB$18) | BA31: =IF($O31="","",BB$20) | BB31: 39.05 | BC31: =IF(BB31 = 0, "", 1-BB31/$O31) | BD31: =IF($O31 = "", "", BF$18) | BE31: =IF($O31="","",BF$20) | BF31: 35.5 | BG31: =IF(BF31 = 0, "", 1-BF31/$O31) | BH31: =IF($O31 = "", "", BJ$18) | BI31: =IF($O31="","",BJ$20) | BK31: =IF(BJ31 = 0, "", 1-BJ31/$O31) | BL31: =IF($O31 = "", "", BN$18) | BM31: =IF($O31="","",BN$20) | BO31: =IF(BN31 = 0, "", 1-BN31/$O31) | BP31: =IF($O31 = "", "", BR$18) | BQ31: =IF($O31="","",BR$20) | BS31: =IF(BR31 = 0, "", 1-BR31/$O31)
B32: 9557534782106 | C32: 3869848181_MY-22367431341 | D32: 3869848181 | F32: L'Oréal Paris (2-3pcs Haircare Set) Shampoo + Conditioners with Anti Hairfall & Anti Dry Hair | N32: VBOM | O32: 71 | P32: =IF($O32 = "", "", R$18) | Q32: =IF($O32="","",R$20) | R32: 53.25 | S32: =IF(R32 = 0, "", 1-R32/$O32) | T32: =IF($O32 = "", "", V$18) | U32: =IF($O32="","",V$20) | V32: 46.15 | W32: =IF(V32 = 0, "", 1-V32/$O32) | X32: =IF($O32 = "", "", Z$18) | Y32: =IF($O32="","",Z$20) | Z32: 46.15 | AA32: =IF(Z32 = 0, "", 1-Z32/$O32) | AB32: =IF($O32 = "", "", AD$18) | AC32: =IF($O32="","",AD$20) | AD32: 42.6 | AE32: =IF(AD32 = 0, "", 1-AD32/$O32) | AF32: =IF($O32 = "", "", AH$18) | AG32: =IF($O32="","",AH$20) | AH32: 39.05 | AI32: =IF(AH32 = 0, "", 1-AH32/$O32) | AJ32: =IF($O32 = "", "", AL$18) | AK32: =IF($O32="","",AL$20) | AL32: 49.7 | AM32: =IF(AL32 = 0, "", 1-AL32/$O32) | AN32: =IF($O32 = "", "", AP$18) | AO32: =IF($O32="","",AP$20) | AP32: 46.15 | AQ32: =IF(AP32 = 0, "", 1-AP32/$O32) | AR32: =IF($O32 = "", "", AT$18) | AS32: =IF($O32="","",AT$20) | AT32: 42.6 | AU32: =IF(AT32 = 0, "", 1-AT32/$O32) | AV32: =IF($O32 = "", "", AX$18) | AW32: =IF($O32="","",AX$20) | AX32: 46.15 | AY32: =IF(AX32 = 0, "", 1-AX32/$O32) | AZ32: =IF($O32 = "", "", BB$18) | BA32: =IF($O32="","",BB$20) | BB32: 42.6 | BC32: =IF(BB32 = 0, "", 1-BB32/$O32) | BD32: =IF($O32 = "", "", BF$18) | BE32: =IF($O32="","",BF$20) | BF32: 39.05 | BG32: =IF(BF32 = 0, "", 1-BF32/$O32) | BH32: =IF($O32 = "", "", BJ$18) | BI32: =IF($O32="","",BJ$20) | BK32: =IF(BJ32 = 0, "", 1-BJ32/$O32) | BL32: =IF($O32 = "", "", BN$18) | BM32: =IF($O32="","",BN$20) | BO32: =IF(BN32 = 0, "", 1-BN32/$O32) | BP32: =IF($O32 = "", "", BR$18) | BQ32: =IF($O32="","",BR$20) | BS32: =IF(BR32 = 0, "", 1-BR32/$O32)
B33: 9557534779434 | C33: 3869848181_MY-22367431338 | D33: 3869848181 | F33: L'Oréal Paris (2-3pcs Haircare Set) Shampoo + Conditioners with Anti Hairfall & Anti Dry Hair | N33: VBOM | O33: 107 | P33: =IF($O33 = "", "", R$18) | Q33: =IF($O33="","",R$20) | R33: 80.25 | S33: =IF(R33 = 0, "", 1-R33/$O33) | T33: =IF($O33 = "", "", V$18) | U33: =IF($O33="","",V$20) | V33: 69.55 | W33: =IF(V33 = 0, "", 1-V33/$O33) | X33: =IF($O33 = "", "", Z$18) | Y33: =IF($O33="","",Z$20) | Z33: 64.2 | AA33: =IF(Z33 = 0, "", 1-Z33/$O33) | AB33: =IF($O33 = "", "", AD$18) | AC33: =IF($O33="","",AD$20) | AD33: 58.85 | AE33: =IF(AD33 = 0, "", 1-AD33/$O33) | AF33: =IF($O33 = "", "", AH$18) | AG33: =IF($O33="","",AH$20) | AH33: 53.5 | AI33: =IF(AH33 = 0, "", 1-AH33/$O33) | AJ33: =IF($O33 = "", "", AL$18) | AK33: =IF($O33="","",AL$20) | AL33: 74.9 | AM33: =IF(AL33 = 0, "", 1-AL33/$O33) | AN33: =IF($O33 = "", "", AP$18) | AO33: =IF($O33="","",AP$20) | AP33: 69.55 | AQ33: =IF(AP33 = 0, "", 1-AP33/$O33) | AR33: =IF($O33 = "", "", AT$18) | AS33: =IF($O33="","",AT$20) | AT33: 64.2 | AU33: =IF(AT33 = 0, "", 1-AT33/$O33) | AV33: =IF($O33 = "", "", AX$18) | AW33: =IF($O33="","",AX$20) | AX33: 64.2 | AY33: =IF(AX33 = 0, "", 1-AX33/$O33) | AZ33: =IF($O33 = "", "", BB$18) | BA33: =IF($O33="","",BB$20) | BB33: 58.85 | BC33: =IF(BB33 = 0, "", 1-BB33/$O33) | BD33: =IF($O33 = "", "", BF$18) | BE33: =IF($O33="","",BF$20) | BF33: 53.5 | BG33: =IF(BF33 = 0, "", 1-BF33/$O33) | BH33: =IF($O33 = "", "", BJ$18) | BI33: =IF($O33="","",BJ$20) | BK33: =IF(BJ33 = 0, "", 1-BJ33/$O33) | BL33: =IF($O33 = "", "", BN$18) | BM33: =IF($O33="","",BN$20) | BO33: =IF(BN33 = 0, "", 1-BN33/$O33) | BP33: =IF($O33 = "", "", BR$18) | BQ33: =IF($O33="","",BR$20) | BS33: =IF(BR33 = 0, "", 1-BR33/$O33)
B34: 9557534779458 | C34: 3869848181_MY-22367431339 | D34: 3869848181 | F34: L'Oréal Paris (2-3pcs Haircare Set) Shampoo + Conditioners with Anti Hairfall & Anti Dry Hair | N34: VBOM | O34: 232.2 | P34: =IF($O34 = "", "", R$18) | Q34: =IF($O34="","",R$20) | R34: 174.15 | S34: =IF(R34 = 0, "", 1-R34/$O34) | T34: =IF($O34 = "", "", V$18) | U34: =IF($O34="","",V$20) | V34: 150.93 | W34: =IF(V34 = 0, "", 1-V34/$O34) | X34: =IF($O34 = "", "", Z$18) | Y34: =IF($O34="","",Z$20) | Z34: 150.93 | AA34: =IF(Z34 = 0, "", 1-Z34/$O34) | AB34: =IF($O34 = "", "", AD$18) | AC34: =IF($O34="","",AD$20) | AD34: 139.32 | AE34: =IF(AD34 = 0, "", 1-AD34/$O34) | AF34: =IF($O34 = "", "", AH$18) | AG34: =IF($O34="","",AH$20) | AH34: 127.71 | AI34: =IF(AH34 = 0, "", 1-AH34/$O34) | AJ34: =IF($O34 = "", "", AL$18) | AK34: =IF($O34="","",AL$20) | AL34: 162.54 | AM34: =IF(AL34 = 0, "", 1-AL34/$O34) | AN34: =IF($O34 = "", "", AP$18) | AO34: =IF($O34="","",AP$20) | AP34: 150.93 | AQ34: =IF(AP34 = 0, "", 1-AP34/$O34) | AR34: =IF($O34 = "", "", AT$18) | AS34: =IF($O34="","",AT$20) | AT34: 139.32 | AU34: =IF(AT34 = 0, "", 1-AT34/$O34) | AV34: =IF($O34 = "", "", AX$18) | AW34: =IF($O34="","",AX$20) | AX34: 150.93 | AY34: =IF(AX34 = 0, "", 1-AX34/$O34) | AZ34: =IF($O34 = "", "", BB$18) | BA34: =IF($O34="","",BB$20) | BB34: 139.32 | BC34: =IF(BB34 = 0, "", 1-BB34/$O34) | BD34: =IF($O34 = "", "", BF$18) | BE34: =IF($O34="","",BF$20) | BF34: 127.71 | BG34: =IF(BF34 = 0, "", 1-BF34/$O34) | BH34: =IF($O34 = "", "", BJ$18) | BI34: =IF($O34="","",BJ$20) | BK34: =IF(BJ34 = 0, "", 1-BJ34/$O34) | BL34: =IF($O34 = "", "", BN$18) | BM34: =IF($O34="","",BN$20) | BO34: =IF(BN34 = 0, "", 1-BN34/$O34) | BP34: =IF($O34 = "", "", BR$18) | BQ34: =IF($O34="","",BR$20) | BS34: =IF(BR34 = 0, "", 1-BR34/$O34)
B35: 9557534782175 | C35: 3869848181_MY-22367431336 | D35: 3869848181 | F35: L'Oréal Paris (2-3pcs Haircare Set) Shampoo + Conditioners with Anti Hairfall & Anti Dry Hair | N35: VBOM | O35: 107 | P35: =IF($O35 = "", "", R$18) | Q35: =IF($O35="","",R$20) | R35: 80.25 | S35: =IF(R35 = 0, "", 1-R35/$O35) | T35: =IF($O35 = "", "", V$18) | U35: =IF($O35="","",V$20) | V35: 69.55 | W35: =IF(V35 = 0, "", 1-V35/$O35) | X35: =IF($O35 = "", "", Z$18) | Y35: =IF($O35="","",Z$20) | Z35: 64.2 | AA35: =IF(Z35 = 0, "", 1-Z35/$O35) | AB35: =IF($O35 = "", "", AD$18) | AC35: =IF($O35="","",AD$20) | AD35: 58.85 | AE35: =IF(AD35 = 0, "", 1-AD35/$O35) | AF35: =IF($O35 = "", "", AH$18) | AG35: =IF($O35="","",AH$20) | AH35: 53.5 | AI35: =IF(AH35 = 0, "", 1-AH35/$O35) | AJ35: =IF($O35 = "", "", AL$18) | AK35: =IF($O35="","",AL$20) | AL35: 74.9 | AM35: =IF(AL35 = 0, "", 1-AL35/$O35) | AN35: =IF($O35 = "", "", AP$18) | AO35: =IF($O35="","",AP$20) | AP35: 69.55 | AQ35: =IF(AP35 = 0, "", 1-AP35/$O35) | AR35: =IF($O35 = "", "", AT$18) | AS35: =IF($O35="","",AT$20) | AT35: 64.2 | AU35: =IF(AT35 = 0, "", 1-AT35/$O35) | AV35: =IF($O35 = "", "", AX$18) | AW35: =IF($O35="","",AX$20) | AX35: 64.2 | AY35: =IF(AX35 = 0, "", 1-AX35/$O35) | AZ35: =IF($O35 = "", "", BB$18) | BA35: =IF($O35="","",BB$20) | BB35: 58.85 | BC35: =IF(BB35 = 0, "", 1-BB35/$O35) | BD35: =IF($O35 = "", "", BF$18) | BE35: =IF($O35="","",BF$20) | BF35: 53.5 | BG35: =IF(BF35 = 0, "", 1-BF35/$O35) | BH35: =IF($O35 = "", "", BJ$18) | BI35: =IF($O35="","",BJ$20) | BK35: =IF(BJ35 = 0, "", 1-BJ35/$O35) | BL35: =IF($O35 = "", "", BN$18) | BM35: =IF($O35="","",BN$20) | BO35: =IF(BN35 = 0, "", 1-BN35/$O35) | BP35: =IF($O35 = "", "", BR$18) | BQ35: =IF($O35="","",BR$20) | BS35: =IF(BR35 = 0, "", 1-BR35/$O35)
B36: 9557534779441 | C36: 3869848181_MY-22367431337 | D36: 3869848181 | F36: L'Oréal Paris (2-3pcs Haircare Set) Shampoo + Conditioners with Anti Hairfall & Anti Dry Hair | N36: VBOM | O36: 107 | P36: =IF($O36 = "", "", R$18) | Q36: =IF($O36="","",R$20) | R36: 80.25 | S36: =IF(R36 = 0, "", 1-R36/$O36) | T36: =IF($O36 = "", "", V$18) | U36: =IF($O36="","",V$20) | V36: 69.55 | W36: =IF(V36 = 0, "", 1-V36/$O36) | X36: =IF($O36 = "", "", Z$18) | Y36: =IF($O36="","",Z$20) | Z36: 64.2 | AA36: =IF(Z36 = 0, "", 1-Z36/$O36) | AB36: =IF($O36 = "", "", AD$18) | AC36: =IF($O36="","",AD$20) | AD36: 58.85 | AE36: =IF(AD36 = 0, "", 1-AD36/$O36) | AF36: =IF($O36 = "", "", AH$18) | AG36: =IF($O36="","",AH$20) | AH36: 53.5 | AI36: =IF(AH36 = 0, "", 1-AH36/$O36) | AJ36: =IF($O36 = "", "", AL$18) | AK36: =IF($O36="","",AL$20) | AL36: 74.9 | AM36: =IF(AL36 = 0, "", 1-AL36/$O36) | AN36: =IF($O36 = "", "", AP$18) | AO36: =IF($O36="","",AP$20) | AP36: 69.55 | AQ36: =IF(AP36 = 0, "", 1-AP36/$O36) | AR36: =IF($O36 = "", "", AT$18) | AS36: =IF($O36="","",AT$20) | AT36: 64.2 | AU36: =IF(AT36 = 0, "", 1-AT36/$O36) | AV36: =IF($O36 = "", "", AX$18) | AW36: =IF($O36="","",AX$20) | AX36: 64.2 | AY36: =IF(AX36 = 0, "", 1-AX36/$O36) | AZ36: =IF($O36 = "", "", BB$18) | BA36: =IF($O36="","",BB$20) | BB36: 58.85 | BC36: =IF(BB36 = 0, "", 1-BB36/$O36) | BD36: =IF($O36 = "", "", BF$18) | BE36: =IF($O36="","",BF$20) | BF36: 53.5 | BG36: =IF(BF36 = 0, "", 1-BF36/$O36) | BH36: =IF($O36 = "", "", BJ$18) | BI36: =IF($O36="","",BJ$20) | BK36: =IF(BJ36 = 0, "", 1-BJ36/$O36) | BL36: =IF($O36 = "", "", BN$18) | BM36: =IF($O36="","",BN$20) | BO36: =IF(BN36 = 0, "", 1-BN36/$O36) | BP36: =IF($O36 = "", "", BR$18) | BQ36: =IF($O36="","",BR$20) | BS36: =IF(BR36 = 0, "", 1-BR36/$O36)
B37: 9557534751393 | C37: LO533HBACOZN3GANMY-216793474 | D37: 230150628 | F37: L’Oréal Paris Elseve Extraordinary Oil Gold For All Hair Types, Hair Serum, Hair Treatment, Hair Oil 100ml Twinpack | N37: PBOM | O37: 123.8 | P37: =IF($O37 = "", "", R$18) | Q37: =IF($O37="","",R$20) | R37: 92.85 | S37: =IF(R37 = 0, "", 1-R37/$O37) | T37: =IF($O37 = "", "", V$18) | U37: =IF($O37="","",V$20) | V37: 80.47 | W37: =IF(V37 = 0, "", 1-V37/$O37) | X37: =IF($O37 = "", "", Z$18) | Y37: =IF($O37="","",Z$20) | Z37: 74.28 | AA37: =IF(Z37 = 0, "", 1-Z37/$O37) | AB37: =IF($O37 = "", "", AD$18) | AC37: =IF($O37="","",AD$20) | AD37: 68.09 | AE37: =IF(AD37 = 0, "", 1-AD37/$O37) | AF37: =IF($O37 = "", "", AH$18) | AG37: =IF($O37="","",AH$20) | AH37: 61.9 | AI37: =IF(AH37 = 0, "", 1-AH37/$O37) | AJ37: =IF($O37 = "", "", AL$18) | AK37: =IF($O37="","",AL$20) | AL37: 86.66 | AM37: =IF(AL37 = 0, "", 1-AL37/$O37) | AN37: =IF($O37 = "", "", AP$18) | AO37: =IF($O37="","",AP$20) | AP37: 80.47 | AQ37: =IF(AP37 = 0, "", 1-AP37/$O37) | AR37: =IF($O37 = "", "", AT$18) | AS37: =IF($O37="","",AT$20) | AT37: 74.28 | AU37: =IF(AT37 = 0, "", 1-AT37/$O37) | AV37: =IF($O37 = "", "", AX$18) | AW37: =IF($O37="","",AX$20) | AX37: 74.28 | AY37: =IF(AX37 = 0, "", 1-AX37/$O37) | AZ37: =IF($O37 = "", "", BB$18) | BA37: =IF($O37="","",BB$20) | BB37: 68.09 | BC37: =IF(BB37 = 0, "", 1-BB37/$O37) | BD37: =IF($O37 = "", "", BF$18) | BE37: =IF($O37="","",BF$20) | BF37: 61.9 | BG37: =IF(BF37 = 0, "", 1-BF37/$O37) | BH37: =IF($O37 = "", "", BJ$18) | BI37: =IF($O37="","",BJ$20) | BL37: =IF($O37 = "", "", BN$18) | BM37: =IF($O37="","",BN$20) | BO37: =IF(BN37 = 0, "", 1-BN37/$O37) | BP37: =IF($O37 = "", "", BR$18) | BQ37: =IF($O37="","",BR$20) | BS37: =IF(BR37 = 0, "", 1-BR37/$O37)
B38: 3600523192700 | C38: LO533HBAD3DGXRANMY-250824264 | D38: 251680470 | F38: L'Oreal Paris Magic Retouch Instant Root Concealer Spray Cover Greys Roots (Hair Colouring & Hair Care) | N38: Single | O38: 48.9 | P38: =IF($O38 = "", "", R$18) | Q38: =IF($O38="","",R$20) | R38: 39.12 | S38: =IF(R38 = 0, "", 1-R38/$O38) | T38: =IF($O38 = "", "", V$18) | U38: =IF($O38="","",V$20) | V38: 34.23 | W38: =IF(V38 = 0, "", 1-V38/$O38) | X38: =IF($O38 = "", "", Z$18) | Y38: =IF($O38="","",Z$20) | Z38: 34.23 | AA38: =IF(Z38 = 0, "", 1-Z38/$O38) | AB38: =IF($O38 = "", "", AD$18) | AC38: =IF($O38="","",AD$20) | AD38: 31.79 | AE38: =IF(AD38 = 0, "", 1-AD38/$O38) | AF38: =IF($O38 = "", "", AH$18) | AG38: =IF($O38="","",AH$20) | AH38: 29.34 | AI38: =IF(AH38 = 0, "", 1-AH38/$O38) | AJ38: =IF($O38 = "", "", AL$18) | AK38: =IF($O38="","",AL$20) | AL38: 36.68 | AM38: =IF(AL38 = 0, "", 1-AL38/$O38) | AN38: =IF($O38 = "", "", AP$18) | AO38: =IF($O38="","",AP$20) | AP38: 34.23 | AQ38: =IF(AP38 = 0, "", 1-AP38/$O38) | AR38: =IF($O38 = "", "", AT$18) | AS38: =IF($O38="","",AT$20) | AT38: 31.79 | AU38: =IF(AT38 = 0, "", 1-AT38/$O38) | AV38: =IF($O38 = "", "", AX$18) | AW38: =IF($O38="","",AX$20) | AX38: 34.23 | AY38: =IF(AX38 = 0, "", 1-AX38/$O38) | AZ38: =IF($O38 = "", "", BB$18) | BA38: =IF($O38="","",BB$20) | BB38: 31.79 | BC38: =IF(BB38 = 0, "", 1-BB38/$O38) | BD38: =IF($O38 = "", "", BF$18) | BE38: =IF($O38="","",BF$20) | BF38: 29.34 | BG38: =IF(BF38 = 0, "", 1-BF38/$O38) | BH38: =IF($O38 = "", "", BJ$18) | BI38: =IF($O38="","",BJ$20) | BL38: =IF($O38 = "", "", BN$18) | BM38: =IF($O38="","",BN$20) | BO38: =IF(BN38 = 0, "", 1-BN38/$O38) | BP38: =IF($O38 = "", "", BR$18) | BQ38: =IF($O38="","",BR$20) | BS38: =IF(BR38 = 0, "", 1-BR38/$O38)
B39: 3600523192687 | C39: LO533HBAD3DH06ANMY-250824334 | D39: 251680470 | F39: L'Oreal Paris Magic Retouch Instant Root Concealer Spray Cover Greys Roots (Hair Colouring & Hair Care) | N39: Single | O39: 48.9 | P39: =IF($O39 = "", "", R$18) | Q39: =IF($O39="","",R$20) | R39: 39.12 | S39: =IF(R39 = 0, "", 1-R39/$O39) | T39: =IF($O39 = "", "", V$18) | U39: =IF($O39="","",V$20) | V39: 34.23 | W39: =IF(V39 = 0, "", 1-V39/$O39) | X39: =IF($O39 = "", "", Z$18) | Y39: =IF($O39="","",Z$20) | Z39: 34.23 | AA39: =IF(Z39 = 0, "", 1-Z39/$O39) | AB39: =IF($O39 = "", "", AD$18) | AC39: =IF($O39="","",AD$20) | AD39: 31.79 | AE39: =IF(AD39 = 0, "", 1-AD39/$O39) | AF39: =IF($O39 = "", "", AH$18) | AG39: =IF($O39="","",AH$20) | AH39: 29.34 | AI39: =IF(AH39 = 0, "", 1-AH39/$O39) | AJ39: =IF($O39 = "", "", AL$18) | AK39: =IF($O39="","",AL$20) | AL39: 36.68 | AM39: =IF(AL39 = 0, "", 1-AL39/$O39) | AN39: =IF($O39 = "", "", AP$18) | AO39: =IF($O39="","",AP$20) | AP39: 34.23 | AQ39: =IF(AP39 = 0, "", 1-AP39/$O39) | AR39: =IF($O39 = "", "", AT$18) | AS39: =IF($O39="","",AT$20) | AT39: 31.79 | AU39: =IF(AT39 = 0, "", 1-AT39/$O39) | AV39: =IF($O39 = "", "", AX$18) | AW39: =IF($O39="","",AX$20) | AX39: 34.23 | AY39: =IF(AX39 = 0, "", 1-AX39/$O39) | AZ39: =IF($O39 = "", "", BB$18) | BA39: =IF($O39="","",BB$20) | BB39: 31.79 | BC39: =IF(BB39 = 0, "", 1-BB39/$O39) | BD39: =IF($O39 = "", "", BF$18) | BE39: =IF($O39="","",BF$20) | BF39: 29.34 | BG39: =IF(BF39 = 0, "", 1-BF39/$O39) | BH39: =IF($O39 = "", "", BJ$18) | BI39: =IF($O39="","",BJ$20) | BL39: =IF($O39 = "", "", BN$18) | BM39: =IF($O39="","",BN$20) | BO39: =IF(BN39 = 0, "", 1-BN39/$O39) | BP39: =IF($O39 = "", "", BR$18) | BQ39: =IF($O39="","",BR$20) | BS39: =IF(BR39 = 0, "", 1-BR39/$O39)
B40: 3600523192694 | C40: LO533HBAD3DGX1ANMY-250824237 | D40: 251680470 | F40: L'Oreal Paris Magic Retouch Instant Root Concealer Spray Cover Greys Roots (Hair Colouring & Hair Care) | N40: Single | O40: 48.9 | P40: =IF($O40 = "", "", R$18) | Q40: =IF($O40="","",R$20) | R40: 39.12 | S40: =IF(R40 = 0, "", 1-R40/$O40) | T40: =IF($O40 = "", "", V$18) | U40: =IF($O40="","",V$20) | V40: 34.23 | W40: =IF(V40 = 0, "", 1-V40/$O40) | X40: =IF($O40 = "", "", Z$18) | Y40: =IF($O40="","",Z$20) | Z40: 34.23 | AA40: =IF(Z40 = 0, "", 1-Z40/$O40) | AB40: =IF($O40 = "", "", AD$18) | AC40: =IF($O40="","",AD$20) | AD40: 31.79 | AE40: =IF(AD40 = 0, "", 1-AD40/$O40) | AF40: =IF($O40 = "", "", AH$18) | AG40: =IF($O40="","",AH$20) | AH40: 29.34 | AI40: =IF(AH40 = 0, "", 1-AH40/$O40) | AJ40: =IF($O40 = "", "", AL$18) | AK40: =IF($O40="","",AL$20) | AL40: 36.68 | AM40: =IF(AL40 = 0, "", 1-AL40/$O40) | AN40: =IF($O40 = "", "", AP$18) | AO40: =IF($O40="","",AP$20) | AP40: 34.23 | AQ40: =IF(AP40 = 0, "", 1-AP40/$O40) | AR40: =IF($O40 = "", "", AT$18) | AS40: =IF($O40="","",AT$20) | AT40: 31.79 | AU40: =IF(AT40 = 0, "", 1-AT40/$O40) | AV40: =IF($O40 = "", "", AX$18) | AW40: =IF($O40="","",AX$20) | AX40: 34.23 | AY40: =IF(AX40 = 0, "", 1-AX40/$O40) | AZ40: =IF($O40 = "", "", BB$18) | BA40: =IF($O40="","",BB$20) | BB40: 31.79 | BC40: =IF(BB40 = 0, "", 1-BB40/$O40) | BD40: =IF($O40 = "", "", BF$18) | BE40: =IF($O40="","",BF$20) | BF40: 29.34 | BG40: =IF(BF40 = 0, "", 1-BF40/$O40) | BH40: =IF($O40 = "", "", BJ$18) | BI40: =IF($O40="","",BJ$20) | BL40: =IF($O40 = "", "", BN$18) | BM40: =IF($O40="","",BN$20) | BO40: =IF(BN40 = 0, "", 1-BN40/$O40) | BP40: =IF($O40 = "", "", BR$18) | BQ40: =IF($O40="","",BR$20) | BS40: =IF(BR40 = 0, "", 1-BR40/$O40)
B41: 9557534804594 | C41: 4539216028_MY-25638519620 | D41: 4539216028 | F41: L'Oréal Paris Revitalift Advanced Anti-Wrinkle Firming Day + Night Cream 50ml Bundle | N41: VBOM | O41: 205.8 | P41: =IF($O41 = "", "", R$18) | Q41: =IF($O41="","",R$20) | R41: 154.35 | S41: =IF(R41 = 0, "", 1-R41/$O41) | T41: =IF($O41 = "", "", V$18) | U41: =IF($O41="","",V$20) | V41: 133.77 | W41: =IF(V41 = 0, "", 1-V41/$O41) | X41: =IF($O41 = "", "", Z$18) | Y41: =IF($O41="","",Z$20) | Z41: 133.77 | AA41: =IF(Z41 = 0, "", 1-Z41/$O41) | AB41: =IF($O41 = "", "", AD$18) | AC41: =IF($O41="","",AD$20) | AD41: 123.48 | AE41: =IF(AD41 = 0, "", 1-AD41/$O41) | AF41: =IF($O41 = "", "", AH$18) | AG41: =IF($O41="","",AH$20) | AH41: 113.19 | AI41: =IF(AH41 = 0, "", 1-AH41/$O41) | AJ41: =IF($O41 = "", "", AL$18) | AK41: =IF($O41="","",AL$20) | AL41: 144.06 | AM41: =IF(AL41 = 0, "", 1-AL41/$O41) | AN41: =IF($O41 = "", "", AP$18) | AO41: =IF($O41="","",AP$20) | AP41: 133.77 | AQ41: =IF(AP41 = 0, "", 1-AP41/$O41) | AR41: =IF($O41 = "", "", AT$18) | AS41: =IF($O41="","",AT$20) | AT41: 123.48 | AU41: =IF(AT41 = 0, "", 1-AT41/$O41) | AV41: =IF($O41 = "", "", AX$18) | AW41: =IF($O41="","",AX$20) | AX41: 133.77 | AY41: =IF(AX41 = 0, "", 1-AX41/$O41) | AZ41: =IF($O41 = "", "", BB$18) | BA41: =IF($O41="","",BB$20) | BB41: 123.48 | BC41: =IF(BB41 = 0, "", 1-BB41/$O41) | BD41: =IF($O41 = "", "", BF$18) | BE41: =IF($O41="","",BF$20) | BF41: 113.19 | BG41: =IF(BF41 = 0, "", 1-BF41/$O41) | BH41: =IF($O41 = "", "", BJ$18) | BI41: =IF($O41="","",BJ$20) | BL41: =IF($O41 = "", "", BN$18) | BM41: =IF($O41="","",BN$20) | BO41: =IF(BN41 = 0, "", 1-BN41/$O41) | BP41: =IF($O41 = "", "", BR$18) | BQ41: =IF($O41="","",BR$20) | BS41: =IF(BR41 = 0, "", 1-BR41/$O41)
B42: 9557534812414 | C42: 4685038185_MY-26274096320 | D42: 4685038185 | F42: L'Oréal Paris Infallible Pro-Cover Cushion 24H Longwear Foundation 14g + Refill, Coverage Moisture and Oil Control | N42: Single | O42: 129.9 | P42: =IF($O42 = "", "", R$18) | Q42: =IF($O42="","",R$20) | R42: 103.92 | S42: =IF(R42 = 0, "", 1-R42/$O42) | T42: =IF($O42 = "", "", V$18) | U42: =IF($O42="","",V$20) | V42: 90.93 | W42: =IF(V42 = 0, "", 1-V42/$O42) | X42: =IF($O42 = "", "", Z$18) | Y42: =IF($O42="","",Z$20) | Z42: 97.425 | AA42: =IF(Z42 = 0, "", 1-Z42/$O42) | AB42: =IF($O42 = "", "", AD$18) | AC42: =IF($O42="","",AD$20) | AD42: 90.93 | AE42: =IF(AD42 = 0, "", 1-AD42/$O42) | AF42: =IF($O42 = "", "", AH$18) | AG42: =IF($O42="","",AH$20) | AH42: 84.435 | AI42: =IF(AH42 = 0, "", 1-AH42/$O42) | AJ42: =IF($O42 = "", "", AL$18) | AK42: =IF($O42="","",AL$20) | AL42: 97.43 | AM42: =IF(AL42 = 0, "", 1-AL42/$O42) | AN42: =IF($O42 = "", "", AP$18) | AO42: =IF($O42="","",AP$20) | AP42: 90.93 | AQ42: =IF(AP42 = 0, "", 1-AP42/$O42) | AR42: =IF($O42 = "", "", AT$18) | AS42: =IF($O42="","",AT$20) | AT42: 84.44 | AU42: =IF(AT42 = 0, "", 1-AT42/$O42) | AV42: =IF($O42 = "", "", AX$18) | AW42: =IF($O42="","",AX$20) | AX42: 97.425 | AY42: =IF(AX42 = 0, "", 1-AX42/$O42) | AZ42: =IF($O42 = "", "", BB$18) | BA42: =IF($O42="","",BB$20) | BB42: 90.93 | BC42: =IF(BB42 = 0, "", 1-BB42/$O42) | BD42: =IF($O42 = "", "", BF$18) | BE42: =IF($O42="","",BF$20) | BF42: 84.435 | BG42: =IF(BF42 = 0, "", 1-BF42/$O42) | BH42: =IF($O42 = "", "", BJ$18) | BI42: =IF($O42="","",BJ$20) | BL42: =IF($O42 = "", "", BN$18) | BM42: =IF($O42="","",BN$20) | BO42: =IF(BN42 = 0, "", 1-BN42/$O42) | BP42: =IF($O42 = "", "", BR$18) | BQ42: =IF($O42="","",BR$20) | BS42: =IF(BR42 = 0, "", 1-BR42/$O42)
B43: 9557534812421 | C43: 4685038185_MY-26274096321 | D43: 4685038185 | F43: L'Oréal Paris Infallible Pro-Cover Cushion 24H Longwear Foundation 14g + Refill, Coverage Moisture and Oil Control | N43: Single | O43: 129.9 | P43: =IF($O43 = "", "", R$18) | Q43: =IF($O43="","",R$20) | R43: 103.92 | S43: =IF(R43 = 0, "", 1-R43/$O43) | T43: =IF($O43 = "", "", V$18) | U43: =IF($O43="","",V$20) | V43: 90.93 | W43: =IF(V43 = 0, "", 1-V43/$O43) | X43: =IF($O43 = "", "", Z$18) | Y43: =IF($O43="","",Z$20) | Z43: 97.425 | AA43: =IF(Z43 = 0, "", 1-Z43/$O43) | AB43: =IF($O43 = "", "", AD$18) | AC43: =IF($O43="","",AD$20) | AD43: 90.93 | AE43: =IF(AD43 = 0, "", 1-AD43/$O43) | AF43: =IF($O43 = "", "", AH$18) | AG43: =IF($O43="","",AH$20) | AH43: 84.435 | AI43: =IF(AH43 = 0, "", 1-AH43/$O43) | AJ43: =IF($O43 = "", "", AL$18) | AK43: =IF($O43="","",AL$20) | AL43: 97.43 | AM43: =IF(AL43 = 0, "", 1-AL43/$O43) | AN43: =IF($O43 = "", "", AP$18) | AO43: =IF($O43="","",AP$20) | AP43: 90.93 | AQ43: =IF(AP43 = 0, "", 1-AP43/$O43) | AR43: =IF($O43 = "", "", AT$18) | AS43: =IF($O43="","",AT$20) | AT43: 84.44 | AU43: =IF(AT43 = 0, "", 1-AT43/$O43) | AV43: =IF($O43 = "", "", AX$18) | AW43: =IF($O43="","",AX$20) | AX43: 97.425 | AY43: =IF(AX43 = 0, "", 1-AX43/$O43) | AZ43: =IF($O43 = "", "", BB$18) | BA43: =IF($O43="","",BB$20) | BB43: 90.93 | BC43: =IF(BB43 = 0, "", 1-BB43/$O43) | BD43: =IF($O43 = "", "", BF$18) | BE43: =IF($O43="","",BF$20) | BF43: 84.435 | BG43: =IF(BF43 = 0, "", 1-BF43/$O43) | BH43: =IF($O43 = "", "", BJ$18) | BI43: =IF($O43="","",BJ$20) | BL43: =IF($O43 = "", "", BN$18) | BM43: =IF($O43="","",BN$20) | BO43: =IF(BN43 = 0, "", 1-BN43/$O43) | BP43: =IF($O43 = "", "", BR$18) | BQ43: =IF($O43="","",BR$20) | BS43: =IF(BR43 = 0, "", 1-BR43/$O43)
B44: 9557534812438 | C44: 4685038185_MY-26274096322 | D44: 4685038185 | F44: L'Oréal Paris Infallible Pro-Cover Cushion 24H Longwear Foundation 14g + Refill, Coverage Moisture and Oil Control | N44: Single | O44: 129.9 | P44: =IF($O44 = "", "", R$18) | Q44: =IF($O44="","",R$20) | R44: 103.92 | S44: =IF(R44 = 0, "", 1-R44/$O44) | T44: =IF($O44 = "", "", V$18) | U44: =IF($O44="","",V$20) | V44: 90.93 | W44: =IF(V44 = 0, "", 1-V44/$O44) | X44: =IF($O44 = "", "", Z$18) | Y44: =IF($O44="","",Z$20) | Z44: 97.425 | AA44: =IF(Z44 = 0, "", 1-Z44/$O44) | AB44: =IF($O44 = "", "", AD$18) | AC44: =IF($O44="","",AD$20) | AD44: 90.93 | AE44: =IF(AD44 = 0, "", 1-AD44/$O44) | AF44: =IF($O44 = "", "", AH$18) | AG44: =IF($O44="","",AH$20) | AH44: 84.435 | AI44: =IF(AH44 = 0, "", 1-AH44/$O44) | AJ44: =IF($O44 = "", "", AL$18) | AK44: =IF($O44="","",AL$20) | AL44: 97.43 | AM44: =IF(AL44 = 0, "", 1-AL44/$O44) | AN44: =IF($O44 = "", "", AP$18) | AO44: =IF($O44="","",AP$20) | AP44: 90.93 | AQ44: =IF(AP44 = 0, "", 1-AP44/$O44) | AR44: =IF($O44 = "", "", AT$18) | AS44: =IF($O44="","",AT$20) | AT44: 84.44 | AU44: =IF(AT44 = 0, "", 1-AT44/$O44) | AV44: =IF($O44 = "", "", AX$18) | AW44: =IF($O44="","",AX$20) | AX44: 97.425 | AY44: =IF(AX44 = 0, "", 1-AX44/$O44) | AZ44: =IF($O44 = "", "", BB$18) | BA44: =IF($O44="","",BB$20) | BB44: 90.93 | BC44: =IF(BB44 = 0, "", 1-BB44/$O44) | BD44: =IF($O44 = "", "", BF$18) | BE44: =IF($O44="","",BF$20) | BF44: 84.435 | BG44: =IF(BF44 = 0, "", 1-BF44/$O44) | BH44: =IF($O44 = "", "", BJ$18) | BI44: =IF($O44="","",BJ$20) | BL44: =IF($O44 = "", "", BN$18) | BM44: =IF($O44="","",BN$20) | BO44: =IF(BN44 = 0, "", 1-BN44/$O44) | BP44: =IF($O44 = "", "", BR$18) | BQ44: =IF($O44="","",BR$20) | BS44: =IF(BR44 = 0, "", 1-BR44/$O44)
B45: 9557534812445 | C45: 4685038185_MY-26274096323 | D45: 4685038185 | F45: L'Oréal Paris Infallible Pro-Cover Cushion 24H Longwear Foundation 14g + Refill, Coverage Moisture and Oil Control | N45: Single | O45: 129.9 | P45: =IF($O45 = "", "", R$18) | Q45: =IF($O45="","",R$20) | R45: 103.92 | S45: =IF(R45 = 0, "", 1-R45/$O45) | T45: =IF($O45 = "", "", V$18) | U45: =IF($O45="","",V$20) | V45: 90.93 | W45: =IF(V45 = 0, "", 1-V45/$O45) | X45: =IF($O45 = "", "", Z$18) | Y45: =IF($O45="","",Z$20) | Z45: 97.425 | AA45: =IF(Z45 = 0, "", 1-Z45/$O45) | AB45: =IF($O45 = "", "", AD$18) | AC45: =IF($O45="","",AD$20) | AD45: 90.93 | AE45: =IF(AD45 = 0, "", 1-AD45/$O45) | AF45: =IF($O45 = "", "", AH$18) | AG45: =IF($O45="","",AH$20) | AH45: 84.435 | AI45: =IF(AH45 = 0, "", 1-AH45/$O45) | AJ45: =IF($O45 = "", "", AL$18) | AK45: =IF($O45="","",AL$20) | AL45: 97.43 | AM45: =IF(AL45 = 0, "", 1-AL45/$O45) | AN45: =IF($O45 = "", "", AP$18) | AO45: =IF($O45="","",AP$20) | AP45: 90.93 | AQ45: =IF(AP45 = 0, "", 1-AP45/$O45) | AR45: =IF($O45 = "", "", AT$18) | AS45: =IF($O45="","",AT$20) | AT45: 84.44 | AU45: =IF(AT45 = 0, "", 1-AT45/$O45) | AV45: =IF($O45 = "", "", AX$18) | AW45: =IF($O45="","",AX$20) | AX45: 97.425 | AY45: =IF(AX45 = 0, "", 1-AX45/$O45) | AZ45: =IF($O45 = "", "", BB$18) | BA45: =IF($O45="","",BB$20) | BB45: 90.93 | BC45: =IF(BB45 = 0, "", 1-BB45/$O45) | BD45: =IF($O45 = "", "", BF$18) | BE45: =IF($O45="","",BF$20) | BF45: 84.435 | BG45: =IF(BF45 = 0, "", 1-BF45/$O45) | BH45: =IF($O45 = "", "", BJ$18) | BI45: =IF($O45="","",BJ$20) | BL45: =IF($O45 = "", "", BN$18) | BM45: =IF($O45="","",BN$20) | BO45: =IF(BN45 = 0, "", 1-BN45/$O45) | BP45: =IF($O45 = "", "", BR$18) | BQ45: =IF($O45="","",BR$20) | BS45: =IF(BR45 = 0, "", 1-BR45/$O45)
B46: 8992304016776 | C46: 11513596_MY-1802898840 | D46: 11513596 | F46: L'Oreal Paris Revitalift Anti Aging Day Cream SPF35 (50ml/20ml) | N46: Single | O46: 35.9 | P46: =IF($O46 = "", "", R$18) | Q46: =IF($O46="","",R$20) | R46: 28.72 | S46: =IF(R46 = 0, "", 1-R46/$O46) | T46: =IF($O46 = "", "", V$18) | U46: =IF($O46="","",V$20) | V46: 25.13 | W46: =IF(V46 = 0, "", 1-V46/$O46) | X46: =IF($O46 = "", "", Z$18) | Y46: =IF($O46="","",Z$20) | Z46: 32.31 | AA46: =IF(Z46 = 0, "", 1-Z46/$O46) | AB46: =IF($O46 = "", "", AD$18) | AC46: =IF($O46="","",AD$20) | AD46: 30.52 | AE46: =IF(AD46 = 0, "", 1-AD46/$O46) | AF46: =IF($O46 = "", "", AH$18) | AG46: =IF($O46="","",AH$20) | AH46: 28.72 | AI46: =IF(AH46 = 0, "", 1-AH46/$O46) | AJ46: =IF($O46 = "", "", AL$18) | AK46: =IF($O46="","",AL$20) | AL46: 26.93 | AM46: =IF(AL46 = 0, "", 1-AL46/$O46) | AN46: =IF($O46 = "", "", AP$18) | AO46: =IF($O46="","",AP$20) | AP46: 25.13 | AQ46: =IF(AP46 = 0, "", 1-AP46/$O46) | AR46: =IF($O46 = "", "", AT$18) | AS46: =IF($O46="","",AT$20) | AT46: 23.34 | AU46: =IF(AT46 = 0, "", 1-AT46/$O46) | AV46: =IF($O46 = "", "", AX$18) | AW46: =IF($O46="","",AX$20) | AX46: 32.31 | AY46: =IF(AX46 = 0, "", 1-AX46/$O46) | AZ46: =IF($O46 = "", "", BB$18) | BA46: =IF($O46="","",BB$20) | BB46: 30.52 | BC46: =IF(BB46 = 0, "", 1-BB46/$O46) | BD46: =IF($O46 = "", "", BF$18) | BE46: =IF($O46="","",BF$20) | BF46: 28.72 | BG46: =IF(BF46 = 0, "", 1-BF46/$O46) | BH46: =IF($O46 = "", "", BJ$18) | BI46: =IF($O46="","",BJ$20) | BK46: =IF(BJ46 = 0, "", 1-BJ46/$O46) | BL46: =IF($O46 = "", "", BN$18) | BM46: =IF($O46="","",BN$20) | BO46: =IF(BN46 = 0, "", 1-BN46/$O46) | BP46: =IF($O46 = "", "", BR$18) | BQ46: =IF($O46="","",BR$20) | BS46: =IF(BR46 = 0, "", 1-BR46/$O46)
B47: 8992304017827 | C47: LO533HBAA5WX7EANMY-12060019 | D47: 11513596 | F47: L'Oreal Paris Revitalift Anti Aging Day Cream SPF35 (50ml/20ml) | N47: Single | O47: 76.9 | P47: =IF($O47 = "", "", R$18) | Q47: =IF($O47="","",R$20) | R47: 61.52 | S47: =IF(R47 = 0, "", 1-R47/$O47) | T47: =IF($O47 = "", "", V$18) | U47: =IF($O47="","",V$20) | V47: 53.83 | W47: =IF(V47 = 0, "", 1-V47/$O47) | X47: =IF($O47 = "", "", Z$18) | Y47: =IF($O47="","",Z$20) | Z47: 53.83 | AA47: =IF(Z47 = 0, "", 1-Z47/$O47) | AB47: =IF($O47 = "", "", AD$18) | AC47: =IF($O47="","",AD$20) | AD47: 49.99 | AE47: =IF(AD47 = 0, "", 1-AD47/$O47) | AF47: =IF($O47 = "", "", AH$18) | AG47: =IF($O47="","",AH$20) | AH47: 46.14 | AI47: =IF(AH47 = 0, "", 1-AH47/$O47) | AJ47: =IF($O47 = "", "", AL$18) | AK47: =IF($O47="","",AL$20) | AL47: 57.68 | AM47: =IF(AL47 = 0, "", 1-AL47/$O47) | AN47: =IF($O47 = "", "", AP$18) | AO47: =IF($O47="","",AP$20) | AP47: 53.83 | AQ47: =IF(AP47 = 0, "", 1-AP47/$O47) | AR47: =IF($O47 = "", "", AT$18) | AS47: =IF($O47="","",AT$20) | AT47: 49.99 | AU47: =IF(AT47 = 0, "", 1-AT47/$O47) | AV47: =IF($O47 = "", "", AX$18) | AW47: =IF($O47="","",AX$20) | AX47: 53.83 | AY47: =IF(AX47 = 0, "", 1-AX47/$O47) | AZ47: =IF($O47 = "", "", BB$18) | BA47: =IF($O47="","",BB$20) | BB47: 49.99 | BC47: =IF(BB47 = 0, "", 1-BB47/$O47) | BD47: =IF($O47 = "", "", BF$18) | BE47: =IF($O47="","",BF$20) | BF47: 46.14 | BG47: =IF(BF47 = 0, "", 1-BF47/$O47) | BH47: =IF($O47 = "", "", BJ$18) | BI47: =IF($O47="","",BJ$20) | BK47: =IF(BJ47 = 0, "", 1-BJ47/$O47) | BL47: =IF($O47 = "", "", BN$18) | BM47: =IF($O47="","",BN$20) | BO47: =IF(BN47 = 0, "", 1-BN47/$O47) | BP47: =IF($O47 = "", "", BR$18) | BQ47: =IF($O47="","",BR$20) | BS47: =IF(BR47 = 0, "", 1-BR47/$O47)
B48: 9557534803054 | C48: 4532434218_MY-25602908225 | D48: 4532434218 | F48: L’Oréal Paris Elseve Hyaluron Pure 72H Purifying Shampoo Rehydrating Conditioner for Hydrated Hair Bundles | N48: VBOM | O48: 66.8 | P48: =IF($O48 = "", "", R$18) | Q48: =IF($O48="","",R$20) | R48: 50.1 | S48: =IF(R48 = 0, "", 1-R48/$O48) | T48: =IF($O48 = "", "", V$18) | U48: =IF($O48="","",V$20) | V48: 43.42 | W48: =IF(V48 = 0, "", 1-V48/$O48) | X48: =IF($O48 = "", "", Z$18) | Y48: =IF($O48="","",Z$20) | Z48: 43.42 | AA48: =IF(Z48 = 0, "", 1-Z48/$O48) | AB48: =IF($O48 = "", "", AD$18) | AC48: =IF($O48="","",AD$20) | AD48: 40.08 | AE48: =IF(AD48 = 0, "", 1-AD48/$O48) | AF48: =IF($O48 = "", "", AH$18) | AG48: =IF($O48="","",AH$20) | AH48: 36.74 | AI48: =IF(AH48 = 0, "", 1-AH48/$O48) | AJ48: =IF($O48 = "", "", AL$18) | AK48: =IF($O48="","",AL$20) | AL48: 46.76 | AM48: =IF(AL48 = 0, "", 1-AL48/$O48) | AN48: =IF($O48 = "", "", AP$18) | AO48: =IF($O48="","",AP$20) | AP48: 43.42 | AQ48: =IF(AP48 = 0, "", 1-AP48/$O48) | AR48: =IF($O48 = "", "", AT$18) | AS48: =IF($O48="","",AT$20) | AT48: 40.08 | AU48: =IF(AT48 = 0, "", 1-AT48/$O48) | AV48: =IF($O48 = "", "", AX$18) | AW48: =IF($O48="","",AX$20) | AX48: 43.42 | AY48: =IF(AX48 = 0, "", 1-AX48/$O48) | AZ48: =IF($O48 = "", "", BB$18) | BA48: =IF($O48="","",BB$20) | BB48: 40.08 | BC48: =IF(BB48 = 0, "", 1-BB48/$O48) | BD48: =IF($O48 = "", "", BF$18) | BE48: =IF($O48="","",BF$20) | BF48: 36.74 | BG48: =IF(BF48 = 0, "", 1-BF48/$O48) | BH48: =IF($O48 = "", "", BJ$18) | BI48: =IF($O48="","",BJ$20) | BK48: =IF(BJ48 = 0, "", 1-BJ48/$O48) | BL48: =IF($O48 = "", "", BN$18) | BM48: =IF($O48="","",BN$20) | BO48: =IF(BN48 = 0, "", 1-BN48/$O48) | BP48: =IF($O48 = "", "", BR$18) | BQ48: =IF($O48="","",BR$20) | BS48: =IF(BR48 = 0, "", 1-BR48/$O48)
B49: 9557534804488 | C49: 4532434218_MY-25602908226 | D49: 4532434218 | F49: L’Oréal Paris Elseve Hyaluron Pure 72H Purifying Shampoo Rehydrating Conditioner for Hydrated Hair Bundles | N49: VBOM | O49: 79.8 | P49: =IF($O49 = "", "", R$18) | Q49: =IF($O49="","",R$20) | R49: 59.85 | S49: =IF(R49 = 0, "", 1-R49/$O49) | T49: =IF($O49 = "", "", V$18) | U49: =IF($O49="","",V$20) | V49: 51.87 | W49: =IF(V49 = 0, "", 1-V49/$O49) | X49: =IF($O49 = "", "", Z$18) | Y49: =IF($O49="","",Z$20) | Z49: 51.87 | AA49: =IF(Z49 = 0, "", 1-Z49/$O49) | AB49: =IF($O49 = "", "", AD$18) | AC49: =IF($O49="","",AD$20) | AD49: 47.88 | AE49: =IF(AD49 = 0, "", 1-AD49/$O49) | AF49: =IF($O49 = "", "", AH$18) | AG49: =IF($O49="","",AH$20) | AH49: 43.89 | AI49: =IF(AH49 = 0, "", 1-AH49/$O49) | AJ49: =IF($O49 = "", "", AL$18) | AK49: =IF($O49="","",AL$20) | AL49: 55.86 | AM49: =IF(AL49 = 0, "", 1-AL49/$O49) | AN49: =IF($O49 = "", "", AP$18) | AO49: =IF($O49="","",AP$20) | AP49: 51.87 | AQ49: =IF(AP49 = 0, "", 1-AP49/$O49) | AR49: =IF($O49 = "", "", AT$18) | AS49: =IF($O49="","",AT$20) | AT49: 47.88 | AU49: =IF(AT49 = 0, "", 1-AT49/$O49) | AV49: =IF($O49 = "", "", AX$18) | AW49: =IF($O49="","",AX$20) | AX49: 51.87 | AY49: =IF(AX49 = 0, "", 1-AX49/$O49) | AZ49: =IF($O49 = "", "", BB$18) | BA49: =IF($O49="","",BB$20) | BB49: 47.88 | BC49: =IF(BB49 = 0, "", 1-BB49/$O49) | BD49: =IF($O49 = "", "", BF$18) | BE49: =IF($O49="","",BF$20) | BF49: 43.89 | BG49: =IF(BF49 = 0, "", 1-BF49/$O49) | BH49: =IF($O49 = "", "", BJ$18) | BI49: =IF($O49="","",BJ$20) | BK49: =IF(BJ49 = 0, "", 1-BJ49/$O49) | BL49: =IF($O49 = "", "", BN$18) | BM49: =IF($O49="","",BN$20) | BO49: =IF(BN49 = 0, "", 1-BN49/$O49) | BP49: =IF($O49 = "", "", BR$18) | BQ49: =IF($O49="","",BR$20) | BS49: =IF(BR49 = 0, "", 1-BR49/$O49)
B50: 9557534803047 | C50: 4532434218_MY-25602976550 | D50: 4532434218 | F50: L’Oréal Paris Elseve Hyaluron Pure 72H Purifying Shampoo Rehydrating Conditioner for Hydrated Hair Bundles | N50: VBOM | O50: 53.8 | P50: =IF($O50 = "", "", R$18) | Q50: =IF($O50="","",R$20) | R50: 40.35 | S50: =IF(R50 = 0, "", 1-R50/$O50) | T50: =IF($O50 = "", "", V$18) | U50: =IF($O50="","",V$20) | V50: 34.97 | W50: =IF(V50 = 0, "", 1-V50/$O50) | X50: =IF($O50 = "", "", Z$18) | Y50: =IF($O50="","",Z$20) | Z50: 34.97 | AA50: =IF(Z50 = 0, "", 1-Z50/$O50) | AB50: =IF($O50 = "", "", AD$18) | AC50: =IF($O50="","",AD$20) | AD50: 32.28 | AE50: =IF(AD50 = 0, "", 1-AD50/$O50) | AF50: =IF($O50 = "", "", AH$18) | AG50: =IF($O50="","",AH$20) | AH50: 29.59 | AI50: =IF(AH50 = 0, "", 1-AH50/$O50) | AJ50: =IF($O50 = "", "", AL$18) | AK50: =IF($O50="","",AL$20) | AL50: 37.66 | AM50: =IF(AL50 = 0, "", 1-AL50/$O50) | AN50: =IF($O50 = "", "", AP$18) | AO50: =IF($O50="","",AP$20) | AP50: 34.97 | AQ50: =IF(AP50 = 0, "", 1-AP50/$O50) | AR50: =IF($O50 = "", "", AT$18) | AS50: =IF($O50="","",AT$20) | AT50: 32.28 | AU50: =IF(AT50 = 0, "", 1-AT50/$O50) | AV50: =IF($O50 = "", "", AX$18) | AW50: =IF($O50="","",AX$20) | AX50: 34.97 | AY50: =IF(AX50 = 0, "", 1-AX50/$O50) | AZ50: =IF($O50 = "", "", BB$18) | BA50: =IF($O50="","",BB$20) | BB50: 32.28 | BC50: =IF(BB50 = 0, "", 1-BB50/$O50) | BD50: =IF($O50 = "", "", BF$18) | BE50: =IF($O50="","",BF$20) | BF50: 29.59 | BG50: =IF(BF50 = 0, "", 1-BF50/$O50) | BH50: =IF($O50 = "", "", BJ$18) | BI50: =IF($O50="","",BJ$20) | BK50: =IF(BJ50 = 0, "", 1-BJ50/$O50) | BL50: =IF($O50 = "", "", BN$18) | BM50: =IF($O50="","",BN$20) | BO50: =IF(BN50 = 0, "", 1-BN50/$O50) | BP50: =IF($O50 = "", "", BR$18) | BQ50: =IF($O50="","",BR$20) | BS50: =IF(BR50 = 0, "", 1-BR50/$O50)
B51: 9557534803061 | C51: 4532434218_MY-25602976549 | D51: 4532434218 | F51: L’Oréal Paris Elseve Hyaluron Pure 72H Purifying Shampoo Rehydrating Conditioner for Hydrated Hair Bundles | N51: VBOM | O51: 41.8 | P51: =IF($O51 = "", "", R$18) | Q51: =IF($O51="","",R$20) | R51: 31.35 | S51: =IF(R51 = 0, "", 1-R51/$O51) | T51: =IF($O51 = "", "", V$18) | U51: =IF($O51="","",V$20) | V51: 27.17 | W51: =IF(V51 = 0, "", 1-V51/$O51) | X51: =IF($O51 = "", "", Z$18) | Y51: =IF($O51="","",Z$20) | Z51: 27.17 | AA51: =IF(Z51 = 0, "", 1-Z51/$O51) | AB51: =IF($O51 = "", "", AD$18) | AC51: =IF($O51="","",AD$20) | AD51: 25.08 | AE51: =IF(AD51 = 0, "", 1-AD51/$O51) | AF51: =IF($O51 = "", "", AH$18) | AG51: =IF($O51="","",AH$20) | AH51: 22.99 | AI51: =IF(AH51 = 0, "", 1-AH51/$O51) | AJ51: =IF($O51 = "", "", AL$18) | AK51: =IF($O51="","",AL$20) | AL51: 29.26 | AM51: =IF(AL51 = 0, "", 1-AL51/$O51) | AN51: =IF($O51 = "", "", AP$18) | AO51: =IF($O51="","",AP$20) | AP51: 27.17 | AQ51: =IF(AP51 = 0, "", 1-AP51/$O51) | AR51: =IF($O51 = "", "", AT$18) | AS51: =IF($O51="","",AT$20) | AT51: 25.08 | AU51: =IF(AT51 = 0, "", 1-AT51/$O51) | AV51: =IF($O51 = "", "", AX$18) | AW51: =IF($O51="","",AX$20) | AX51: 27.17 | AY51: =IF(AX51 = 0, "", 1-AX51/$O51) | AZ51: =IF($O51 = "", "", BB$18) | BA51: =IF($O51="","",BB$20) | BB51: 25.08 | BC51: =IF(BB51 = 0, "", 1-BB51/$O51) | BD51: =IF($O51 = "", "", BF$18) | BE51: =IF($O51="","",BF$20) | BF51: 22.99 | BG51: =IF(BF51 = 0, "", 1-BF51/$O51) | BH51: =IF($O51 = "", "", BJ$18) | BI51: =IF($O51="","",BJ$20) | BK51: =IF(BJ51 = 0, "", 1-BJ51/$O51) | BL51: =IF($O51 = "", "", BN$18) | BM51: =IF($O51="","",BN$20) | BO51: =IF(BN51 = 0, "", 1-BN51/$O51) | BP51: =IF($O51 = "", "", BR$18) | BQ51: =IF($O51="","",BR$20) | BS51: =IF(BR51 = 0, "", 1-BR51/$O51)
